Workbook

Sheet Входные данные
A1: Модель этапа 1 HomePrice.uz v0.1 — Входные данные
A2: Единицы: сум, если не указано иное. Формулы других листов читают только этот лист. Ячейка «База» (столбец F) — то, что вы вводите; «Пессимист» и «Оптимист» берутся из неё, если не заданы отдельно.
A4: Цветовая разметка
B5: [факт] — известно из документов или от владельца (18.10.2026)
B6: [гипотеза] — предположение; часть помечена [проверить]
B7: [заглушка] — временное значение до данных (market_sizing.xlsx и др.), не оценка
B8: нужно от Темура — пусто, пока нет данных; модель считает пустое как 0 и сообщает об этом в листе «Проверка»
B9: [выбор] — переключатель модели
B10: Статус проверки модели: | C10: =Проверка!C3 -> ФОРМУЛЫ ОК, НЕ ХВАТАЕТ ДАННЫХ ВЛАДЕЛЬЦА
A12: № | B12: Параметр | C12: Ед. | D12: Статус | E12: Пессимист | F12: База | G12: Оптимист | H12: Источник | I12: Комментарий / что нужно
A13: A. Цена и срок отчёта уровня 3
A14: P01 | B14: Цена отчёта уровня 3 (KMT), средний чек | C14: сум | D14: [факт] | E14: =IF(F14="","",F14) -> 1000000 | F14: 1000000 | G14: =IF(F14="","",F14) -> 1000000 | H14: Владелец 18.10.2026; 05_4P; 02_Marketing_Context | I14: Входит ли НДС — см. строку ниже.
A15: P02 | B15: Срок отчёта | C15: дней | D15: [факт] | E15: =IF(F15="","",F15) -> 2 | F15: 2 | G15: =IF(F15="","",F15) -> 2 | H15: 05_4P; 02_Marketing_Context | I15: Цель — 1 день. В расчёте не используется.
A16: P03 | B16: Цена включает НДС? (1 = да, 0 = нет) | C16: 1/0 | D16: нужно от Темура | E16: =IF(F16="","",F16) | G16: =IF(F16="","",F16) | H16: 14_Rebaseline п.4.1 [проверить] | I16: Пусто = НДС не вычитается (выручка = цена). Вопрос Q8.
A17: P04 | B17: Ставка НДС | C17: % | D17: нужно от Темура | E17: =IF(F17="","",F17) | G17: =IF(F17="","",F17) | H17: — | I17: Ставку не подставляю: проверить действующую у бухгалтера или юриста. Вопрос Q8.
A18: P05 | B18: Курс сум за доллар (справочно) | C18: сум/$ | D18: [гипотеза][проверить] | E18: =IF(F18="","",F18) -> 12000 | F18: 12000 | G18: =IF(F18="","",F18) -> 12000 | H18: 05_4P, 14_Rebaseline п.4.1 | I18: Только для пересчёта допустимой стоимости привлечения в доллары. Проверить на дату.
A19: B. Маржа и прямые затраты одного заказа
A20: P06 | B20: Метод маржи (1 = процент владельца, 2 = построчно) | C20: 1/2 | D20: [выбор] | E20: =IF(F20="","",F20) -> 1 | F20: 1 | G20: =IF(F20="","",F20) -> 1 | H20: Решение модели | I20: Перейти на 2, когда будут данные по 20–30 заказам (Q1–Q3). При методе 2 с пустыми строками маржа = 100% — лист «Проверка» это отмечает.
A21: P07 | B21: Маржа (прибыль) заказа, % выручки | C21: % | D21: [гипотеза][проверить] | E21: 0.3 | F21: 0.5 | G21: 0.5 | H21: Владелец 18.10: прибыль ≈50% (его оценка). Пессимист 30% — заглушка из иллюстрации 14 п.4.1 (200–500 тыс. сум) | I21: Не проверено по заказам. Что входит в «прибыль» (оценщик, выезд, налоги, время администрации)? Q1.
A22: P08 | B22: Гонорар оценщика / выплата специалисту | C22: сум/заказ | D22: нужно от Темура | E22: =IF(F22="","",F22) | G22: =IF(F22="","",F22) | H22: — | I22: Только для метода 2. Q3.
A23: P09 | B23: Выезд (транспорт, время специалиста) | C23: сум/заказ | D23: нужно от Темура | E23: =IF(F23="","",F23) | G23: =IF(F23="","",F23) | H23: — | I23: Только для метода 2. Q2.
A24: P10 | B24: Проверка документов, подготовка и оформление отчёта | C24: сум/заказ | D24: нужно от Темура | E24: =IF(F24="","",F24) | G24: =IF(F24="","",F24) | H24: — | I24: Только для метода 2. Q3.
A25: P11 | B25: Налоги и сборы с заказа | C25: сум/заказ | D25: нужно от Темура | E25: =IF(F25="","",F25) | G25: =IF(F25="","",F25) | H25: — | I25: Только для метода 2. Q1, Q8.
A26: P12 | B26: Платёжные и банковские комиссии | C26: сум/заказ | D26: нужно от Темура | E26: =IF(F26="","",F26) | G26: =IF(F26="","",F26) | H26: — | I26: Только для метода 2. Q7.
A27: P13 | B27: Администрирование, связь, печать | C27: сум/заказ | D27: нужно от Темура | E27: =IF(F27="","",F27) | G27: =IF(F27="","",F27) | H27: — | I27: Только для метода 2. Q1.
A28: P14 | B28: Юридические и страховые расходы (ответственность оценщика) | C28: сум/заказ | D28: нужно от Темура | E28: =IF(F28="","",F28) | G28: =IF(F28="","",F28) | H28: Навык ценообразования: [проверить] | I28: Только для метода 2. Q1.
A29: C. Решения I1, D10 и партнёры
A30: P15 | B30: I1: кому идут заказы (1 = только KMT, 2 = гибрид: клиент партнёра остаётся партнёру) | C30: 1/2 | D30: [факт] | E30: =IF(F30="","",F30) -> 1 | F30: 1 | G30: =IF(F30="","",F30) -> 1 | H30: Владелец 18.10: базовый сценарий — заказы только в KMT | I30: Решение I1 за владельцем и не записано в 08. Оба варианта считаются рядом в листе D10_I1.
A31: P16 | B31: D10: что видит клиент после оценки (1 = блок KMT с контактами без формы, 2 = нейтральный текст) | C31: 1/2 | D31: [факт] | E31: =IF(F31="","",F31) -> 1 | F31: 1 | G31: =IF(F31="","",F31) -> 1 | H31: Владелец 18.10: блок KMT с контактами, заказ идёт в KMT, без формы до A4 | I31: Решение D10 за владельцем и не записано в 08. Оба варианта считаются рядом в листе D10_I1.
A32: P17 | B32: Доля маржи заказа, учитываемая проекту (100% = взгляд владельца на Bizzone и KMT вместе) | C32: % | D32: [гипотеза][проверить] | E32: =IF(F32="","",F32) -> 1 | F32: 1 | G32: =IF(F32="","",F32) -> 1 | H32: CLAUDE.md: проект ведёт Bizzone, KMT — партнёр; договор Bizzone–KMT в документах не описан | I32: Если маржа остаётся у KMT, у проекта как юрлица дохода нет. Q9.
A33: P18 | B33: Доля заказов от рекомендателей (банк, брокер) с вознаграждением | C33: % | D33: [гипотеза] | E33: =IF(F33="","",F33) -> 0 | F33: 0 | G33: =IF(F33="","",F33) -> 0 | H33: 14_Rebaseline п.4.3: вознаграждение за передачу клиента не вводить, пока юрист не ответил | I33: Ноль на этапе 1. Q7.
A34: P19 | B34: Вознаграждение рекомендателю, % от чека | C34: % | D34: [гипотеза] | E34: =IF(F34="","",F34) -> 0.15 | F34: 0.15 | G34: =IF(F34="","",F34) -> 0.15 | H34: 05_4P: 10–20% от чека (взята середина) | I34: Применяется к заказам через рекомендателя; на средний заказ — через долю выше.
A35: P20 | B35: I1 = гибрид: доля заказов, уходящая партнёру (клиент по ссылке или коду партнёра) | C35: % | D35: [заглушка] | E35: =IF(F35="","",F35) -> 0.2 | F35: 0.2 | G35: =IF(F35="","",F35) -> 0.2 | H35: — | I35: Данных нет, значение условное. Q14. См. сетку в «Чувствительность».
A36: P21 | B36: I1 = гибрид: плата проекту с заказа, переданного партнёру, % от чека | C36: % | D36: [гипотеза] | E36: =IF(F36="","",F36) -> 0 | F36: 0 | G36: =IF(F36="","",F36) -> 0 | H36: 14 п.4.3: без вознаграждения на этапе 1; 05_4P: 10–20% — для агрегатора (модель B) | I36: Ноль на этапе 1.
A37: P22 | B37: D10 = нейтральный текст: какая доля заказов сохраняется относительно блока KMT | C37: % | D37: [заглушка] | E37: =IF(F37="","",F37) -> 0.25 | F37: 0.25 | G37: =IF(F37="","",F37) -> 0.25 | H37: — | I37: Данных нет. Измерять по кликам на первых 100 результатах (14 п.4.2). Q14.
A38: D. Допустимое привлечение
A39: P23 | B39: Потолок доли маржи на привлечение | C39: % | D39: [гипотеза] | E39: =IF(F39="","",F39) -> 0.2 | F39: 0.2 | G39: =IF(F39="","",F39) -> 0.2 | H39: 14_Rebaseline п.4.1: рабочий потолок 20% маржи, только для расчётов | I39: Не измерено на этом рынке. Пересмотр на неделе 8–10.
A40: P24 | B40: Маркетинговый бюджет в месяц | C40: сум/мес | D40: [факт] | E40: =IF(F40="","",F40) -> 0 | F40: 0 | G40: =IF(F40="","",F40) -> 0 | H40: 08_Decisions п.5; 05_4P: бюджета нет | I40: Сумму микротестов определяет владелец (Q12).
A41: E. Воронка
A42: P25 | B42: Расчётов уровня 1 в месяц (в режиме) | C42: шт/мес | D42: [заглушка] | E42: 100 | F42: 300 | G42: 900 | H42: Заглушка до market_sizing.xlsx. Ориентир: порог ≥100 расчётов из 05/14 | I42: Не прогноз. Заменить данными market_sizing.xlsx. Q16.
A43: P26 | B43: Конверсия посетитель → расчёт | C43: % | D43: нужно от Темура | E43: =IF(F43="","",F43) | G43: =IF(F43="","",F43) | H43: Измерять (E2) | I43: Данных воронки нет. Пусто = число посетителей не считается.
A44: P27 | B44: Конверсия расчёт → интерес (контакт или клик по блоку KMT) | C44: % | D44: [гипотеза] | E44: 0.15 | F44: 0.2 | G44: 0.25 | H44: 05_4P: контакт 15–25% от ур.1 | I44: До A4 контактов нет: измеряется анонимным кликом по блоку KMT.
A45: P28 | B45: Конверсия интерес → заказ уровня 3 | C45: % | D45: [гипотеза] | E45: 0.02 | F45: 0.035 | G45: 0.05 | H45: 05_4P: заказ 2–5% от контакта | I45: Данных для Узбекистана нет (самокритика в 05).
A46: P29 | B46: Доля заказов, которых KMT не получил бы без HomePrice | C46: % | D46: [гипотеза][проверить] | E46: =IF(F46="","",F46) -> 1 | F46: 1 | G46: =IF(F46="","",F46) -> 1 | H46: — | I46: 100% — верхняя граница. Часть заказов KMT получает и так (налог на имущество). Q10.
A47: P30 | B47: Месяцев выхода на режим | C47: мес | D47: [гипотеза] | E47: =IF(F47="","",F47) -> 2 | F47: 2 | G47: =IF(F47="","",F47) -> 2 | H47: 05_4P: органика 6–8 недель | I47: Линейный рост объёма от 0 до режима.
A48: F. Постоянные операционные расходы (в месяц)
A49: P31 | B49: Хостинг и сервисы | C49: сум/мес | D49: [факт] | E49: =IF(F49="","",F49) -> 1000000 | F49: 1000000 | G49: =IF(F49="","",F49) -> 1000000 | H49: Владелец 18.10.2026 | I49: Что входит и с НДС ли — Q6.
A50: P32 | B50: SMS, колл-центр, платные сервисы, прочее | C50: сум/мес | D50: нужно от Темура | E50: =IF(F50="","",F50) | G50: =IF(F50="","",F50) | H50: Stage1_Plan L4 | I50: Q6.
A51: G. Часы команды и ставки
A52: P33 | B52: Единицы часов (1 = в неделю, 2 = в месяц, 3 = на весь этап 1) | C52: 1/2/3 | D52: нужно от Темура | E52: =IF(F52="","",F52) | G52: =IF(F52="","",F52) | H52: Владелец 18.10: «единицы времени уточнить» | I52: Пусто = стоимость труда не считается. Q4.
A53: P34 | B53: Длительность этапа 1 | C53: мес | D53: нужно от Темура | E53: =IF(F53="","",F53) | G53: =IF(F53="","",F53) | H53: — | I53: Нужна для пересчёта часов. Q11.
A54: P35 | B54: Часы: Темур | C54: ч/период | D54: [факт][проверить] | E54: 20 | F54: 17.5 | G54: 15 | H54: Владелец 18.10: 15–20 | I54: Диапазон владельца; пессимист = 20, оптимист = 15. Единицы неизвестны (Q4).
A55: P36 | B55: Часы: Равшан | C55: ч/период | D55: [факт][проверить] | E55: 20 | F55: 17.5 | G55: 15 | H55: Владелец 18.10: 15–20 | I55: Так же. Q4.
A56: P37 | B56: Часы: Азиз | C56: ч/период | D56: [факт][проверить] | E56: =IF(F56="","",F56) -> 50 | F56: 50 | G56: =IF(F56="","",F56) -> 50 | H56: Владелец 18.10: 50 | I56: Единицы неизвестны. Q4.
A57: P38 | B57: Ставка: Темур | C57: сум/час | D57: нужно от Темура | E57: =IF(F57="","",F57) | G57: =IF(F57="","",F57) | H57: Владелец: ставки не заданы | I57: Q5.
A58: P39 | B58: Ставка: Равшан | C58: сум/час | D58: нужно от Темура | E58: =IF(F58="","",F58) | G58: =IF(F58="","",F58) | H58: Владелец: ставки не заданы | I58: Q5.
A59: P40 | B59: Ставка: Азиз | C59: сум/час | D59: нужно от Темура | E59: =IF(F59="","",F59) | G59: =IF(F59="","",F59) | H59: Владелец: ставки не заданы | I59: Q5.
A60: P41 | B60: Доля часов Темура на разработку и запуск (разово) | C60: % | D60: [гипотеза] | E60: =IF(F60="","",F60) -> 0 | F60: 0 | G60: =IF(F60="","",F60) -> 0 | H60: — | I60: Остальное — постоянная работа (контент, интервью). Q4.
A61: P42 | B61: Доля часов Равшана на разработку и запуск (разово) | C61: % | D61: [гипотеза] | E61: =IF(F61="","",F61) -> 1 | F61: 1 | G61: =IF(F61="","",F61) -> 1 | H61: Stage1_Plan, блоки A и M: юридическая основа разовая | I61: Q4.
A62: P43 | B62: Доля часов Азиза на разработку и запуск (разово) | C62: % | D62: [гипотеза] | E62: =IF(F62="","",F62) -> 1 | F62: 1 | G62: =IF(F62="","",F62) -> 1 | H62: CLAUDE.md: главный программист | I62: Q4.
A63: H. Разовые расходы разработки и запуска (вне операционных)
A64: P44 | B64: Юрист (внешний), документы pd.gov.uz | C64: сум | D64: нужно от Темура | E64: =IF(F64="","",F64) | G64: =IF(F64="","",F64) | H64: Stage1_Plan L4 | I64: Q11.
A65: P45 | B65: Регистрация, пошлины, сертификаты | C65: сум | D65: нужно от Темура | E65: =IF(F65="","",F65) | G65: =IF(F65="","",F65) | H65: Stage1_Plan L4 | I65: Q11.
A66: P46 | B66: Договоры Click/Payme, платёжная интеграция | C66: сум | D66: нужно от Темура | E66: =IF(F66="","",F66) | G66: =IF(F66="","",F66) | H66: Stage1_Plan K1 | I66: Q11.
A67: P47 | B67: Внешняя разработка, дизайн, прочее | C67: сум | D67: нужно от Темура | E67: =IF(F67="","",F67) | G67: =IF(F67="","",F67) | H67: — | I67: Q11.
A68: I. Реакция спроса на цену (для проверки цены ±10% и ±20%)
A69: P48 | B69: Изменение числа заказов при росте цены на 10% | C69: доля | D69: нужно от Темура | E69: =IF(F69="","",F69) | G69: =IF(F69="","",F69) | H69: Навык ценообразования: чувствительность | I69: Пример: −0,05 = на 5% меньше заказов. Пусто = объём не реагирует (нереалистично, верхняя граница). Q13.
B71: Рынок: размер подтянуть из market_sizing.xlsx, когда он будет готов (сейчас — заглушка в строке «Расчётов уровня 1 в месяц»).

Sheet Вопросы к Темуру
A1: Вопросы к Темуру: что нужно, чтобы заполнить красные ячейки
A2: Чем раньше ответ, тем раньше модель перестанет занижать затраты. Срок маржи по записке пересборки — 28.10.2026 (14_Rebaseline п.4.1).
A4: № | B4: Вопрос | C4: Зачем (какие ячейки) | D4: Формат ответа
A5: Q1 | B5: Маржа последних 20–30 заказов KMT. По каждому: цена, гонорар оценщика, выезд, налоги, прочие прямые затраты, итоговая прибыль. Разбивка по сегментам: ипотека, наследство, суд, налог на имущество, прочее. Что входит в «прибыль ≈50%»? | C5: Маржа заказа (m_pct, dc1–dc7). Главный драйвер допустимого привлечения и БУ | D5: Таблица или выгрузка, без ФИО клиентов
A6: Q2 | B6: Себестоимость выезда: транспорт, время специалиста, доля заказов с выездом. | C6: dc2 | D6: Сум на заказ и доля
A7: Q3 | B7: Часы специалиста на один заказ ур.3 и как оплачивается оценщик (оклад, процент с заказа, сдельно). | C7: dc1, dc3 | D7: Часы и схема оплаты
A8: Q4 | B8: Единицы часов: «Темур и Равшан 15–20, Азиз 50» — в неделю, в месяц или на весь этап 1? Какая часть — разработка и запуск (разово), какая — постоянная работа (контент, поддержка)? | C8: h_unit, dT, dR, dA | D8: 1/2/3 и доли
A9: Q5 | B9: Ставки времени: считать ли время владельца, Равшана и Азиза по рыночной ставке, по зарплате или не считать? Сумма в сум за час или за месяц для каждого. | C9: rT, rR, rA | D9: Сум/час или сум/мес на человека
A10: Q6 | B10: Хостинг и сервисы 1 млн сум в месяц: что входит (сервер в РУз, домены, Telegram-бот, аналитика, SMS, ИИ-ассистент), с НДС ли, изменится ли после pd.gov.uz? Отдельно: SMS, колл-центр. | C10: host, oth | D10: Состав и сумма
A11: Q7 | B11: Комиссии: платим ли рекомендателям (банк, брокер, нотариус) и сколько; комиссия Click/Payme после K1; планируется ли плата партнёрам-оценщикам. Ответ юриста: допустимо ли вознаграждение за передачу клиента. | C11: share_ref, k_ref, fee_c, dc5 | D11: Процент и решение юриста
A12: Q8 | B12: НДС: цена 1 млн сум с НДС или без? Какая ставка применяется к KMT? | C12: vat_incl, vat_rate | D12: Да/нет и ставка
A13: Q9 | B13: Договор Bizzone–KMT: кому достаётся маржа заказа, есть ли плата проекту за лиды или лицензию на модели, кто платит за разработку и хостинг? | C13: share_bz. Определяет, окупается ли проект или только KMT | D13: Доля маржи проекту, %
A14: Q10 | B14: Сколько заказов в месяц KMT получает сейчас (в том числе по налогу на имущество) и сколько «новых» заказов пришли бы и без HomePrice? Какова мощность KMT? | C14: incr; ограничение по мощности | D14: Число и доля
A15: Q11 | B15: Длительность этапа 1 в месяцах и разовые расходы: юрист, pd.gov.uz, Click/Payme, внешняя разработка. | C15: stage_m, ot1–ot4 | D15: Месяцы и суммы
... A20: Q16 | B20: Когда будет готов market_sizing.xlsx? Подставлю объём расчётов вместо заглушки. | C20: calcs | D20: Дата

Sheet Юнит-экономика
A1: Юнит-экономика заказа уровня 3 (отчёт KMT)
A2: Все числа — из листа «Входные данные». Выручка и маржа заказа возникают в KMT; доля, учитываемая проекту, задаётся параметром share_bz.
B4: Показатель | C4: Пессимист | D4: База | E4: Оптимист | F4: Комментарий
B5: 1. Выручка и прямые затраты
B6: Цена отчёта | C6: =N('Входные данные'!$E$14) -> 1000000 | D6: =N('Входные данные'!$F$14) -> 1000000 | E6: =N('Входные данные'!$G$14) -> 1000000 | F6: [факт] 1 млн сум
B7: НДС в цене | C7: =IF(N('Входные данные'!$E$16)=1,'Юнит-экономика'!$C$6-'Юнит-экономика'!$C$6/(1+N('Входные данные'!$E$17)),0) -> 0 | D7: =IF(N('Входные данные'!$F$16)=1,'Юнит-экономика'!$D$6-'Юнит-экономика'!$D$6/(1+N('Входные данные'!$F$17)),0) -> 0 | E7: =IF(N('Входные данные'!$G$16)=1,'Юнит-экономика'!$E$6-'Юнит-экономика'!$E$6/(1+N('Входные данные'!$G$17)),0) -> 0 | F7: Пока НДС не задан — 0 (нужно от Темура)
B8: Выручка без НДС | C8: ='Юнит-экономика'!$C$6-'Юнит-экономика'!$C$7 -> 1000000 | D8: ='Юнит-экономика'!$D$6-'Юнит-экономика'!$D$7 -> 1000000 | E8: ='Юнит-экономика'!$E$6-'Юнит-экономика'!$E$7 -> 1000000
B9: Сумма построчных прямых затрат (метод 2) | C9: =N('Входные данные'!$E$22)+N('Входные данные'!$E$23)+N('Входные данные'!$E$24)+N('Входные данные'!$E$25)+N('Входные данные'!$E$26)+N('Входные данные'!$E$27)+N('Входные данные'!$E$28) -> 0 | D9: =N('Входные данные'!$F$22)+N('Входные данные'!$F$23)+N('Входные данные'!$F$24)+N('Входные данные'!$F$25)+N('Входные данные'!$F$26)+N('Входные данные'!$F$27)+N('Входные данные'!$F$28) -> 0 | E9: =N('Входные данные'!$G$22)+N('Входные данные'!$G$23)+N('Входные данные'!$G$24)+N('Входные данные'!$G$25)+N('Входные данные'!$G$26)+N('Входные данные'!$G$27)+N('Входные данные'!$G$28) -> 0 | F9: Пока пусто — нужно от Темура
B10: Прямые затраты на заказ | C10: =IF(N('Входные данные'!$E$20)=2,'Юнит-экономика'!$C$9,'Юнит-экономика'!$C$8*(1-N('Входные данные'!$E$21))) -> 700000 | D10: =IF(N('Входные данные'!$F$20)=2,'Юнит-экономика'!$D$9,'Юнит-экономика'!$D$8*(1-N('Входные данные'!$F$21))) -> 500000 | E10: =IF(N('Входные данные'!$G$20)=2,'Юнит-экономика'!$E$9,'Юнит-экономика'!$E$8*(1-N('Входные данные'!$G$21))) -> 500000 | F10: Метод 1: выручка × (1 − маржа владельца)
B11: Маржа заказа до комиссии | C11: ='Юнит-экономика'!$C$8-'Юнит-экономика'!$C$10 -> 300000 | D11: ='Юнит-экономика'!$D$8-'Юнит-экономика'!$D$10 -> 500000 | E11: ='Юнит-экономика'!$E$8-'Юнит-экономика'!$E$10 -> 500000
B12: Маржа, % выручки | C12: =IF('Юнит-экономика'!$C$8>0,'Юнит-экономика'!$C$11/'Юнит-экономика'!$C$8,0) -> 0.3 | D12: =IF('Юнит-экономика'!$D$8>0,'Юнит-экономика'!$D$11/'Юнит-экономика'!$D$8,0) -> 0.5 | E12: =IF('Юнит-экономика'!$E$8>0,'Юнит-экономика'!$E$11/'Юнит-экономика'!$E$8,0) -> 0.5
B13: Источник маржи | C13: =IF(N('Входные данные'!$E$20)=2,IF('Юнит-экономика'!$C$9=0,"НЕТ ДАННЫХ: строки пусты","построчно"),"оценка владельца [проверить]") -> оценка владельца [проверить] | D13: =IF(N('Входные данные'!$F$20)=2,IF('Юнит-экономика'!$D$9=0,"НЕТ ДАННЫХ: строки пусты","построчно"),"оценка владельца [проверить]") -> оценка владельца [проверить] | E13: =IF(N('Входные данные'!$G$20)=2,IF('Юнит-экономика'!$E$9=0,"НЕТ ДАННЫХ: строки пусты","построчно"),"оценка владельца [проверить]") -> оценка владельца [проверить]
B15: 2. Комиссия партнёра-рекомендателя
B16: Комиссия на заказ, пришедший через рекомендателя | C16: =N('Входные данные'!$E$34)*'Юнит-экономика'!$C$8 -> 150000 | D16: =N('Входные данные'!$F$34)*'Юнит-экономика'!$D$8 -> 150000 | E16: =N('Входные данные'!$G$34)*'Юнит-экономика'!$E$8 -> 150000 | F16: [гипотеза] 10–20% от чека (05_4P)
B17: Маржа такого заказа после комиссии | C17: ='Юнит-экономика'!$C$11-'Юнит-экономика'!$C$16 -> 150000 | D17: ='Юнит-экономика'!$D$11-'Юнит-экономика'!$D$16 -> 350000 | E17: ='Юнит-экономика'!$E$11-'Юнит-экономика'!$E$16 -> 350000
B18: Комиссия съедает, % маржи | C18: =IF('Юнит-экономика'!$C$11>0,'Юнит-экономика'!$C$16/'Юнит-экономика'!$C$11,0) -> 0.5 | D18: =IF('Юнит-экономика'!$D$11>0,'Юнит-экономика'!$D$16/'Юнит-экономика'!$D$11,0) -> 0.3 | E18: =IF('Юнит-экономика'!$E$11>0,'Юнит-экономика'!$E$16/'Юнит-экономика'!$E$11,0) -> 0.3 | F18: В 14_Rebaseline: 33–67% при марже 300 тыс. сум
B19: Комиссия на средний заказ (с учётом доли рекомендателей) | C19: =N('Входные данные'!$E$33)*'Юнит-экономика'!$C$16 -> 0 | D19: =N('Входные данные'!$F$33)*'Юнит-экономика'!$D$16 -> 0 | E19: =N('Входные данные'!$G$33)*'Юнит-экономика'!$E$16 -> 0 | F19: Доля на этапе 1 — 0 по рекомендации 14
B20: Маржа среднего заказа после комиссии | C20: ='Юнит-экономика'!$C$11-'Юнит-экономика'!$C$19 -> 300000 | D20: ='Юнит-экономика'!$D$11-'Юнит-экономика'!$D$19 -> 500000 | E20: ='Юнит-экономика'!$E$11-'Юнит-экономика'!$E$19 -> 500000 | F20: База для допустимого привлечения
B22: 3. Допустимая стоимость привлечения (потолок = доля маржи)
B23: Допустимо на один заказ | C23: =N('Входные данные'!$E$39)*MAX(0,'Юнит-экономика'!$C$20) -> 60000 | D23: =N('Входные данные'!$F$39)*MAX(0,'Юнит-экономика'!$D$20) -> 100000 | E23: =N('Входные данные'!$G$39)*MAX(0,'Юнит-экономика'!$E$20) -> 100000 | F23: [гипотеза] 20% маржи (14, п.4.1)
B24: Допустимо на один «интерес» (контакт, клик) | C24: ='Юнит-экономика'!$C$23*N('Входные данные'!$E$45) -> 1200 | D24: ='Юнит-экономика'!$D$23*N('Входные данные'!$F$45) -> 3500 | E24: ='Юнит-экономика'!$E$23*N('Входные данные'!$G$45) -> 5000
B25: Допустимо на один расчёт уровня 1 | C25: ='Юнит-экономика'!$C$23*N('Входные данные'!$E$44)*N('Входные данные'!$E$45)*N('Входные данные'!$E$46) -> 180 | D25: ='Юнит-экономика'!$D$23*N('Входные данные'!$F$44)*N('Входные данные'!$F$45)*N('Входные данные'!$F$46) -> 700 | E25: ='Юнит-экономика'!$E$23*N('Входные данные'!$G$44)*N('Входные данные'!$G$45)*N('Входные данные'!$G$46) -> 1250 | F25: Учитывает инкрементальность. Платный трафик на потребительский калькулятор окупается только при очень дешёвом клике
B26: То же, долларов | C26: =IF(N('Входные данные'!$E$18)>0,'Юнит-экономика'!$C$25/N('Входные данные'!$E$18),0) -> 0.015 | D26: =IF(N('Входные данные'!$F$18)>0,'Юнит-экономика'!$D$25/N('Входные данные'!$F$18),0) -> 0.058333333 | E26: =IF(N('Входные данные'!$G$18)>0,'Юнит-экономика'!$E$25/N('Входные данные'!$G$18),0) -> 0.10416667
B27: Комиссия рекомендателя больше потолка привлечения в … раз | C27: =IF(AND('Юнит-экономика'!$C$17>0,N('Входные данные'!$E$39)>0),'Юнит-экономика'!$C$16/(N('Входные данные'!$E$39)*'Юнит-экономика'!$C$17),"н/д") -> 5 | D27: =IF(AND('Юнит-экономика'!$D$17>0,N('Входные данные'!$F$39)>0),'Юнит-экономика'!$D$16/(N('Входные данные'!$F$39)*'Юнит-экономика'!$D$17),"н/д") -> 2.1428571 | E27: =IF(AND('Юнит-экономика'!$E$17>0,N('Входные данные'!$G$39)>0),'Юнит-экономика'!$E$16/(N('Входные данные'!$G$39)*'Юнит-экономика'!$E$17),"н/д") -> 2.1428571 | F27: Если >1, вознаграждение выше потолка 20% и вводить его нельзя без пересмотра потолка
B29: 4. Маржа проекта на один заказ по решению I1
B30: I1 = только KMT | C30: ='Юнит-экономика'!$C$20*N('Входные данные'!$E$32) -> 300000 | D30: ='Юнит-экономика'!$D$20*N('Входные данные'!$F$32) -> 500000 | E30: ='Юнит-экономика'!$E$20*N('Входные данные'!$G$32) -> 500000
B31: I1 = гибрид (клиент партнёра остаётся партнёру) | C31: =((1-N('Входные данные'!$E$35))*'Юнит-экономика'!$C$20+N('Входные данные'!$E$35)*N('Входные данные'!$E$36)*'Юнит-экономика'!$C$8)*N('Входные данные'!$E$32) -> 240000 | D31: =((1-N('Входные данные'!$F$35))*'Юнит-экономика'!$D$20+N('Входные данные'!$F$35)*N('Входные данные'!$F$36)*'Юнит-экономика'!$D$8)*N('Входные данные'!$F$32) -> 400000 | E31: =((1-N('Входные данные'!$G$35))*'Юнит-экономика'!$E$20+N('Входные данные'!$G$35)*N('Входные данные'!$G$36)*'Юнит-экономика'!$E$8)*N('Входные данные'!$G$32) -> 400000 | F31: Заказы партнёра дают только плату fee_c, остальное — маржу KMT
B32: Выбранный вариант (см. «Входные данные») | C32: =IF(N('Входные данные'!$E$30)=2,'Юнит-экономика'!$C$31,'Юнит-экономика'!$C$30) -> 300000 | D32: =IF(N('Входные данные'!$F$30)=2,'Юнит-экономика'!$D$31,'Юнит-экономика'!$D$30) -> 500000 | E32: =IF(N('Входные данные'!$G$30)=2,'Юнит-экономика'!$E$31,'Юнит-экономика'!$E$30) -> 500000

Sheet Воронка
A1: Воронка: посетитель → расчёт → интерес → заказ
A2: Конверсии из 05_4P — гипотезы. До A4 «интерес» измеряется анонимным кликом по блоку KMT, не контактом.
B4: Показатель | C4: Пессимист | D4: База | E4: Оптимист | F4: Комментарий
B5: Посетителей в месяц | C5: =IF(N('Входные данные'!$E$43)>0,N('Входные данные'!$E$42)/N('Входные данные'!$E$43),"нужно измерить") -> нужно измерить | D5: =IF(N('Входные данные'!$F$43)>0,N('Входные данные'!$F$42)/N('Входные данные'!$F$43),"нужно измерить") -> нужно измерить | E5: =IF(N('Входные данные'!$G$43)>0,N('Входные данные'!$G$42)/N('Входные данные'!$G$43),"нужно измерить") -> нужно измерить | F5: Нужна конверсия посетитель → расчёт (нужно от Темура / E2)
B6: Расчётов уровня 1 в месяц | C6: =N('Входные данные'!$E$42) -> 100 | D6: =N('Входные данные'!$F$42) -> 300 | E6: =N('Входные данные'!$G$42) -> 900 | F6: [заглушка] до market_sizing.xlsx
B7: Конверсия расчёт → интерес | C7: =N('Входные данные'!$E$44) -> 0.15 | D7: =N('Входные данные'!$F$44) -> 0.2 | E7: =N('Входные данные'!$G$44) -> 0.25 | F7: [гипотеза] 05_4P
B8: Интересов в месяц | C8: =Воронка!$C$6*Воронка!$C$7 -> 15 | D8: =Воронка!$D$6*Воронка!$D$7 -> 60 | E8: =Воронка!$E$6*Воронка!$E$7 -> 225
B9: Конверсия интерес → заказ | C9: =N('Входные данные'!$E$45) -> 0.02 | D9: =N('Входные данные'!$F$45) -> 0.035 | E9: =N('Входные данные'!$G$45) -> 0.05 | F9: [гипотеза] 05_4P
B10: Заказов уровня 3 в месяц (всего) | C10: =Воронка!$C$8*Воронка!$C$9 -> 0.3 | D10: =Воронка!$D$8*Воронка!$D$9 -> 2.1 | E10: =Воронка!$E$8*Воронка!$E$9 -> 11.25
B11: Доля инкрементальных заказов | C11: =N('Входные данные'!$E$46) -> 1 | D11: =N('Входные данные'!$F$46) -> 1 | E11: =N('Входные данные'!$G$46) -> 1 | F11: [гипотеза][проверить] верхняя граница 100%
B12: Инкрементальных заказов в месяц | C12: =Воронка!$C$10*Воронка!$C$11 -> 0.3 | D12: =Воронка!$D$10*Воронка!$D$11 -> 2.1 | E12: =Воронка!$E$10*Воронка!$E$11 -> 11.25
B13: Сквозная конверсия расчёт → инкрементальный заказ | C13: =Воронка!$C$7*Воронка!$C$9*Воронка!$C$11 -> 0.003 | D13: =Воронка!$D$7*Воронка!$D$9*Воронка!$D$11 -> 0.007 | E13: =Воронка!$E$7*Воронка!$E$9*Воронка!$E$11 -> 0.0125 | F13: Диапазон 0,3% – 1,25% совпадает с 14, п.4.1 (до инкрементальности)
B14: Расчётов на один заказ | C14: =IF(Воронка!$C$13>0,1/Воронка!$C$13,"нет конверсии") -> 333.33333 | D14: =IF(Воронка!$D$13>0,1/Воронка!$D$13,"нет конверсии") -> 142.85714 | E14: =IF(Воронка!$E$13>0,1/Воронка!$E$13,"нет конверсии") -> 80
B16: Влияние решения D10
B17: Множитель потока по выбранному D10 | C17: =IF(N('Входные данные'!$E$31)=2,N('Входные данные'!$E$37),1) -> 1 | D17: =IF(N('Входные данные'!$F$31)=2,N('Входные данные'!$F$37),1) -> 1 | E17: =IF(N('Входные данные'!$G$31)=2,N('Входные данные'!$G$37),1) -> 1 | F17: б+ = 100%; нейтральный текст = доля m_a [заглушка]
B18: Заказов в месяц с учётом D10 (режим) | C18: =Воронка!$C$12*Воронка!$C$17 -> 0.3 | D18: =Воронка!$D$12*Воронка!$D$17 -> 2.1 | E18: =Воронка!$E$12*Воронка!$E$17 -> 11.25
B19: Выручка заказов в KMT, сум/мес (без НДС) | C19: =Воронка!$C$18*'Юнит-экономика'!$C$8 -> 300000 | D19: =Воронка!$D$18*'Юнит-экономика'!$D$8 -> 2100000 | E19: =Воронка!$E$18*'Юнит-экономика'!$E$8 -> 11250000
B20: Маржа проекта, сум/мес (режим, по выбранному I1) | C20: =Воронка!$C$18*'Юнит-экономика'!$C$32 -> 90000 | D20: =Воронка!$D$18*'Юнит-экономика'!$D$32 -> 1050000 | E20: =Воронка!$E$18*'Юнит-экономика'!$E$32 -> 5625000

Sheet Сценарии_BEP
A1: Точка безубыточности и окупаемость этапа 1 (три сценария)
A2: Разработка и запуск считаются отдельно от операционных затрат. Пустые входы считаются нулём — итоги занижают затраты, пока их нет.
B4: Показатель | C4: Пессимист | D4: База | E4: Оптимист | F4: Комментарий
B5: 1. Операционные расходы в месяц
B6: Хостинг и сервисы | C6: =N('Входные данные'!$E$49) -> 1000000 | D6: =N('Входные данные'!$F$49) -> 1000000 | E6: =N('Входные данные'!$G$49) -> 1000000 | F6: [факт] 1 млн сум
B7: SMS, колл-центр, прочее | C7: =N('Входные данные'!$E$50) -> 0 | D7: =N('Входные данные'!$F$50) -> 0 | E7: =N('Входные данные'!$G$50) -> 0 | F7: нужно от Темура
B8: Маркетинг | C8: =N('Входные данные'!$E$40) -> 0 | D8: =N('Входные данные'!$F$40) -> 0 | E8: =N('Входные данные'!$G$40) -> 0 | F8: [факт] бюджета нет
B9: Денежные операционные расходы | C9: =Сценарии_BEP!$C$6+Сценарии_BEP!$C$7+Сценарии_BEP!$C$8 -> 1000000 | D9: =Сценарии_BEP!$D$6+Сценарии_BEP!$D$7+Сценарии_BEP!$D$8 -> 1000000 | E9: =Сценарии_BEP!$E$6+Сценарии_BEP!$E$7+Сценарии_BEP!$E$8 -> 1000000
B10: Часов в месяц на 1 час «периода» | C10: =IF(N('Входные данные'!$E$52)=1,52/12,IF(N('Входные данные'!$E$52)=2,1,IF(AND(N('Входные данные'!$E$52)=3,N('Входные данные'!$E$53)>0),1/N('Входные данные'!$E$53),0))) -> 0 | D10: =IF(N('Входные данные'!$F$52)=1,52/12,IF(N('Входные данные'!$F$52)=2,1,IF(AND(N('Входные данные'!$F$52)=3,N('Входные данные'!$F$53)>0),1/N('Входные данные'!$F$53),0))) -> 0 | E10: =IF(N('Входные данные'!$G$52)=1,52/12,IF(N('Входные данные'!$G$52)=2,1,IF(AND(N('Входные данные'!$G$52)=3,N('Входные данные'!$G$53)>0),1/N('Входные данные'!$G$53),0))) -> 0 | F10: 0, пока не заданы единицы часов (нужно от Темура)
B11: Труд, постоянная часть: Темур | C11: =N('Входные данные'!$E$54)*(1-N('Входные данные'!$E$60))*Сценарии_BEP!$C$10*N('Входные данные'!$E$57) -> 0 | D11: =N('Входные данные'!$F$54)*(1-N('Входные данные'!$F$60))*Сценарии_BEP!$D$10*N('Входные данные'!$F$57) -> 0 | E11: =N('Входные данные'!$G$54)*(1-N('Входные данные'!$G$60))*Сценарии_BEP!$E$10*N('Входные данные'!$G$57) -> 0 | F11: часы × (1 − доля разработки) × коэф. × ставка
B12: Труд, постоянная часть: Равшан | C12: =N('Входные данные'!$E$55)*(1-N('Входные данные'!$E$61))*Сценарии_BEP!$C$10*N('Входные данные'!$E$58) -> 0 | D12: =N('Входные данные'!$F$55)*(1-N('Входные данные'!$F$61))*Сценарии_BEP!$D$10*N('Входные данные'!$F$58) -> 0 | E12: =N('Входные данные'!$G$55)*(1-N('Входные данные'!$G$61))*Сценарии_BEP!$E$10*N('Входные данные'!$G$58) -> 0 | F12: часы × (1 − доля разработки) × коэф. × ставка
B13: Труд, постоянная часть: Азиз | C13: =N('Входные данные'!$E$56)*(1-N('Входные данные'!$E$62))*Сценарии_BEP!$C$10*N('Входные данные'!$E$59) -> 0 | D13: =N('Входные данные'!$F$56)*(1-N('Входные данные'!$F$62))*Сценарии_BEP!$D$10*N('Входные данные'!$F$59) -> 0 | E13: =N('Входные данные'!$G$56)*(1-N('Входные данные'!$G$62))*Сценарии_BEP!$E$10*N('Входные данные'!$G$59) -> 0 | F13: часы × (1 − доля разработки) × коэф. × ставка
B14: Труд команды (постоянная часть), сум/мес | C14: =Сценарии_BEP!$C$11+Сценарии_BEP!$C$12+Сценарии_BEP!$C$13 -> 0 | D14: =Сценарии_BEP!$D$11+Сценарии_BEP!$D$12+Сценарии_BEP!$D$13 -> 0 | E14: =Сценарии_BEP!$E$11+Сценарии_BEP!$E$12+Сценарии_BEP!$E$13 -> 0 | F14: Условная стоимость времени, не денежный расход
B15: Полные операционные расходы, сум/мес | C15: =Сценарии_BEP!$C$9+Сценарии_BEP!$C$14 -> 1000000 | D15: =Сценарии_BEP!$D$9+Сценарии_BEP!$D$14 -> 1000000 | E15: =Сценарии_BEP!$E$9+Сценарии_BEP!$E$14 -> 1000000
B17: 2. Разработка и запуск (разово, отдельно от операционных)
B18: Периодов часов за этап | C18: =IF(N('Входные данные'!$E$52)=1,N('Входные данные'!$E$53)*52/12,IF(N('Входные данные'!$E$52)=2,N('Входные данные'!$E$53),IF(N('Входные данные'!$E$52)=3,1,0))) -> 0 | D18: =IF(N('Входные данные'!$F$52)=1,N('Входные данные'!$F$53)*52/12,IF(N('Входные данные'!$F$52)=2,N('Входные данные'!$F$53),IF(N('Входные данные'!$F$52)=3,1,0))) -> 0 | E18: =IF(N('Входные данные'!$G$52)=1,N('Входные данные'!$G$53)*52/12,IF(N('Входные данные'!$G$52)=2,N('Входные данные'!$G$53),IF(N('Входные данные'!$G$52)=3,1,0))) -> 0 | F18: Нужны единицы часов и длительность этапа
B19: Разработка и запуск: Темур | C19: =N('Входные данные'!$E$54)*N('Входные данные'!$E$60)*N('Входные данные'!$E$57)*Сценарии_BEP!$C$18 -> 0 | D19: =N('Входные данные'!$F$54)*N('Входные данные'!$F$60)*N('Входные данные'!$F$57)*Сценарии_BEP!$D$18 -> 0 | E19: =N('Входные данные'!$G$54)*N('Входные данные'!$G$60)*N('Входные данные'!$G$57)*Сценарии_BEP!$E$18 -> 0
B20: Разработка и запуск: Равшан | C20: =N('Входные данные'!$E$55)*N('Входные данные'!$E$61)*N('Входные данные'!$E$58)*Сценарии_BEP!$C$18 -> 0 | D20: =N('Входные данные'!$F$55)*N('Входные данные'!$F$61)*N('Входные данные'!$F$58)*Сценарии_BEP!$D$18 -> 0 | E20: =N('Входные данные'!$G$55)*N('Входные данные'!$G$61)*N('Входные данные'!$G$58)*Сценарии_BEP!$E$18 -> 0
B21: Разработка и запуск: Азиз | C21: =N('Входные данные'!$E$56)*N('Входные данные'!$E$62)*N('Входные данные'!$E$59)*Сценарии_BEP!$C$18 -> 0 | D21: =N('Входные данные'!$F$56)*N('Входные данные'!$F$62)*N('Входные данные'!$F$59)*Сценарии_BEP!$D$18 -> 0 | E21: =N('Входные данные'!$G$56)*N('Входные данные'!$G$62)*N('Входные данные'!$G$59)*Сценарии_BEP!$E$18 -> 0
B22: Разработка: труд команды | C22: =Сценарии_BEP!$C$19+Сценарии_BEP!$C$20+Сценарии_BEP!$C$21 -> 0 | D22: =Сценарии_BEP!$D$19+Сценарии_BEP!$D$20+Сценарии_BEP!$D$21 -> 0 | E22: =Сценарии_BEP!$E$19+Сценарии_BEP!$E$20+Сценарии_BEP!$E$21 -> 0
B23: Разовые внешние расходы | C23: =N('Входные данные'!$E$64)+N('Входные данные'!$E$65)+N('Входные данные'!$E$66)+N('Входные данные'!$E$67) -> 0 | D23: =N('Входные данные'!$F$64)+N('Входные данные'!$F$65)+N('Входные данные'!$F$66)+N('Входные данные'!$F$67) -> 0 | E23: =N('Входные данные'!$G$64)+N('Входные данные'!$G$65)+N('Входные данные'!$G$66)+N('Входные данные'!$G$67) -> 0 | F23: нужно от Темура
B24: Разработка и запуск, итого | C24: =Сценарии_BEP!$C$22+Сценарии_BEP!$C$23 -> 0 | D24: =Сценарии_BEP!$D$22+Сценарии_BEP!$D$23 -> 0 | E24: =Сценарии_BEP!$E$22+Сценарии_BEP!$E$23 -> 0
B26: 3. Точка безубыточности (режим, без ramp)
B27: Маржа проекта на заказ (выбранный I1) | C27: ='Юнит-экономика'!$C$32 -> 300000 | D27: ='Юнит-экономика'!$D$32 -> 500000 | E27: ='Юнит-экономика'!$E$32 -> 500000
B28: Эффективная конверсия расчёт → заказ (с учётом D10) | C28: =Воронка!$C$13*Воронка!$C$17 -> 0.003 | D28: =Воронка!$D$13*Воронка!$D$17 -> 0.007 | E28: =Воронка!$E$13*Воронка!$E$17 -> 0.0125
B29: БУ денежная: заказов в месяц | C29: =IF(Сценарии_BEP!$C$27>0,Сценарии_BEP!$C$9/Сценарии_BEP!$C$27,"нет БУ: маржа ≤ 0") -> 3.3333333 | D29: =IF(Сценарии_BEP!$D$27>0,Сценарии_BEP!$D$9/Сценарии_BEP!$D$27,"нет БУ: маржа ≤ 0") -> 2 | E29: =IF(Сценарии_BEP!$E$27>0,Сценарии_BEP!$E$9/Сценарии_BEP!$E$27,"нет БУ: маржа ≤ 0") -> 2 | F29: Покрывает хостинг, сервисы, маркетинг
B30: БУ полная: заказов в месяц | C30: =IF(Сценарии_BEP!$C$27>0,Сценарии_BEP!$C$15/Сценарии_BEP!$C$27,"нет БУ: маржа ≤ 0") -> 3.3333333 | D30: =IF(Сценарии_BEP!$D$27>0,Сценарии_BEP!$D$15/Сценарии_BEP!$D$27,"нет БУ: маржа ≤ 0") -> 2 | E30: =IF(Сценарии_BEP!$E$27>0,Сценарии_BEP!$E$15/Сценарии_BEP!$E$27,"нет БУ: маржа ≤ 0") -> 2 | F30: Плюс условная стоимость труда
B31: БУ денежная: расчётов уровня 1 в месяц | C31: =IF(AND(ISNUMBER(Сценарии_BEP!$C$29),Сценарии_BEP!$C$28>0),Сценарии_BEP!$C$29/Сценарии_BEP!$C$28,"нет БУ") -> 1111.1111 | D31: =IF(AND(ISNUMBER(Сценарии_BEP!$D$29),Сценарии_BEP!$D$28>0),Сценарии_BEP!$D$29/Сценарии_BEP!$D$28,"нет БУ") -> 285.71429 | E31: =IF(AND(ISNUMBER(Сценарии_BEP!$E$29),Сценарии_BEP!$E$28>0),Сценарии_BEP!$E$29/Сценарии_BEP!$E$28,"нет БУ") -> 160
B32: БУ полная: расчётов уровня 1 в месяц | C32: =IF(AND(ISNUMBER(Сценарии_BEP!$C$30),Сценарии_BEP!$C$28>0),Сценарии_BEP!$C$30/Сценарии_BEP!$C$28,"нет БУ") -> 1111.1111 | D32: =IF(AND(ISNUMBER(Сценарии_BEP!$D$30),Сценарии_BEP!$D$28>0),Сценарии_BEP!$D$30/Сценарии_BEP!$D$28,"нет БУ") -> 285.71429 | E32: =IF(AND(ISNUMBER(Сценарии_BEP!$E$30),Сценарии_BEP!$E$28>0),Сценарии_BEP!$E$30/Сценарии_BEP!$E$28,"нет БУ") -> 160
B33: БУ полная, если тратить на привлечение весь потолок: заказов в месяц | C33: =IF(Сценарии_BEP!$C$27*(1-N('Входные данные'!$E$39))>0,Сценарии_BEP!$C$15/(Сценарии_BEP!$C$27*(1-N('Входные данные'!$E$39))),"нет БУ") -> 4.1666667 | D33: =IF(Сценарии_BEP!$D$27*(1-N('Входные данные'!$F$39))>0,Сценарии_BEP!$D$15/(Сценарии_BEP!$D$27*(1-N('Входные данные'!$F$39))),"нет БУ") -> 2.5 | E33: =IF(Сценарии_BEP!$E$27*(1-N('Входные данные'!$G$39))>0,Сценарии_BEP!$E$15/(Сценарии_BEP!$E$27*(1-N('Входные данные'!$G$39))),"нет БУ") -> 2.5 | F33: Маржа за вычетом привлечения по потолку
B34: Объём сценария / БУ полная (расчёты), раз | C34: =IF(ISNUMBER(Сценарии_BEP!$C$32),Воронка!$C$6/Сценарии_BEP!$C$32,"н/д") -> 0.09 | D34: =IF(ISNUMBER(Сценарии_BEP!$D$32),Воронка!$D$6/Сценарии_BEP!$D$32,"н/д") -> 1.05 | E34: =IF(ISNUMBER(Сценарии_BEP!$E$32),Воронка!$E$6/Сценарии_BEP!$E$32,"н/д") -> 5.625 | F34: Меньше 1 — сценарий не покрывает расходы
B35: Результат в режиме до труда (маржа − денежные), сум/мес | C35: =Воронка!$C$20-Сценарии_BEP!$C$9 -> -910000 | D35: =Воронка!$D$20-Сценарии_BEP!$D$9 -> 50000 | E35: =Воронка!$E$20-Сценарии_BEP!$E$9 -> 4625000
B36: Результат в режиме с трудом (маржа − полные), сум/мес | C36: =Воронка!$C$20-Сценарии_BEP!$C$15 -> -910000 | D36: =Воронка!$D$20-Сценарии_BEP!$D$15 -> 50000 | E36: =Воронка!$E$20-Сценарии_BEP!$E$15 -> 4625000
B37: Простая окупаемость разработки, мес | C37: =IF(Сценарии_BEP!$C$24<=0,"нет данных о затратах на разработку",IF(Сценарии_BEP!$C$36>0,Сценарии_BEP!$C$24/Сценарии_BEP!$C$36,"не окупается")) -> нет данных о затратах на разработку | D37: =IF(Сценарии_BEP!$D$24<=0,"нет данных о затратах на разработку",IF(Сценарии_BEP!$D$36>0,Сценарии_BEP!$D$24/Сценарии_BEP!$D$36,"не окупается")) -> нет данных о затратах на разработку | E37: =IF(Сценарии_BEP!$E$24<=0,"нет данных о затратах на разработку",IF(Сценарии_BEP!$E$36>0,Сценарии_BEP!$E$24/Сценарии_BEP!$E$36,"не окупается")) -> нет данных о затратах на разработку | F37: Разработка ÷ месячный результат в режиме
B39: 4. Итоги 12 месяцев (с ramp)
B40: Заказов за 12 мес | C40: =P54 -> 3.45 | D40: =P71 -> 24.15 | E40: =P88 -> 129.375
B41: Маржа проекта за 12 мес | C41: =P56 -> 1035000 | D41: =P73 -> 12075000 | E41: =P90 -> 64687500
B42: Операционный результат за 12 мес | C42: =P58 -> -10965000 | D42: =P75 -> 75000 | E42: =P92 -> 52687500
B43: Итог за 12 мес с разработкой | C43: =O61 -> -10965000 | D43: =O78 -> 75000 | E43: =O95 -> 52687500
B44: Месяц окупаемости операций | C44: =IF(COUNT(D62:O62)=0,"не окупается за 12 мес",MIN(D62:O62)) -> не окупается за 12 мес | D44: =IF(COUNT(D79:O79)=0,"не окупается за 12 мес",MIN(D79:O79)) -> 11 | E44: =IF(COUNT(D96:O96)=0,"не окупается за 12 мес",MIN(D96:O96)) -> 1
B45: Месяц окупаемости с разработкой | C45: =IF(COUNT(D63:O63)=0,"не окупается за 12 мес",MIN(D63:O63)) -> не окупается за 12 мес | D45: =IF(COUNT(D80:O80)=0,"не окупается за 12 мес",MIN(D80:O80)) -> 11 | E45: =IF(COUNT(D97:O97)=0,"не окупается за 12 мес",MIN(D97:O97)) -> 1
B46: Окупаемость считается по накопленному результату; если операционный результат в режиме отрицателен, окупаемости нет при любом сроке.
B50: Помесячно: Пессимист
B51: Месяц (0 = разработка) | C51: 0 | D51: 1 | E51: 2 | F51: 3 | G51: 4 | H51: 5 | I51: 6 | J51: 7 | K51: 8 | L51: 9 | M51: 10 | N51: 11 | O51: 12 | P51: Итого
B52: Коэффициент выхода на режим | D52: =IF(N('Входные данные'!$E$47)<=0,1,MIN(1,D51/N('Входные данные'!$E$47))) -> 0.5 | E52: =IF(N('Входные данные'!$E$47)<=0,1,MIN(1,E51/N('Входные данные'!$E$47))) -> 1 | F52: =IF(N('Входные данные'!$E$47)<=0,1,MIN(1,F51/N('Входные данные'!$E$47))) -> 1 | G52: =IF(N('Входные данные'!$E$47)<=0,1,MIN(1,G51/N('Входные данные'!$E$47))) -> 1 | H52: =IF(N('Входные данные'!$E$47)<=0,1,MIN(1,H51/N('Входные данные'!$E$47))) -> 1 | I52: =IF(N('Входные данные'!$E$47)<=0,1,MIN(1,I51/N('Входные данные'!$E$47))) -> 1 | J52: =IF(N('Входные данные'!$E$47)<=0,1,MIN(1,J51/N('Входные данные'!$E$47))) -> 1 | K52: =IF(N('Входные данные'!$E$47)<=0,1,MIN(1,K51/N('Входные данные'!$E$47))) -> 1 | ... O52: =IF(N('Входные данные'!$E$47)<=0,1,MIN(1,O51/N('Входные данные'!$E$47))) -> 1
B53: Расчётов уровня 1 | D53: =Воронка!$C$6*D52 -> 50 | E53: =Воронка!$C$6*E52 -> 100 | F53: =Воронка!$C$6*F52 -> 100 | G53: =Воронка!$C$6*G52 -> 100 | H53: =Воронка!$C$6*H52 -> 100 | I53: =Воронка!$C$6*I52 -> 100 | J53: =Воронка!$C$6*J52 -> 100 | K53: =Воронка!$C$6*K52 -> 100 | ... O53: =Воронка!$C$6*O52 -> 100 | P53: =SUM(D53:O53) -> 1150
B54: Инкрементальных заказов | D54: =D53*Воронка!$C$13*Воронка!$C$17 -> 0.15 | E54: =E53*Воронка!$C$13*Воронка!$C$17 -> 0.3 | F54: =F53*Воронка!$C$13*Воронка!$C$17 -> 0.3 | G54: =G53*Воронка!$C$13*Воронка!$C$17 -> 0.3 | H54: =H53*Воронка!$C$13*Воронка!$C$17 -> 0.3 | I54: =I53*Воронка!$C$13*Воронка!$C$17 -> 0.3 | J54: =J53*Воронка!$C$13*Воронка!$C$17 -> 0.3 | K54: =K53*Воронка!$C$13*Воронка!$C$17 -> 0.3 | ... O54: =O53*Воронка!$C$13*Воронка!$C$17 -> 0.3 | P54: =SUM(D54:O54) -> 3.45
B55: Выручка заказов в KMT (без НДС) | D55: =D54*'Юнит-экономика'!$C$8 -> 150000 | E55: =E54*'Юнит-экономика'!$C$8 -> 300000 | F55: =F54*'Юнит-экономика'!$C$8 -> 300000 | G55: =G54*'Юнит-экономика'!$C$8 -> 300000 | H55: =H54*'Юнит-экономика'!$C$8 -> 300000 | I55: =I54*'Юнит-экономика'!$C$8 -> 300000 | J55: =J54*'Юнит-экономика'!$C$8 -> 300000 | K55: =K54*'Юнит-экономика'!$C$8 -> 300000 | ... O55: =O54*'Юнит-экономика'!$C$8 -> 300000 | P55: =SUM(D55:O55) -> 3450000
B56: Маржа проекта | D56: =D54*'Юнит-экономика'!$C$32 -> 45000 | E56: =E54*'Юнит-экономика'!$C$32 -> 90000 | F56: =F54*'Юнит-экономика'!$C$32 -> 90000 | G56: =G54*'Юнит-экономика'!$C$32 -> 90000 | H56: =H54*'Юнит-экономика'!$C$32 -> 90000 | I56: =I54*'Юнит-экономика'!$C$32 -> 90000 | J56: =J54*'Юнит-экономика'!$C$32 -> 90000 | K56: =K54*'Юнит-экономика'!$C$32 -> 90000 | ... O56: =O54*'Юнит-экономика'!$C$32 -> 90000 | P56: =SUM(D56:O56) -> 1035000
B57: Операционные расходы (полные) | D57: =Сценарии_BEP!$C$15 -> 1000000 | E57: =Сценарии_BEP!$C$15 -> 1000000 | F57: =Сценарии_BEP!$C$15 -> 1000000 | G57: =Сценарии_BEP!$C$15 -> 1000000 | H57: =Сценарии_BEP!$C$15 -> 1000000 | I57: =Сценарии_BEP!$C$15 -> 1000000 | J57: =Сценарии_BEP!$C$15 -> 1000000 | K57: =Сценарии_BEP!$C$15 -> 1000000 | ... O57: =Сценарии_BEP!$C$15 -> 1000000 | P57: =SUM(D57:O57) -> 12000000
B58: Операционный результат | D58: =D56-D57 -> -955000 | E58: =E56-E57 -> -910000 | F58: =F56-F57 -> -910000 | G58: =G56-G57 -> -910000 | H58: =H56-H57 -> -910000 | I58: =I56-I57 -> -910000 | J58: =J56-J57 -> -910000 | K58: =K56-K57 -> -910000 | ... O58: =O56-O57 -> -910000 | P58: =SUM(D58:O58) -> -10965000
B59: Накопленный операционный результат | C59: 0 | D59: =C59+D58 -> -955000 | E59: =D59+E58 -> -1865000 | F59: =E59+F58 -> -2775000 | G59: =F59+G58 -> -3685000 | H59: =G59+H58 -> -4595000 | I59: =H59+I58 -> -5505000 | J59: =I59+J58 -> -6415000 | K59: =J59+K58 -> -7325000 | ... O59: =N59+O58 -> -10965000
B60: Разработка и запуск (разово) | C60: =-Сценарии_BEP!$C$24 -> 0 | D60: 0 | E60: 0 | F60: 0 | G60: 0 | H60: 0 | I60: 0 | J60: 0 | K60: 0 | L60: 0 | M60: 0 | N60: 0 | O60: 0 | P60: =C60 -> 0
B61: Накопленный итог с разработкой | C61: =C60 -> 0 | D61: =C61+D58+D60 -> -955000 | E61: =D61+E58+E60 -> -1865000 | F61: =E61+F58+F60 -> -2775000 | G61: =F61+G58+G60 -> -3685000 | H61: =G61+H58+H60 -> -4595000 | I61: =H61+I58+I60 -> -5505000 | J61: =I61+J58+J60 -> -6415000 | K61: =J61+K58+K60 -> -7325000 | ... O61: =N61+O58+O60 -> -10965000
B62: Флаг: операции окупились (номер месяца) | D62: =IF(D59>=0,D51,"") | E62: =IF(E59>=0,E51,"") | F62: =IF(F59>=0,F51,"") | G62: =IF(G59>=0,G51,"") | H62: =IF(H59>=0,H51,"") | I62: =IF(I59>=0,I51,"") | J62: =IF(J59>=0,J51,"") | K62: =IF(K59>=0,K51,"") | ... O62: =IF(O59>=0,O51,"")
B63: Флаг: окупилось с разработкой (номер месяца) | D63: =IF(D61>=0,D51,"") | E63: =IF(E61>=0,E51,"") | F63: =IF(F61>=0,F51,"") | G63: =IF(G61>=0,G51,"") | H63: =IF(H61>=0,H51,"") | I63: =IF(I61>=0,I51,"") | J63: =IF(J61>=0,J51,"") | K63: =IF(K61>=0,K51,"") | ... O63: =IF(O61>=0,O51,"")
B67: Помесячно: База
B68: Месяц (0 = разработка) | C68: 0 | D68: 1 | E68: 2 | F68: 3 | G68: 4 | H68: 5 | I68: 6 | J68: 7 | K68: 8 | L68: 9 | M68: 10 | N68: 11 | O68: 12 | P68: Итого
B69: Коэффициент выхода на режим | D69: =IF(N('Входные данные'!$F$47)<=0,1,MIN(1,D68/N('Входные данные'!$F$47))) -> 0.5 | E69: =IF(N('Входные данные'!$F$47)<=0,1,MIN(1,E68/N('Входные данные'!$F$47))) -> 1 | F69: =IF(N('Входные данные'!$F$47)<=0,1,MIN(1,F68/N('Входные данные'!$F$47))) -> 1 | G69: =IF(N('Входные данные'!$F$47)<=0,1,MIN(1,G68/N('Входные данные'!$F$47))) -> 1 | H69: =IF(N('Входные данные'!$F$47)<=0,1,MIN(1,H68/N('Входные данные'!$F$47))) -> 1 | I69: =IF(N('Входные данные'!$F$47)<=0,1,MIN(1,I68/N('Входные данные'!$F$47))) -> 1 | J69: =IF(N('Входные данные'!$F$47)<=0,1,MIN(1,J68/N('Входные данные'!$F$47))) -> 1 | K69: =IF(N('Входные данные'!$F$47)<=0,1,MIN(1,K68/N('Входные данные'!$F$47))) -> 1 | ... O69: =IF(N('Входные данные'!$F$47)<=0,1,MIN(1,O68/N('Входные данные'!$F$47))) -> 1
B70: Расчётов уровня 1 | D70: =Воронка!$D$6*D69 -> 150 | E70: =Воронка!$D$6*E69 -> 300 | F70: =Воронка!$D$6*F69 -> 300 | G70: =Воронка!$D$6*G69 -> 300 | H70: =Воронка!$D$6*H69 -> 300 | I70: =Воронка!$D$6*I69 -> 300 | J70: =Воронка!$D$6*J69 -> 300 | K70: =Воронка!$D$6*K69 -> 300 | ... O70: =Воронка!$D$6*O69 -> 300 | P70: =SUM(D70:O70) -> 3450
B71: Инкрементальных заказов | D71: =D70*Воронка!$D$13*Воронка!$D$17 -> 1.05 | E71: =E70*Воронка!$D$13*Воронка!$D$17 -> 2.1 | F71: =F70*Воронка!$D$13*Воронка!$D$17 -> 2.1 | G71: =G70*Воронка!$D$13*Воронка!$D$17 -> 2.1 | H71: =H70*Воронка!$D$13*Воронка!$D$17 -> 2.1 | I71: =I70*Воронка!$D$13*Воронка!$D$17 -> 2.1 | J71: =J70*Воронка!$D$13*Воронка!$D$17 -> 2.1 | K71: =K70*Воронка!$D$13*Воронка!$D$17 -> 2.1 | ... O71: =O70*Воронка!$D$13*Воронка!$D$17 -> 2.1 | P71: =SUM(D71:O71) -> 24.15
B72: Выручка заказов в KMT (без НДС) | D72: =D71*'Юнит-экономика'!$D$8 -> 1050000 | E72: =E71*'Юнит-экономика'!$D$8 -> 2100000 | F72: =F71*'Юнит-экономика'!$D$8 -> 2100000 | G72: =G71*'Юнит-экономика'!$D$8 -> 2100000 | H72: =H71*'Юнит-экономика'!$D$8 -> 2100000 | I72: =I71*'Юнит-экономика'!$D$8 -> 2100000 | J72: =J71*'Юнит-экономика'!$D$8 -> 2100000 | K72: =K71*'Юнит-экономика'!$D$8 -> 2100000 | ... O72: =O71*'Юнит-экономика'!$D$8 -> 2100000 | P72: =SUM(D72:O72) -> 24150000
B73: Маржа проекта | D73: =D71*'Юнит-экономика'!$D$32 -> 525000 | E73: =E71*'Юнит-экономика'!$D$32 -> 1050000 | F73: =F71*'Юнит-экономика'!$D$32 -> 1050000 | G73: =G71*'Юнит-экономика'!$D$32 -> 1050000 | H73: =H71*'Юнит-экономика'!$D$32 -> 1050000 | I73: =I71*'Юнит-экономика'!$D$32 -> 1050000 | J73: =J71*'Юнит-экономика'!$D$32 -> 1050000 | K73: =K71*'Юнит-экономика'!$D$32 -> 1050000 | ... O73: =O71*'Юнит-экономика'!$D$32 -> 1050000 | P73: =SUM(D73:O73) -> 12075000
B74: Операционные расходы (полные) | D74: =Сценарии_BEP!$D$15 -> 1000000 | E74: =Сценарии_BEP!$D$15 -> 1000000 | F74: =Сценарии_BEP!$D$15 -> 1000000 | G74: =Сценарии_BEP!$D$15 -> 1000000 | H74: =Сценарии_BEP!$D$15 -> 1000000 | I74: =Сценарии_BEP!$D$15 -> 1000000 | J74: =Сценарии_BEP!$D$15 -> 1000000 | K74: =Сценарии_BEP!$D$15 -> 1000000 | ... O74: =Сценарии_BEP!$D$15 -> 1000000 | P74: =SUM(D74:O74) -> 12000000
B75: Операционный результат | D75: =D73-D74 -> -475000 | E75: =E73-E74 -> 50000 | F75: =F73-F74 -> 50000 | G75: =G73-G74 -> 50000 | H75: =H73-H74 -> 50000 | I75: =I73-I74 -> 50000 | J75: =J73-J74 -> 50000 | K75: =K73-K74 -> 50000 | ... O75: =O73-O74 -> 50000 | P75: =SUM(D75:O75) -> 75000
B76: Накопленный операционный результат | C76: 0 | D76: =C76+D75 -> -475000 | E76: =D76+E75 -> -425000 | F76: =E76+F75 -> -375000 | G76: =F76+G75 -> -325000 | H76: =G76+H75 -> -275000 | I76: =H76+I75 -> -225000 | J76: =I76+J75 -> -175000 | K76: =J76+K75 -> -125000 | ... O76: =N76+O75 -> 75000
B77: Разработка и запуск (разово) | C77: =-Сценарии_BEP!$D$24 -> 0 | D77: 0 | E77: 0 | F77: 0 | G77: 0 | H77: 0 | I77: 0 | J77: 0 | K77: 0 | L77: 0 | M77: 0 | N77: 0 | O77: 0 | P77: =C77 -> 0
B78: Накопленный итог с разработкой | C78: =C77 -> 0 | D78: =C78+D75+D77 -> -475000 | E78: =D78+E75+E77 -> -425000 | F78: =E78+F75+F77 -> -375000 | G78: =F78+G75+G77 -> -325000 | H78: =G78+H75+H77 -> -275000 | I78: =H78+I75+I77 -> -225000 | J78: =I78+J75+J77 -> -175000 | K78: =J78+K75+K77 -> -125000 | ... O78: =N78+O75+O77 -> 75000
B79: Флаг: операции окупились (номер месяца) | D79: =IF(D76>=0,D68,"") | E79: =IF(E76>=0,E68,"") | F79: =IF(F76>=0,F68,"") | G79: =IF(G76>=0,G68,"") | H79: =IF(H76>=0,H68,"") | I79: =IF(I76>=0,I68,"") | J79: =IF(J76>=0,J68,"") | K79: =IF(K76>=0,K68,"") | ... O79: =IF(O76>=0,O68,"") -> 12
B80: Флаг: окупилось с разработкой (номер месяца) | D80: =IF(D78>=0,D68,"") | E80: =IF(E78>=0,E68,"") | F80: =IF(F78>=0,F68,"") | G80: =IF(G78>=0,G68,"") | H80: =IF(H78>=0,H68,"") | I80: =IF(I78>=0,I68,"") | J80: =IF(J78>=0,J68,"") | K80: =IF(K78>=0,K68,"") | ... O80: =IF(O78>=0,O68,"") -> 12
B84: Помесячно: Оптимист
B85: Месяц (0 = разработка) | C85: 0 | D85: 1 | E85: 2 | F85: 3 | G85: 4 | H85: 5 | I85: 6 | J85: 7 | K85: 8 | L85: 9 | M85: 10 | N85: 11 | O85: 12 | P85: Итого
B86: Коэффициент выхода на режим | D86: =IF(N('Входные данные'!$G$47)<=0,1,MIN(1,D85/N('Входные данные'!$G$47))) -> 0.5 | E86: =IF(N('Входные данные'!$G$47)<=0,1,MIN(1,E85/N('Входные данные'!$G$47))) -> 1 | F86: =IF(N('Входные данные'!$G$47)<=0,1,MIN(1,F85/N('Входные данные'!$G$47))) -> 1 | G86: =IF(N('Входные данные'!$G$47)<=0,1,MIN(1,G85/N('Входные данные'!$G$47))) -> 1 | H86: =IF(N('Входные данные'!$G$47)<=0,1,MIN(1,H85/N('Входные данные'!$G$47))) -> 1 | I86: =IF(N('Входные данные'!$G$47)<=0,1,MIN(1,I85/N('Входные данные'!$G$47))) -> 1 | J86: =IF(N('Входные данные'!$G$47)<=0,1,MIN(1,J85/N('Входные данные'!$G$47))) -> 1 | K86: =IF(N('Входные данные'!$G$47)<=0,1,MIN(1,K85/N('Входные данные'!$G$47))) -> 1 | ... O86: =IF(N('Входные данные'!$G$47)<=0,1,MIN(1,O85/N('Входные данные'!$G$47))) -> 1
B87: Расчётов уровня 1 | D87: =Воронка!$E$6*D86 -> 450 | E87: =Воронка!$E$6*E86 -> 900 | F87: =Воронка!$E$6*F86 -> 900 | G87: =Воронка!$E$6*G86 -> 900 | H87: =Воронка!$E$6*H86 -> 900 | I87: =Воронка!$E$6*I86 -> 900 | J87: =Воронка!$E$6*J86 -> 900 | K87: =Воронка!$E$6*K86 -> 900 | ... O87: =Воронка!$E$6*O86 -> 900 | P87: =SUM(D87:O87) -> 10350
B88: Инкрементальных заказов | D88: =D87*Воронка!$E$13*Воронка!$E$17 -> 5.625 | E88: =E87*Воронка!$E$13*Воронка!$E$17 -> 11.25 | F88: =F87*Воронка!$E$13*Воронка!$E$17 -> 11.25 | G88: =G87*Воронка!$E$13*Воронка!$E$17 -> 11.25 | H88: =H87*Воронка!$E$13*Воронка!$E$17 -> 11.25 | I88: =I87*Воронка!$E$13*Воронка!$E$17 -> 11.25 | J88: =J87*Воронка!$E$13*Воронка!$E$17 -> 11.25 | K88: =K87*Воронка!$E$13*Воронка!$E$17 -> 11.25 | ... O88: =O87*Воронка!$E$13*Воронка!$E$17 -> 11.25 | P88: =SUM(D88:O88) -> 129.375
B89: Выручка заказов в KMT (без НДС) | D89: =D88*'Юнит-экономика'!$E$8 -> 5625000 | E89: =E88*'Юнит-экономика'!$E$8 -> 11250000 | F89: =F88*'Юнит-экономика'!$E$8 -> 11250000 | G89: =G88*'Юнит-экономика'!$E$8 -> 11250000 | H89: =H88*'Юнит-экономика'!$E$8 -> 11250000 | I89: =I88*'Юнит-экономика'!$E$8 -> 11250000 | J89: =J88*'Юнит-экономика'!$E$8 -> 11250000 | K89: =K88*'Юнит-экономика'!$E$8 -> 11250000 | ... O89: =O88*'Юнит-экономика'!$E$8 -> 11250000 | P89: =SUM(D89:O89) -> 129375000
B90: Маржа проекта | D90: =D88*'Юнит-экономика'!$E$32 -> 2812500 | E90: =E88*'Юнит-экономика'!$E$32 -> 5625000 | F90: =F88*'Юнит-экономика'!$E$32 -> 5625000 | G90: =G88*'Юнит-экономика'!$E$32 -> 5625000 | H90: =H88*'Юнит-экономика'!$E$32 -> 5625000 | I90: =I88*'Юнит-экономика'!$E$32 -> 5625000 | J90: =J88*'Юнит-экономика'!$E$32 -> 5625000 | K90: =K88*'Юнит-экономика'!$E$32 -> 5625000 | ... O90: =O88*'Юнит-экономика'!$E$32 -> 5625000 | P90: =SUM(D90:O90) -> 64687500
B91: Операционные расходы (полные) | D91: =Сценарии_BEP!$E$15 -> 1000000 | E91: =Сценарии_BEP!$E$15 -> 1000000 | F91: =Сценарии_BEP!$E$15 -> 1000000 | G91: =Сценарии_BEP!$E$15 -> 1000000 | H91: =Сценарии_BEP!$E$15 -> 1000000 | I91: =Сценарии_BEP!$E$15 -> 1000000 | J91: =Сценарии_BEP!$E$15 -> 1000000 | K91: =Сценарии_BEP!$E$15 -> 1000000 | ... O91: =Сценарии_BEP!$E$15 -> 1000000 | P91: =SUM(D91:O91) -> 12000000
B92: Операционный результат | D92: =D90-D91 -> 1812500 | E92: =E90-E91 -> 4625000 | F92: =F90-F91 -> 4625000 | G92: =G90-G91 -> 4625000 | H92: =H90-H91 -> 4625000 | I92: =I90-I91 -> 4625000 | J92: =J90-J91 -> 4625000 | K92: =K90-K91 -> 4625000 | ... O92: =O90-O91 -> 4625000 | P92: =SUM(D92:O92) -> 52687500
B93: Накопленный операционный результат | C93: 0 | D93: =C93+D92 -> 1812500 | E93: =D93+E92 -> 6437500 | F93: =E93+F92 -> 11062500 | G93: =F93+G92 -> 15687500 | H93: =G93+H92 -> 20312500 | I93: =H93+I92 -> 24937500 | J93: =I93+J92 -> 29562500 | K93: =J93+K92 -> 34187500 | ... O93: =N93+O92 -> 52687500
B94: Разработка и запуск (разово) | C94: =-Сценарии_BEP!$E$24 -> 0 | D94: 0 | E94: 0 | F94: 0 | G94: 0 | H94: 0 | I94: 0 | J94: 0 | K94: 0 | L94: 0 | M94: 0 | N94: 0 | O94: 0 | P94: =C94 -> 0
B95: Накопленный итог с разработкой | C95: =C94 -> 0 | D95: =C95+D92+D94 -> 1812500 | E95: =D95+E92+E94 -> 6437500 | F95: =E95+F92+F94 -> 11062500 | G95: =F95+G92+G94 -> 15687500 | H95: =G95+H92+H94 -> 20312500 | I95: =H95+I92+I94 -> 24937500 | J95: =I95+J92+J94 -> 29562500 | K95: =J95+K92+K94 -> 34187500 | ... O95: =N95+O92+O94 -> 52687500
B96: Флаг: операции окупились (номер месяца) | D96: =IF(D93>=0,D85,"") -> 1 | E96: =IF(E93>=0,E85,"") -> 2 | F96: =IF(F93>=0,F85,"") -> 3 | G96: =IF(G93>=0,G85,"") -> 4 | H96: =IF(H93>=0,H85,"") -> 5 | I96: =IF(I93>=0,I85,"") -> 6 | J96: =IF(J93>=0,J85,"") -> 7 | K96: =IF(K93>=0,K85,"") -> 8 | ... O96: =IF(O93>=0,O85,"") -> 12
B97: Флаг: окупилось с разработкой (номер месяца) | D97: =IF(D95>=0,D85,"") -> 1 | E97: =IF(E95>=0,E85,"") -> 2 | F97: =IF(F95>=0,F85,"") -> 3 | G97: =IF(G95>=0,G85,"") -> 4 | H97: =IF(H95>=0,H85,"") -> 5 | I97: =IF(I95>=0,I85,"") -> 6 | J97: =IF(J95>=0,J85,"") -> 7 | K97: =IF(K95>=0,K85,"") -> 8 | ... O97: =IF(O95>=0,O85,"") -> 12

Sheet D10_I1
A1: Влияние решений D10 и I1: по два варианта, четыре сочетания
A2: Режим (без ramp). I1: A = только KMT, C = гибрид по принадлежности клиента. D10: б+ = блок KMT с контактами без формы, а = нейтральный текст. Варианты I1-B, I1-D и D10-в/г не моделируются.
B4: Сценарий: Пессимист
B5: Показатель | C5: I1=A · D10=б+ | D5: I1=A · D10=а | E5: I1=C · D10=б+ | F5: I1=C · D10=а
B6: Множитель потока D10 | C6: 1 | D6: =N('Входные данные'!$E$37) -> 0.25 | E6: 1 | F6: =N('Входные данные'!$E$37) -> 0.25
B7: Заказов в месяц | C7: =Воронка!$C$12*C6 -> 0.3 | D7: =Воронка!$C$12*D6 -> 0.075 | E7: =Воронка!$C$12*E6 -> 0.3 | F7: =Воронка!$C$12*F6 -> 0.075
B8: Маржа проекта на заказ | C8: ='Юнит-экономика'!$C$30 -> 300000 | D8: ='Юнит-экономика'!$C$30 -> 300000 | E8: ='Юнит-экономика'!$C$31 -> 240000 | F8: ='Юнит-экономика'!$C$31 -> 240000
B9: Маржа проекта в месяц | C9: =C7*C8 -> 90000 | D9: =D7*D8 -> 22500 | E9: =E7*E8 -> 72000 | F9: =F7*F8 -> 18000
B10: Полные операционные расходы в месяц | C10: =Сценарии_BEP!$C$15 -> 1000000 | D10: =Сценарии_BEP!$C$15 -> 1000000 | E10: =Сценарии_BEP!$C$15 -> 1000000 | F10: =Сценарии_BEP!$C$15 -> 1000000
B11: Результат в месяц | C11: =C9-C10 -> -910000 | D11: =D9-D10 -> -977500 | E11: =E9-E10 -> -928000 | F11: =F9-F10 -> -982000
B12: Разница с базовым сочетанием (A, б+) | C12: =C11-$C11 -> 0 | D12: =D11-$C11 -> -67500 | E12: =E11-$C11 -> -18000 | F12: =F11-$C11 -> -72000
B13: БУ: заказов в месяц | C13: =IF(C8>0,C10/C8,"нет БУ") -> 3.3333333 | D13: =IF(D8>0,D10/D8,"нет БУ") -> 3.3333333 | E13: =IF(E8>0,E10/E8,"нет БУ") -> 4.1666667 | F13: =IF(F8>0,F10/F8,"нет БУ") -> 4.1666667
B14: БУ: расчётов уровня 1 в месяц | C14: =IF(AND(ISNUMBER(C13),Воронка!$C$13*C6>0),C13/(Воронка!$C$13*C6),"нет БУ") -> 1111.1111 | D14: =IF(AND(ISNUMBER(D13),Воронка!$C$13*D6>0),D13/(Воронка!$C$13*D6),"нет БУ") -> 4444.4444 | E14: =IF(AND(ISNUMBER(E13),Воронка!$C$13*E6>0),E13/(Воронка!$C$13*E6),"нет БУ") -> 1388.8889 | F14: =IF(AND(ISNUMBER(F13),Воронка!$C$13*F6>0),F13/(Воронка!$C$13*F6),"нет БУ") -> 5555.5556
B15: Простая окупаемость разработки, мес | C15: =IF(Сценарии_BEP!$C$24<=0,"нет данных о разработке",IF(C11>0,Сценарии_BEP!$C$24/C11,"не окупается")) -> нет данных о разработке | D15: =IF(Сценарии_BEP!$C$24<=0,"нет данных о разработке",IF(D11>0,Сценарии_BEP!$C$24/D11,"не окупается")) -> нет данных о разработке | E15: =IF(Сценарии_BEP!$C$24<=0,"нет данных о разработке",IF(E11>0,Сценарии_BEP!$C$24/E11,"не окупается")) -> нет данных о разработке | F15: =IF(Сценарии_BEP!$C$24<=0,"нет данных о разработке",IF(F11>0,Сценарии_BEP!$C$24/F11,"не окупается")) -> нет данных о разработке
B17: Сценарий: База
B18: Показатель | C18: I1=A · D10=б+ | D18: I1=A · D10=а | E18: I1=C · D10=б+ | F18: I1=C · D10=а
B19: Множитель потока D10 | C19: 1 | D19: =N('Входные данные'!$F$37) -> 0.25 | E19: 1 | F19: =N('Входные данные'!$F$37) -> 0.25
B20: Заказов в месяц | C20: =Воронка!$D$12*C19 -> 2.1 | D20: =Воронка!$D$12*D19 -> 0.525 | E20: =Воронка!$D$12*E19 -> 2.1 | F20: =Воронка!$D$12*F19 -> 0.525
B21: Маржа проекта на заказ | C21: ='Юнит-экономика'!$D$30 -> 500000 | D21: ='Юнит-экономика'!$D$30 -> 500000 | E21: ='Юнит-экономика'!$D$31 -> 400000 | F21: ='Юнит-экономика'!$D$31 -> 400000
B22: Маржа проекта в месяц | C22: =C20*C21 -> 1050000 | D22: =D20*D21 -> 262500 | E22: =E20*E21 -> 840000 | F22: =F20*F21 -> 210000
B23: Полные операционные расходы в месяц | C23: =Сценарии_BEP!$D$15 -> 1000000 | D23: =Сценарии_BEP!$D$15 -> 1000000 | E23: =Сценарии_BEP!$D$15 -> 1000000 | F23: =Сценарии_BEP!$D$15 -> 1000000
B24: Результат в месяц | C24: =C22-C23 -> 50000 | D24: =D22-D23 -> -737500 | E24: =E22-E23 -> -160000 | F24: =F22-F23 -> -790000
B25: Разница с базовым сочетанием (A, б+) | C25: =C24-$C24 -> 0 | D25: =D24-$C24 -> -787500 | E25: =E24-$C24 -> -210000 | F25: =F24-$C24 -> -840000
B26: БУ: заказов в месяц | C26: =IF(C21>0,C23/C21,"нет БУ") -> 2 | D26: =IF(D21>0,D23/D21,"нет БУ") -> 2 | E26: =IF(E21>0,E23/E21,"нет БУ") -> 2.5 | F26: =IF(F21>0,F23/F21,"нет БУ") -> 2.5
B27: БУ: расчётов уровня 1 в месяц | C27: =IF(AND(ISNUMBER(C26),Воронка!$D$13*C19>0),C26/(Воронка!$D$13*C19),"нет БУ") -> 285.71429 | D27: =IF(AND(ISNUMBER(D26),Воронка!$D$13*D19>0),D26/(Воронка!$D$13*D19),"нет БУ") -> 1142.8571 | E27: =IF(AND(ISNUMBER(E26),Воронка!$D$13*E19>0),E26/(Воронка!$D$13*E19),"нет БУ") -> 357.14286 | F27: =IF(AND(ISNUMBER(F26),Воронка!$D$13*F19>0),F26/(Воронка!$D$13*F19),"нет БУ") -> 1428.5714
B28: Простая окупаемость разработки, мес | C28: =IF(Сценарии_BEP!$D$24<=0,"нет данных о разработке",IF(C24>0,Сценарии_BEP!$D$24/C24,"не окупается")) -> нет данных о разработке | D28: =IF(Сценарии_BEP!$D$24<=0,"нет данных о разработке",IF(D24>0,Сценарии_BEP!$D$24/D24,"не окупается")) -> нет данных о разработке | E28: =IF(Сценарии_BEP!$D$24<=0,"нет данных о разработке",IF(E24>0,Сценарии_BEP!$D$24/E24,"не окупается")) -> нет данных о разработке | F28: =IF(Сценарии_BEP!$D$24<=0,"нет данных о разработке",IF(F24>0,Сценарии_BEP!$D$24/F24,"не окупается")) -> нет данных о разработке
B30: Сценарий: Оптимист
B31: Показатель | C31: I1=A · D10=б+ | D31: I1=A · D10=а | E31: I1=C · D10=б+ | F31: I1=C · D10=а
B32: Множитель потока D10 | C32: 1 | D32: =N('Входные данные'!$G$37) -> 0.25 | E32: 1 | F32: =N('Входные данные'!$G$37) -> 0.25
B33: Заказов в месяц | C33: =Воронка!$E$12*C32 -> 11.25 | D33: =Воронка!$E$12*D32 -> 2.8125 | E33: =Воронка!$E$12*E32 -> 11.25 | F33: =Воронка!$E$12*F32 -> 2.8125
B34: Маржа проекта на заказ | C34: ='Юнит-экономика'!$E$30 -> 500000 | D34: ='Юнит-экономика'!$E$30 -> 500000 | E34: ='Юнит-экономика'!$E$31 -> 400000 | F34: ='Юнит-экономика'!$E$31 -> 400000
B35: Маржа проекта в месяц | C35: =C33*C34 -> 5625000 | D35: =D33*D34 -> 1406250 | E35: =E33*E34 -> 4500000 | F35: =F33*F34 -> 1125000
B36: Полные операционные расходы в месяц | C36: =Сценарии_BEP!$E$15 -> 1000000 | D36: =Сценарии_BEP!$E$15 -> 1000000 | E36: =Сценарии_BEP!$E$15 -> 1000000 | F36: =Сценарии_BEP!$E$15 -> 1000000
B37: Результат в месяц | C37: =C35-C36 -> 4625000 | D37: =D35-D36 -> 406250 | E37: =E35-E36 -> 3500000 | F37: =F35-F36 -> 125000
B38: Разница с базовым сочетанием (A, б+) | C38: =C37-$C37 -> 0 | D38: =D37-$C37 -> -4218750 | E38: =E37-$C37 -> -1125000 | F38: =F37-$C37 -> -4500000
B39: БУ: заказов в месяц | C39: =IF(C34>0,C36/C34,"нет БУ") -> 2 | D39: =IF(D34>0,D36/D34,"нет БУ") -> 2 | E39: =IF(E34>0,E36/E34,"нет БУ") -> 2.5 | F39: =IF(F34>0,F36/F34,"нет БУ") -> 2.5
B40: БУ: расчётов уровня 1 в месяц | C40: =IF(AND(ISNUMBER(C39),Воронка!$E$13*C32>0),C39/(Воронка!$E$13*C32),"нет БУ") -> 160 | D40: =IF(AND(ISNUMBER(D39),Воронка!$E$13*D32>0),D39/(Воронка!$E$13*D32),"нет БУ") -> 640 | E40: =IF(AND(ISNUMBER(E39),Воронка!$E$13*E32>0),E39/(Воронка!$E$13*E32),"нет БУ") -> 200 | F40: =IF(AND(ISNUMBER(F39),Воронка!$E$13*F32>0),F39/(Воронка!$E$13*F32),"нет БУ") -> 800
B41: Простая окупаемость разработки, мес | C41: =IF(Сценарии_BEP!$E$24<=0,"нет данных о разработке",IF(C37>0,Сценарии_BEP!$E$24/C37,"не окупается")) -> нет данных о разработке | D41: =IF(Сценарии_BEP!$E$24<=0,"нет данных о разработке",IF(D37>0,Сценарии_BEP!$E$24/D37,"не окупается")) -> нет данных о разработке | E41: =IF(Сценарии_BEP!$E$24<=0,"нет данных о разработке",IF(E37>0,Сценарии_BEP!$E$24/E37,"не окупается")) -> нет данных о разработке | F41: =IF(Сценарии_BEP!$E$24<=0,"нет данных о разработке",IF(F37>0,Сценарии_BEP!$E$24/F37,"не окупается")) -> нет данных о разработке
B43: Цена решений (маржа проекта, сум в месяц)
B44: Показатель | C44: Пессимист | D44: База | E44: Оптимист | F44: Как читать
B45: Цена нейтрального текста при I1=A (б+ минус а) | C45: =$C$9-$D$9 -> 67500 | D45: =$C$22-$D$22 -> 787500 | E45: =$C$35-$D$35 -> 4218750 | F45: Сколько маржи в месяц теряется от отказа от блока KMT. Выгода нейтральности не измерена
B46: Цена гибрида I1=C при D10=б+ (A минус C) | C46: =$C$9-$E$9 -> 18000 | D46: =$C$22-$E$22 -> 210000 | E46: =$C$35-$E$35 -> 1125000 | F46: Сколько маржи уходит партнёрам. Гибрид выгоден, только если партнёры приведут дополнительный поток
B48: Не смоделировано: форма заказа (D10-в, после A4–A8), список оценщиков (D10-г), публичный пул с комиссией (I1-B), белая марка (I1-D).
B49: Заглушки q_c и m_a: заменить данными (клики по блоку KMT на первых 100 результатах; доля заказов по ссылкам партнёров).
B50: Выгода нейтральности (доверие Общества и партнёров) в деньгах не оценена: данных нет.

Sheet Чувствительность
A1: Чувствительность
A2: Оси сеток (синий шрифт) — перебор для чувствительности, не оценки. Все ячейки результатов — формулы; расчёт идёт от столбца «База».
B4: 1. Заказов в месяц (База): конверсия расчёт→интерес × интерес→заказ
B5: строки: расчёт→интерес | столбцы: интерес→заказ
C6: 0.01 | D6: 0.02 | E6: 0.035 | F6: 0.05 | G6: 0.07
B7: 0.1 | C7: =Воронка!$D$6*$B7*C$6*Воронка!$D$11*Воронка!$D$17 -> 0.3 | D7: =Воронка!$D$6*$B7*D$6*Воронка!$D$11*Воронка!$D$17 -> 0.6 | E7: =Воронка!$D$6*$B7*E$6*Воронка!$D$11*Воронка!$D$17 -> 1.05 | F7: =Воронка!$D$6*$B7*F$6*Воронка!$D$11*Воронка!$D$17 -> 1.5 | G7: =Воронка!$D$6*$B7*G$6*Воронка!$D$11*Воронка!$D$17 -> 2.1
B8: 0.15 | C8: =Воронка!$D$6*$B8*C$6*Воронка!$D$11*Воронка!$D$17 -> 0.45 | D8: =Воронка!$D$6*$B8*D$6*Воронка!$D$11*Воронка!$D$17 -> 0.9 | E8: =Воронка!$D$6*$B8*E$6*Воронка!$D$11*Воронка!$D$17 -> 1.575 | F8: =Воронка!$D$6*$B8*F$6*Воронка!$D$11*Воронка!$D$17 -> 2.25 | G8: =Воронка!$D$6*$B8*G$6*Воронка!$D$11*Воронка!$D$17 -> 3.15
B9: 0.2 | C9: =Воронка!$D$6*$B9*C$6*Воронка!$D$11*Воронка!$D$17 -> 0.6 | D9: =Воронка!$D$6*$B9*D$6*Воронка!$D$11*Воронка!$D$17 -> 1.2 | E9: =Воронка!$D$6*$B9*E$6*Воронка!$D$11*Воронка!$D$17 -> 2.1 | F9: =Воронка!$D$6*$B9*F$6*Воронка!$D$11*Воронка!$D$17 -> 3 | G9: =Воронка!$D$6*$B9*G$6*Воронка!$D$11*Воронка!$D$17 -> 4.2
B10: 0.25 | C10: =Воронка!$D$6*$B10*C$6*Воронка!$D$11*Воронка!$D$17 -> 0.75 | D10: =Воронка!$D$6*$B10*D$6*Воронка!$D$11*Воронка!$D$17 -> 1.5 | E10: =Воронка!$D$6*$B10*E$6*Воронка!$D$11*Воронка!$D$17 -> 2.625 | F10: =Воронка!$D$6*$B10*F$6*Воронка!$D$11*Воронка!$D$17 -> 3.75 | G10: =Воронка!$D$6*$B10*G$6*Воронка!$D$11*Воронка!$D$17 -> 5.25
B11: 0.3 | C11: =Воронка!$D$6*$B11*C$6*Воронка!$D$11*Воронка!$D$17 -> 0.9 | D11: =Воронка!$D$6*$B11*D$6*Воронка!$D$11*Воронка!$D$17 -> 1.8 | E11: =Воронка!$D$6*$B11*E$6*Воронка!$D$11*Воронка!$D$17 -> 3.15 | F11: =Воронка!$D$6*$B11*F$6*Воронка!$D$11*Воронка!$D$17 -> 4.5 | G11: =Воронка!$D$6*$B11*G$6*Воронка!$D$11*Воронка!$D$17 -> 6.3
B12: Объём расчётов — заглушка
B14: 2. Результат проекта в месяц (База, с полными расходами), сум
B15: строки: расчёт→интерес | столбцы: интерес→заказ
C16: 0.01 | D16: 0.02 | E16: 0.035 | F16: 0.05 | G16: 0.07
B17: 0.1 | C17: =Воронка!$D$6*$B17*C$16*Воронка!$D$11*Воронка!$D$17*'Юнит-экономика'!$D$32-Сценарии_BEP!$D$15 -> -850000 | D17: =Воронка!$D$6*$B17*D$16*Воронка!$D$11*Воронка!$D$17*'Юнит-экономика'!$D$32-Сценарии_BEP!$D$15 -> -700000 | E17: =Воронка!$D$6*$B17*E$16*Воронка!$D$11*Воронка!$D$17*'Юнит-экономика'!$D$32-Сценарии_BEP!$D$15 -> -475000 | F17: =Воронка!$D$6*$B17*F$16*Воронка!$D$11*Воронка!$D$17*'Юнит-экономика'!$D$32-Сценарии_BEP!$D$15 -> -250000 | G17: =Воронка!$D$6*$B17*G$16*Воронка!$D$11*Воронка!$D$17*'Юнит-экономика'!$D$32-Сценарии_BEP!$D$15 -> 50000
B18: 0.15 | C18: =Воронка!$D$6*$B18*C$16*Воронка!$D$11*Воронка!$D$17*'Юнит-экономика'!$D$32-Сценарии_BEP!$D$15 -> -775000 | D18: =Воронка!$D$6*$B18*D$16*Воронка!$D$11*Воронка!$D$17*'Юнит-экономика'!$D$32-Сценарии_BEP!$D$15 -> -550000 | E18: =Воронка!$D$6*$B18*E$16*Воронка!$D$11*Воронка!$D$17*'Юнит-экономика'!$D$32-Сценарии_BEP!$D$15 -> -212500 | F18: =Воронка!$D$6*$B18*F$16*Воронка!$D$11*Воронка!$D$17*'Юнит-экономика'!$D$32-Сценарии_BEP!$D$15 -> 125000 | G18: =Воронка!$D$6*$B18*G$16*Воронка!$D$11*Воронка!$D$17*'Юнит-экономика'!$D$32-Сценарии_BEP!$D$15 -> 575000
B19: 0.2 | C19: =Воронка!$D$6*$B19*C$16*Воронка!$D$11*Воронка!$D$17*'Юнит-экономика'!$D$32-Сценарии_BEP!$D$15 -> -700000 | D19: =Воронка!$D$6*$B19*D$16*Воронка!$D$11*Воронка!$D$17*'Юнит-экономика'!$D$32-Сценарии_BEP!$D$15 -> -400000 | E19: =Воронка!$D$6*$B19*E$16*Воронка!$D$11*Воронка!$D$17*'Юнит-экономика'!$D$32-Сценарии_BEP!$D$15 -> 50000 | F19: =Воронка!$D$6*$B19*F$16*Воронка!$D$11*Воронка!$D$17*'Юнит-экономика'!$D$32-Сценарии_BEP!$D$15 -> 500000 | G19: =Воронка!$D$6*$B19*G$16*Воронка!$D$11*Воронка!$D$17*'Юнит-экономика'!$D$32-Сценарии_BEP!$D$15 -> 1100000
B20: 0.25 | C20: =Воронка!$D$6*$B20*C$16*Воронка!$D$11*Воронка!$D$17*'Юнит-экономика'!$D$32-Сценарии_BEP!$D$15 -> -625000 | D20: =Воронка!$D$6*$B20*D$16*Воронка!$D$11*Воронка!$D$17*'Юнит-экономика'!$D$32-Сценарии_BEP!$D$15 -> -250000 | E20: =Воронка!$D$6*$B20*E$16*Воронка!$D$11*Воронка!$D$17*'Юнит-экономика'!$D$32-Сценарии_BEP!$D$15 -> 312500 | F20: =Воронка!$D$6*$B20*F$16*Воронка!$D$11*Воронка!$D$17*'Юнит-экономика'!$D$32-Сценарии_BEP!$D$15 -> 875000 | G20: =Воронка!$D$6*$B20*G$16*Воронка!$D$11*Воронка!$D$17*'Юнит-экономика'!$D$32-Сценарии_BEP!$D$15 -> 1625000
B21: 0.3 | C21: =Воронка!$D$6*$B21*C$16*Воронка!$D$11*Воронка!$D$17*'Юнит-экономика'!$D$32-Сценарии_BEP!$D$15 -> -550000 | D21: =Воронка!$D$6*$B21*D$16*Воронка!$D$11*Воронка!$D$17*'Юнит-экономика'!$D$32-Сценарии_BEP!$D$15 -> -100000 | E21: =Воронка!$D$6*$B21*E$16*Воронка!$D$11*Воронка!$D$17*'Юнит-экономика'!$D$32-Сценарии_BEP!$D$15 -> 575000 | F21: =Воронка!$D$6*$B21*F$16*Воронка!$D$11*Воронка!$D$17*'Юнит-экономика'!$D$32-Сценарии_BEP!$D$15 -> 1250000 | G21: =Воронка!$D$6*$B21*G$16*Воронка!$D$11*Воронка!$D$17*'Юнит-экономика'!$D$32-Сценарии_BEP!$D$15 -> 2150000
B23: 3. БУ: заказов в месяц
B24: строки: маржа проекта на заказ, сум | столбцы: операционные расходы в месяц, сум
C25: 1000000 | D25: 1500000 | E25: 2000000 | F25: 3000000 | G25: 5000000
B26: 200000 | C26: =IF($B26>0,C$25/$B26,"нет БУ") -> 5 | D26: =IF($B26>0,D$25/$B26,"нет БУ") -> 7.5 | E26: =IF($B26>0,E$25/$B26,"нет БУ") -> 10 | F26: =IF($B26>0,F$25/$B26,"нет БУ") -> 15 | G26: =IF($B26>0,G$25/$B26,"нет БУ") -> 25
B27: 300000 | C27: =IF($B27>0,C$25/$B27,"нет БУ") -> 3.3333333 | D27: =IF($B27>0,D$25/$B27,"нет БУ") -> 5 | E27: =IF($B27>0,E$25/$B27,"нет БУ") -> 6.6666667 | F27: =IF($B27>0,F$25/$B27,"нет БУ") -> 10 | G27: =IF($B27>0,G$25/$B27,"нет БУ") -> 16.666667
B28: 400000 | C28: =IF($B28>0,C$25/$B28,"нет БУ") -> 2.5 | D28: =IF($B28>0,D$25/$B28,"нет БУ") -> 3.75 | E28: =IF($B28>0,E$25/$B28,"нет БУ") -> 5 | F28: =IF($B28>0,F$25/$B28,"нет БУ") -> 7.5 | G28: =IF($B28>0,G$25/$B28,"нет БУ") -> 12.5
B29: 500000 | C29: =IF($B29>0,C$25/$B29,"нет БУ") -> 2 | D29: =IF($B29>0,D$25/$B29,"нет БУ") -> 3 | E29: =IF($B29>0,E$25/$B29,"нет БУ") -> 4 | F29: =IF($B29>0,F$25/$B29,"нет БУ") -> 6 | G29: =IF($B29>0,G$25/$B29,"нет БУ") -> 10
B30: 600000 | C30: =IF($B30>0,C$25/$B30,"нет БУ") -> 1.6666667 | D30: =IF($B30>0,D$25/$B30,"нет БУ") -> 2.5 | E30: =IF($B30>0,E$25/$B30,"нет БУ") -> 3.3333333 | F30: =IF($B30>0,F$25/$B30,"нет БУ") -> 5 | G30: =IF($B30>0,G$25/$B30,"нет БУ") -> 8.3333333
B31: Столбец 1 млн сум = только хостинг и сервисы
B33: 4. БУ: расчётов уровня 1 в месяц при сквозной конверсии База
B34: строки: маржа проекта на заказ, сум | столбцы: операционные расходы в месяц, сум
C35: 1000000 | D35: 1500000 | E35: 2000000 | F35: 3000000 | G35: 5000000
B36: 200000 | C36: =IF(AND($B36>0,Сценарии_BEP!$D$28>0),C$35/$B36/Сценарии_BEP!$D$28,"нет БУ") -> 714.28571 | D36: =IF(AND($B36>0,Сценарии_BEP!$D$28>0),D$35/$B36/Сценарии_BEP!$D$28,"нет БУ") -> 1071.4286 | E36: =IF(AND($B36>0,Сценарии_BEP!$D$28>0),E$35/$B36/Сценарии_BEP!$D$28,"нет БУ") -> 1428.5714 | F36: =IF(AND($B36>0,Сценарии_BEP!$D$28>0),F$35/$B36/Сценарии_BEP!$D$28,"нет БУ") -> 2142.8571 | G36: =IF(AND($B36>0,Сценарии_BEP!$D$28>0),G$35/$B36/Сценарии_BEP!$D$28,"нет БУ") -> 3571.4286
B37: 300000 | C37: =IF(AND($B37>0,Сценарии_BEP!$D$28>0),C$35/$B37/Сценарии_BEP!$D$28,"нет БУ") -> 476.19048 | D37: =IF(AND($B37>0,Сценарии_BEP!$D$28>0),D$35/$B37/Сценарии_BEP!$D$28,"нет БУ") -> 714.28571 | E37: =IF(AND($B37>0,Сценарии_BEP!$D$28>0),E$35/$B37/Сценарии_BEP!$D$28,"нет БУ") -> 952.38095 | F37: =IF(AND($B37>0,Сценарии_BEP!$D$28>0),F$35/$B37/Сценарии_BEP!$D$28,"нет БУ") -> 1428.5714 | G37: =IF(AND($B37>0,Сценарии_BEP!$D$28>0),G$35/$B37/Сценарии_BEP!$D$28,"нет БУ") -> 2380.9524
B38: 400000 | C38: =IF(AND($B38>0,Сценарии_BEP!$D$28>0),C$35/$B38/Сценарии_BEP!$D$28,"нет БУ") -> 357.14286 | D38: =IF(AND($B38>0,Сценарии_BEP!$D$28>0),D$35/$B38/Сценарии_BEP!$D$28,"нет БУ") -> 535.71429 | E38: =IF(AND($B38>0,Сценарии_BEP!$D$28>0),E$35/$B38/Сценарии_BEP!$D$28,"нет БУ") -> 714.28571 | F38: =IF(AND($B38>0,Сценарии_BEP!$D$28>0),F$35/$B38/Сценарии_BEP!$D$28,"нет БУ") -> 1071.4286 | G38: =IF(AND($B38>0,Сценарии_BEP!$D$28>0),G$35/$B38/Сценарии_BEP!$D$28,"нет БУ") -> 1785.7143
B39: 500000 | C39: =IF(AND($B39>0,Сценарии_BEP!$D$28>0),C$35/$B39/Сценарии_BEP!$D$28,"нет БУ") -> 285.71429 | D39: =IF(AND($B39>0,Сценарии_BEP!$D$28>0),D$35/$B39/Сценарии_BEP!$D$28,"нет БУ") -> 428.57143 | E39: =IF(AND($B39>0,Сценарии_BEP!$D$28>0),E$35/$B39/Сценарии_BEP!$D$28,"нет БУ") -> 571.42857 | F39: =IF(AND($B39>0,Сценарии_BEP!$D$28>0),F$35/$B39/Сценарии_BEP!$D$28,"нет БУ") -> 857.14286 | G39: =IF(AND($B39>0,Сценарии_BEP!$D$28>0),G$35/$B39/Сценарии_BEP!$D$28,"нет БУ") -> 1428.5714
B40: 600000 | C40: =IF(AND($B40>0,Сценарии_BEP!$D$28>0),C$35/$B40/Сценарии_BEP!$D$28,"нет БУ") -> 238.09524 | D40: =IF(AND($B40>0,Сценарии_BEP!$D$28>0),D$35/$B40/Сценарии_BEP!$D$28,"нет БУ") -> 357.14286 | E40: =IF(AND($B40>0,Сценарии_BEP!$D$28>0),E$35/$B40/Сценарии_BEP!$D$28,"нет БУ") -> 476.19048 | F40: =IF(AND($B40>0,Сценарии_BEP!$D$28>0),F$35/$B40/Сценарии_BEP!$D$28,"нет БУ") -> 714.28571 | G40: =IF(AND($B40>0,Сценарии_BEP!$D$28>0),G$35/$B40/Сценарии_BEP!$D$28,"нет БУ") -> 1190.4762
B42: 5. Допустимая стоимость привлечения на один расчёт, сум (потолок из «Входные данные»)
B43: строки: маржа заказа после комиссии, сум | столбцы: сквозная конверсия расчёт→заказ
C44: 0.003 | D44: 0.007 | E44: 0.0125 | F44: 0.02
B45: 200000 | C45: =$B45*N('Входные данные'!$F$39)*C$44 -> 120 | D45: =$B45*N('Входные данные'!$F$39)*D$44 -> 280 | E45: =$B45*N('Входные данные'!$F$39)*E$44 -> 500 | F45: =$B45*N('Входные данные'!$F$39)*F$44 -> 800
B46: 300000 | C46: =$B46*N('Входные данные'!$F$39)*C$44 -> 180 | D46: =$B46*N('Входные данные'!$F$39)*D$44 -> 420 | E46: =$B46*N('Входные данные'!$F$39)*E$44 -> 750 | F46: =$B46*N('Входные данные'!$F$39)*F$44 -> 1200
B47: 400000 | C47: =$B47*N('Входные данные'!$F$39)*C$44 -> 240 | D47: =$B47*N('Входные данные'!$F$39)*D$44 -> 560 | E47: =$B47*N('Входные данные'!$F$39)*E$44 -> 1000 | F47: =$B47*N('Входные данные'!$F$39)*F$44 -> 1600
B48: 500000 | C48: =$B48*N('Входные данные'!$F$39)*C$44 -> 300 | D48: =$B48*N('Входные данные'!$F$39)*D$44 -> 700 | E48: =$B48*N('Входные данные'!$F$39)*E$44 -> 1250 | F48: =$B48*N('Входные данные'!$F$39)*F$44 -> 2000
B49: 600000 | C49: =$B49*N('Входные данные'!$F$39)*C$44 -> 360 | D49: =$B49*N('Входные данные'!$F$39)*D$44 -> 840 | E49: =$B49*N('Входные данные'!$F$39)*E$44 -> 1500 | F49: =$B49*N('Входные данные'!$F$39)*F$44 -> 2400
B50: Сравнить с ценой клика (не проверена, нужно от Темура)
B52: 6. Постоянный труд команды, сум в месяц, при одной ставке для всех (База)
B53: строки: единицы часов: 1 неделя, 2 месяц, 3 весь этап | столбцы: ставка, сум/час
C54: 0 | D54: 25000 | E54: 50000 | F54: 100000 | G54: 200000
B55: 1 | C55: =IF($B55=1,(N('Входные данные'!$F$54)*(1-N('Входные данные'!$F$60))+N('Входные данные'!$F$55)*(1-N('Входные данные'!$F$61))+N('Входные данные'!$F$56)*(1-N('Входные данные'!$F$62)))*52/12*C$54,IF($B55=2,(N('Входные данные'!$F$54)*(1-N('Входные данные'!$F$60))+N('Входные данные'!$F$55)*(1-N('Входные данные'!$F$61))+N('Входные данные'!$F$56)*(1-N('Входные данные'!$F$62)))*C$54,IF(N('Входные данные'!$F$53)>0,(N('Входные данные'!$F$54)*(1-N('Входные данные'!$F$60))+N('Входные данные'!$F$55)*(1-N('Входные данные'!$F$61))+N('Входные данные'!$F$56)*(1-N('Входные данные'!$F$62)))/N('Входные данные'!$F$53)*C$54,"нужна длительность этапа"))) -> 0 | D55: =IF($B55=1,(N('Входные данные'!$F$54)*(1-N('Входные данные'!$F$60))+N('Входные данные'!$F$55)*(1-N('Входные данные'!$F$61))+N('Входные данные'!$F$56)*(1-N('Входные данные'!$F$62)))*52/12*D$54,IF($B55=2,(N('Входные данные'!$F$54)*(1-N('Входные данные'!$F$60))+N('Входные данные'!$F$55)*(1-N('Входные данные'!$F$61))+N('Входные данные'!$F$56)*(1-N('Входные данные'!$F$62)))*D$54,IF(N('Входные данные'!$F$53)>0,(N('Входные данные'!$F$54)*(1-N('Входные данные'!$F$60))+N('Входные данные'!$F$55)*(1-N('Входные данные'!$F$61))+N('Входные данные'!$F$56)*(1-N('Входные данные'!$F$62)))/N('Входные данные'!$F$53)*D$54,"нужна длительность этапа"))) -> 1895833.3 | E55: =IF($B55=1,(N('Входные данные'!$F$54)*(1-N('Входные данные'!$F$60))+N('Входные данные'!$F$55)*(1-N('Входные данные'!$F$61))+N('Входные данные'!$F$56)*(1-N('Входные данные'!$F$62)))*52/12*E$54,IF($B55=2,(N('Входные данные'!$F$54)*(1-N('Входные данные'!$F$60))+N('Входные данные'!$F$55)*(1-N('Входные данные'!$F$61))+N('Входные данные'!$F$56)*(1-N('Входные данные'!$F$62)))*E$54,IF(N('Входные данные'!$F$53)>0,(N('Входные данные'!$F$54)*(1-N('Входные данные'!$F$60))+N('Входные данные'!$F$55)*(1-N('Входные данные'!$F$61))+N('Входные данные'!$F$56)*(1-N('Входные данные'!$F$62)))/N('Входные данные'!$F$53)*E$54,"нужна длительность этапа"))) -> 3791666.7 | F55: =IF($B55=1,(N('Входные данные'!$F$54)*(1-N('Входные данные'!$F$60))+N('Входные данные'!$F$55)*(1-N('Входные данные'!$F$61))+N('Входные данные'!$F$56)*(1-N('Входные данные'!$F$62)))*52/12*F$54,IF($B55=2,(N('Входные данные'!$F$54)*(1-N('Входные данные'!$F$60))+N('Входные данные'!$F$55)*(1-N('Входные данные'!$F$61))+N('Входные данные'!$F$56)*(1-N('Входные данные'!$F$62)))*F$54,IF(N('Входные данные'!$F$53)>0,(N('Входные данные'!$F$54)*(1-N('Входные данные'!$F$60))+N('Входные данные'!$F$55)*(1-N('Входные данные'!$F$61))+N('Входные данные'!$F$56)*(1-N('Входные данные'!$F$62)))/N('Входные данные'!$F$53)*F$54,"нужна длительность этапа"))) -> 7583333.3 | G55: =IF($B55=1,(N('Входные данные'!$F$54)*(1-N('Входные данные'!$F$60))+N('Входные данные'!$F$55)*(1-N('Входные данные'!$F$61))+N('Входные данные'!$F$56)*(1-N('Входные данные'!$F$62)))*52/12*G$54,IF($B55=2,(N('Входные данные'!$F$54)*(1-N('Входные данные'!$F$60))+N('Входные данные'!$F$55)*(1-N('Входные данные'!$F$61))+N('Входные данные'!$F$56)*(1-N('Входные данные'!$F$62)))*G$54,IF(N('Входные данные'!$F$53)>0,(N('Входные данные'!$F$54)*(1-N('Входные данные'!$F$60))+N('Входные данные'!$F$55)*(1-N('Входные данные'!$F$61))+N('Входные данные'!$F$56)*(1-N('Входные данные'!$F$62)))/N('Входные данные'!$F$53)*G$54,"нужна длительность этапа"))) -> 15166667
B56: 2 | C56: =IF($B56=1,(N('Входные данные'!$F$54)*(1-N('Входные данные'!$F$60))+N('Входные данные'!$F$55)*(1-N('Входные данные'!$F$61))+N('Входные данные'!$F$56)*(1-N('Входные данные'!$F$62)))*52/12*C$54,IF($B56=2,(N('Входные данные'!$F$54)*(1-N('Входные данные'!$F$60))+N('Входные данные'!$F$55)*(1-N('Входные данные'!$F$61))+N('Входные данные'!$F$56)*(1-N('Входные данные'!$F$62)))*C$54,IF(N('Входные данные'!$F$53)>0,(N('Входные данные'!$F$54)*(1-N('Входные данные'!$F$60))+N('Входные данные'!$F$55)*(1-N('Входные данные'!$F$61))+N('Входные данные'!$F$56)*(1-N('Входные данные'!$F$62)))/N('Входные данные'!$F$53)*C$54,"нужна длительность этапа"))) -> 0 | D56: =IF($B56=1,(N('Входные данные'!$F$54)*(1-N('Входные данные'!$F$60))+N('Входные данные'!$F$55)*(1-N('Входные данные'!$F$61))+N('Входные данные'!$F$56)*(1-N('Входные данные'!$F$62)))*52/12*D$54,IF($B56=2,(N('Входные данные'!$F$54)*(1-N('Входные данные'!$F$60))+N('Входные данные'!$F$55)*(1-N('Входные данные'!$F$61))+N('Входные данные'!$F$56)*(1-N('Входные данные'!$F$62)))*D$54,IF(N('Входные данные'!$F$53)>0,(N('Входные данные'!$F$54)*(1-N('Входные данные'!$F$60))+N('Входные данные'!$F$55)*(1-N('Входные данные'!$F$61))+N('Входные данные'!$F$56)*(1-N('Входные данные'!$F$62)))/N('Входные данные'!$F$53)*D$54,"нужна длительность этапа"))) -> 437500 | E56: =IF($B56=1,(N('Входные данные'!$F$54)*(1-N('Входные данные'!$F$60))+N('Входные данные'!$F$55)*(1-N('Входные данные'!$F$61))+N('Входные данные'!$F$56)*(1-N('Входные данные'!$F$62)))*52/12*E$54,IF($B56=2,(N('Входные данные'!$F$54)*(1-N('Входные данные'!$F$60))+N('Входные данные'!$F$55)*(1-N('Входные данные'!$F$61))+N('Входные данные'!$F$56)*(1-N('Входные данные'!$F$62)))*E$54,IF(N('Входные данные'!$F$53)>0,(N('Входные данные'!$F$54)*(1-N('Входные данные'!$F$60))+N('Входные данные'!$F$55)*(1-N('Входные данные'!$F$61))+N('Входные данные'!$F$56)*(1-N('Входные данные'!$F$62)))/N('Входные данные'!$F$53)*E$54,"нужна длительность этапа"))) -> 875000 | F56: =IF($B56=1,(N('Входные данные'!$F$54)*(1-N('Входные данные'!$F$60))+N('Входные данные'!$F$55)*(1-N('Входные данные'!$F$61))+N('Входные данные'!$F$56)*(1-N('Входные данные'!$F$62)))*52/12*F$54,IF($B56=2,(N('Входные данные'!$F$54)*(1-N('Входные данные'!$F$60))+N('Входные данные'!$F$55)*(1-N('Входные данные'!$F$61))+N('Входные данные'!$F$56)*(1-N('Входные данные'!$F$62)))*F$54,IF(N('Входные данные'!$F$53)>0,(N('Входные данные'!$F$54)*(1-N('Входные данные'!$F$60))+N('Входные данные'!$F$55)*(1-N('Входные данные'!$F$61))+N('Входные данные'!$F$56)*(1-N('Входные данные'!$F$62)))/N('Входные данные'!$F$53)*F$54,"нужна длительность этапа"))) -> 1750000 | G56: =IF($B56=1,(N('Входные данные'!$F$54)*(1-N('Входные данные'!$F$60))+N('Входные данные'!$F$55)*(1-N('Входные данные'!$F$61))+N('Входные данные'!$F$56)*(1-N('Входные данные'!$F$62)))*52/12*G$54,IF($B56=2,(N('Входные данные'!$F$54)*(1-N('Входные данные'!$F$60))+N('Входные данные'!$F$55)*(1-N('Входные данные'!$F$61))+N('Входные данные'!$F$56)*(1-N('Входные данные'!$F$62)))*G$54,IF(N('Входные данные'!$F$53)>0,(N('Входные данные'!$F$54)*(1-N('Входные данные'!$F$60))+N('Входные данные'!$F$55)*(1-N('Входные данные'!$F$61))+N('Входные данные'!$F$56)*(1-N('Входные данные'!$F$62)))/N('Входные данные'!$F$53)*G$54,"нужна длительность этапа"))) -> 3500000
B57: 3 | C57: =IF($B57=1,(N('Входные данные'!$F$54)*(1-N('Входные данные'!$F$60))+N('Входные данные'!$F$55)*(1-N('Входные данные'!$F$61))+N('Входные данные'!$F$56)*(1-N('Входные данные'!$F$62)))*52/12*C$54,IF($B57=2,(N('Входные данные'!$F$54)*(1-N('Входные данные'!$F$60))+N('Входные данные'!$F$55)*(1-N('Входные данные'!$F$61))+N('Входные данные'!$F$56)*(1-N('Входные данные'!$F$62)))*C$54,IF(N('Входные данные'!$F$53)>0,(N('Входные данные'!$F$54)*(1-N('Входные данные'!$F$60))+N('Входные данные'!$F$55)*(1-N('Входные данные'!$F$61))+N('Входные данные'!$F$56)*(1-N('Входные данные'!$F$62)))/N('Входные данные'!$F$53)*C$54,"нужна длительность этапа"))) -> нужна длительность этапа | D57: =IF($B57=1,(N('Входные данные'!$F$54)*(1-N('Входные данные'!$F$60))+N('Входные данные'!$F$55)*(1-N('Входные данные'!$F$61))+N('Входные данные'!$F$56)*(1-N('Входные данные'!$F$62)))*52/12*D$54,IF($B57=2,(N('Входные данные'!$F$54)*(1-N('Входные данные'!$F$60))+N('Входные данные'!$F$55)*(1-N('Входные данные'!$F$61))+N('Входные данные'!$F$56)*(1-N('Входные данные'!$F$62)))*D$54,IF(N('Входные данные'!$F$53)>0,(N('Входные данные'!$F$54)*(1-N('Входные данные'!$F$60))+N('Входные данные'!$F$55)*(1-N('Входные данные'!$F$61))+N('Входные данные'!$F$56)*(1-N('Входные данные'!$F$62)))/N('Входные данные'!$F$53)*D$54,"нужна длительность этапа"))) -> нужна длительность этапа | E57: =IF($B57=1,(N('Входные данные'!$F$54)*(1-N('Входные данные'!$F$60))+N('Входные данные'!$F$55)*(1-N('Входные данные'!$F$61))+N('Входные данные'!$F$56)*(1-N('Входные данные'!$F$62)))*52/12*E$54,IF($B57=2,(N('Входные данные'!$F$54)*(1-N('Входные данные'!$F$60))+N('Входные данные'!$F$55)*(1-N('Входные данные'!$F$61))+N('Входные данные'!$F$56)*(1-N('Входные данные'!$F$62)))*E$54,IF(N('Входные данные'!$F$53)>0,(N('Входные данные'!$F$54)*(1-N('Входные данные'!$F$60))+N('Входные данные'!$F$55)*(1-N('Входные данные'!$F$61))+N('Входные данные'!$F$56)*(1-N('Входные данные'!$F$62)))/N('Входные данные'!$F$53)*E$54,"нужна длительность этапа"))) -> нужна длительность этапа | F57: =IF($B57=1,(N('Входные данные'!$F$54)*(1-N('Входные данные'!$F$60))+N('Входные данные'!$F$55)*(1-N('Входные данные'!$F$61))+N('Входные данные'!$F$56)*(1-N('Входные данные'!$F$62)))*52/12*F$54,IF($B57=2,(N('Входные данные'!$F$54)*(1-N('Входные данные'!$F$60))+N('Входные данные'!$F$55)*(1-N('Входные данные'!$F$61))+N('Входные данные'!$F$56)*(1-N('Входные данные'!$F$62)))*F$54,IF(N('Входные данные'!$F$53)>0,(N('Входные данные'!$F$54)*(1-N('Входные данные'!$F$60))+N('Входные данные'!$F$55)*(1-N('Входные данные'!$F$61))+N('Входные данные'!$F$56)*(1-N('Входные данные'!$F$62)))/N('Входные данные'!$F$53)*F$54,"нужна длительность этапа"))) -> нужна длительность этапа | G57: =IF($B57=1,(N('Входные данные'!$F$54)*(1-N('Входные данные'!$F$60))+N('Входные данные'!$F$55)*(1-N('Входные данные'!$F$61))+N('Входные данные'!$F$56)*(1-N('Входные данные'!$F$62)))*52/12*G$54,IF($B57=2,(N('Входные данные'!$F$54)*(1-N('Входные данные'!$F$60))+N('Входные данные'!$F$55)*(1-N('Входные данные'!$F$61))+N('Входные данные'!$F$56)*(1-N('Входные данные'!$F$62)))*G$54,IF(N('Входные данные'!$F$53)>0,(N('Входные данные'!$F$54)*(1-N('Входные данные'!$F$60))+N('Входные данные'!$F$55)*(1-N('Входные данные'!$F$61))+N('Входные данные'!$F$56)*(1-N('Входные данные'!$F$62)))/N('Входные данные'!$F$53)*G$54,"нужна длительность этапа"))) -> нужна длительность этапа
B58: Единицы часов и ставки не заданы: сетка показывает разброс, а не оценку
B60: 7. Разработка и запуск (труд, разово), сум, при одной ставке для всех (База)
B61: строки: единицы часов: 1 неделя, 2 месяц, 3 весь этап | столбцы: ставка, сум/час
C62: 0 | D62: 25000 | E62: 50000 | F62: 100000 | G62: 200000
B63: 1 | C63: =IF($B63=3,(N('Входные данные'!$F$54)*N('Входные данные'!$F$60)+N('Входные данные'!$F$55)*N('Входные данные'!$F$61)+N('Входные данные'!$F$56)*N('Входные данные'!$F$62))*C$62,IF(N('Входные данные'!$F$53)>0,(N('Входные данные'!$F$54)*N('Входные данные'!$F$60)+N('Входные данные'!$F$55)*N('Входные данные'!$F$61)+N('Входные данные'!$F$56)*N('Входные данные'!$F$62))*IF($B63=1,N('Входные данные'!$F$53)*52/12,N('Входные данные'!$F$53))*C$62,"нужна длительность этапа")) -> нужна длительность этапа | D63: =IF($B63=3,(N('Входные данные'!$F$54)*N('Входные данные'!$F$60)+N('Входные данные'!$F$55)*N('Входные данные'!$F$61)+N('Входные данные'!$F$56)*N('Входные данные'!$F$62))*D$62,IF(N('Входные данные'!$F$53)>0,(N('Входные данные'!$F$54)*N('Входные данные'!$F$60)+N('Входные данные'!$F$55)*N('Входные данные'!$F$61)+N('Входные данные'!$F$56)*N('Входные данные'!$F$62))*IF($B63=1,N('Входные данные'!$F$53)*52/12,N('Входные данные'!$F$53))*D$62,"нужна длительность этапа")) -> нужна длительность этапа | E63: =IF($B63=3,(N('Входные данные'!$F$54)*N('Входные данные'!$F$60)+N('Входные данные'!$F$55)*N('Входные данные'!$F$61)+N('Входные данные'!$F$56)*N('Входные данные'!$F$62))*E$62,IF(N('Входные данные'!$F$53)>0,(N('Входные данные'!$F$54)*N('Входные данные'!$F$60)+N('Входные данные'!$F$55)*N('Входные данные'!$F$61)+N('Входные данные'!$F$56)*N('Входные данные'!$F$62))*IF($B63=1,N('Входные данные'!$F$53)*52/12,N('Входные данные'!$F$53))*E$62,"нужна длительность этапа")) -> нужна длительность этапа | F63: =IF($B63=3,(N('Входные данные'!$F$54)*N('Входные данные'!$F$60)+N('Входные данные'!$F$55)*N('Входные данные'!$F$61)+N('Входные данные'!$F$56)*N('Входные данные'!$F$62))*F$62,IF(N('Входные данные'!$F$53)>0,(N('Входные данные'!$F$54)*N('Входные данные'!$F$60)+N('Входные данные'!$F$55)*N('Входные данные'!$F$61)+N('Входные данные'!$F$56)*N('Входные данные'!$F$62))*IF($B63=1,N('Входные данные'!$F$53)*52/12,N('Входные данные'!$F$53))*F$62,"нужна длительность этапа")) -> нужна длительность этапа | G63: =IF($B63=3,(N('Входные данные'!$F$54)*N('Входные данные'!$F$60)+N('Входные данные'!$F$55)*N('Входные данные'!$F$61)+N('Входные данные'!$F$56)*N('Входные данные'!$F$62))*G$62,IF(N('Входные данные'!$F$53)>0,(N('Входные данные'!$F$54)*N('Входные данные'!$F$60)+N('Входные данные'!$F$55)*N('Входные данные'!$F$61)+N('Входные данные'!$F$56)*N('Входные данные'!$F$62))*IF($B63=1,N('Входные данные'!$F$53)*52/12,N('Входные данные'!$F$53))*G$62,"нужна длительность этапа")) -> нужна длительность этапа
B64: 2 | C64: =IF($B64=3,(N('Входные данные'!$F$54)*N('Входные данные'!$F$60)+N('Входные данные'!$F$55)*N('Входные данные'!$F$61)+N('Входные данные'!$F$56)*N('Входные данные'!$F$62))*C$62,IF(N('Входные данные'!$F$53)>0,(N('Входные данные'!$F$54)*N('Входные данные'!$F$60)+N('Входные данные'!$F$55)*N('Входные данные'!$F$61)+N('Входные данные'!$F$56)*N('Входные данные'!$F$62))*IF($B64=1,N('Входные данные'!$F$53)*52/12,N('Входные данные'!$F$53))*C$62,"нужна длительность этапа")) -> нужна длительность этапа | D64: =IF($B64=3,(N('Входные данные'!$F$54)*N('Входные данные'!$F$60)+N('Входные данные'!$F$55)*N('Входные данные'!$F$61)+N('Входные данные'!$F$56)*N('Входные данные'!$F$62))*D$62,IF(N('Входные данные'!$F$53)>0,(N('Входные данные'!$F$54)*N('Входные данные'!$F$60)+N('Входные данные'!$F$55)*N('Входные данные'!$F$61)+N('Входные данные'!$F$56)*N('Входные данные'!$F$62))*IF($B64=1,N('Входные данные'!$F$53)*52/12,N('Входные данные'!$F$53))*D$62,"нужна длительность этапа")) -> нужна длительность этапа | E64: =IF($B64=3,(N('Входные данные'!$F$54)*N('Входные данные'!$F$60)+N('Входные данные'!$F$55)*N('Входные данные'!$F$61)+N('Входные данные'!$F$56)*N('Входные данные'!$F$62))*E$62,IF(N('Входные данные'!$F$53)>0,(N('Входные данные'!$F$54)*N('Входные данные'!$F$60)+N('Входные данные'!$F$55)*N('Входные данные'!$F$61)+N('Входные данные'!$F$56)*N('Входные данные'!$F$62))*IF($B64=1,N('Входные данные'!$F$53)*52/12,N('Входные данные'!$F$53))*E$62,"нужна длительность этапа")) -> нужна длительность этапа | F64: =IF($B64=3,(N('Входные данные'!$F$54)*N('Входные данные'!$F$60)+N('Входные данные'!$F$55)*N('Входные данные'!$F$61)+N('Входные данные'!$F$56)*N('Входные данные'!$F$62))*F$62,IF(N('Входные данные'!$F$53)>0,(N('Входные данные'!$F$54)*N('Входные данные'!$F$60)+N('Входные данные'!$F$55)*N('Входные данные'!$F$61)+N('Входные данные'!$F$56)*N('Входные данные'!$F$62))*IF($B64=1,N('Входные данные'!$F$53)*52/12,N('Входные данные'!$F$53))*F$62,"нужна длительность этапа")) -> нужна длительность этапа | G64: =IF($B64=3,(N('Входные данные'!$F$54)*N('Входные данные'!$F$60)+N('Входные данные'!$F$55)*N('Входные данные'!$F$61)+N('Входные данные'!$F$56)*N('Входные данные'!$F$62))*G$62,IF(N('Входные данные'!$F$53)>0,(N('Входные данные'!$F$54)*N('Входные данные'!$F$60)+N('Входные данные'!$F$55)*N('Входные данные'!$F$61)+N('Входные данные'!$F$56)*N('Входные данные'!$F$62))*IF($B64=1,N('Входные данные'!$F$53)*52/12,N('Входные данные'!$F$53))*G$62,"нужна длительность этапа")) -> нужна длительность этапа
B65: 3 | C65: =IF($B65=3,(N('Входные данные'!$F$54)*N('Входные данные'!$F$60)+N('Входные данные'!$F$55)*N('Входные данные'!$F$61)+N('Входные данные'!$F$56)*N('Входные данные'!$F$62))*C$62,IF(N('Входные данные'!$F$53)>0,(N('Входные данные'!$F$54)*N('Входные данные'!$F$60)+N('Входные данные'!$F$55)*N('Входные данные'!$F$61)+N('Входные данные'!$F$56)*N('Входные данные'!$F$62))*IF($B65=1,N('Входные данные'!$F$53)*52/12,N('Входные данные'!$F$53))*C$62,"нужна длительность этапа")) -> 0 | D65: =IF($B65=3,(N('Входные данные'!$F$54)*N('Входные данные'!$F$60)+N('Входные данные'!$F$55)*N('Входные данные'!$F$61)+N('Входные данные'!$F$56)*N('Входные данные'!$F$62))*D$62,IF(N('Входные данные'!$F$53)>0,(N('Входные данные'!$F$54)*N('Входные данные'!$F$60)+N('Входные данные'!$F$55)*N('Входные данные'!$F$61)+N('Входные данные'!$F$56)*N('Входные данные'!$F$62))*IF($B65=1,N('Входные данные'!$F$53)*52/12,N('Входные данные'!$F$53))*D$62,"нужна длительность этапа")) -> 1687500 | E65: =IF($B65=3,(N('Входные данные'!$F$54)*N('Входные данные'!$F$60)+N('Входные данные'!$F$55)*N('Входные данные'!$F$61)+N('Входные данные'!$F$56)*N('Входные данные'!$F$62))*E$62,IF(N('Входные данные'!$F$53)>0,(N('Входные данные'!$F$54)*N('Входные данные'!$F$60)+N('Входные данные'!$F$55)*N('Входные данные'!$F$61)+N('Входные данные'!$F$56)*N('Входные данные'!$F$62))*IF($B65=1,N('Входные данные'!$F$53)*52/12,N('Входные данные'!$F$53))*E$62,"нужна длительность этапа")) -> 3375000 | F65: =IF($B65=3,(N('Входные данные'!$F$54)*N('Входные данные'!$F$60)+N('Входные данные'!$F$55)*N('Входные данные'!$F$61)+N('Входные данные'!$F$56)*N('Входные данные'!$F$62))*F$62,IF(N('Входные данные'!$F$53)>0,(N('Входные данные'!$F$54)*N('Входные данные'!$F$60)+N('Входные данные'!$F$55)*N('Входные данные'!$F$61)+N('Входные данные'!$F$56)*N('Входные данные'!$F$62))*IF($B65=1,N('Входные данные'!$F$53)*52/12,N('Входные данные'!$F$53))*F$62,"нужна длительность этапа")) -> 6750000 | G65: =IF($B65=3,(N('Входные данные'!$F$54)*N('Входные данные'!$F$60)+N('Входные данные'!$F$55)*N('Входные данные'!$F$61)+N('Входные данные'!$F$56)*N('Входные данные'!$F$62))*G$62,IF(N('Входные данные'!$F$53)>0,(N('Входные данные'!$F$54)*N('Входные данные'!$F$60)+N('Входные данные'!$F$55)*N('Входные данные'!$F$61)+N('Входные данные'!$F$56)*N('Входные данные'!$F$62))*IF($B65=1,N('Входные данные'!$F$53)*52/12,N('Входные данные'!$F$53))*G$62,"нужна длительность этапа")) -> 13500000
B67: 8. Цена отчёта ±10% и ±20% (База, I1 = только KMT, прямые затраты в сумах без изменений)
B68: Изменение цены | C68: Цена, сум | D68: Маржа на заказ после комиссии | E68: Множитель заказов | F68: Заказов в месяц | G68: Маржа проекта в месяц | H68: Допустимо на заказ (потолок)
B69: -0.2 | C69: ='Юнит-экономика'!$D$6*(1+B69) -> 800000 | D69: ='Юнит-экономика'!$D$8*(1+B69)-'Юнит-экономика'!$D$10-N('Входные данные'!$F$33)*N('Входные данные'!$F$34)*'Юнит-экономика'!$D$8*(1+B69) -> 300000 | E69: =MAX(0,1+N('Входные данные'!$F$69)*B69/0.1) -> 1 | F69: =Воронка!$D$18*E69 -> 2.1 | G69: =F69*D69*N('Входные данные'!$F$32) -> 630000 | H69: =N('Входные данные'!$F$39)*MAX(0,D69) -> 60000
B70: -0.1 | C70: ='Юнит-экономика'!$D$6*(1+B70) -> 900000 | D70: ='Юнит-экономика'!$D$8*(1+B70)-'Юнит-экономика'!$D$10-N('Входные данные'!$F$33)*N('Входные данные'!$F$34)*'Юнит-экономика'!$D$8*(1+B70) -> 400000 | E70: =MAX(0,1+N('Входные данные'!$F$69)*B70/0.1) -> 1 | F70: =Воронка!$D$18*E70 -> 2.1 | G70: =F70*D70*N('Входные данные'!$F$32) -> 840000 | H70: =N('Входные данные'!$F$39)*MAX(0,D70) -> 80000
B71: 0 | C71: ='Юнит-экономика'!$D$6*(1+B71) -> 1000000 | D71: ='Юнит-экономика'!$D$8*(1+B71)-'Юнит-экономика'!$D$10-N('Входные данные'!$F$33)*N('Входные данные'!$F$34)*'Юнит-экономика'!$D$8*(1+B71) -> 500000 | E71: =MAX(0,1+N('Входные данные'!$F$69)*B71/0.1) -> 1 | F71: =Воронка!$D$18*E71 -> 2.1 | G71: =F71*D71*N('Входные данные'!$F$32) -> 1050000 | H71: =N('Входные данные'!$F$39)*MAX(0,D71) -> 100000
B72: 0.1 | C72: ='Юнит-экономика'!$D$6*(1+B72) -> 1100000 | D72: ='Юнит-экономика'!$D$8*(1+B72)-'Юнит-экономика'!$D$10-N('Входные данные'!$F$33)*N('Входные данные'!$F$34)*'Юнит-экономика'!$D$8*(1+B72) -> 600000 | E72: =MAX(0,1+N('Входные данные'!$F$69)*B72/0.1) -> 1 | F72: =Воронка!$D$18*E72 -> 2.1 | G72: =F72*D72*N('Входные данные'!$F$32) -> 1260000 | H72: =N('Входные данные'!$F$39)*MAX(0,D72) -> 120000
B73: 0.2 | C73: ='Юнит-экономика'!$D$6*(1+B73) -> 1200000 | D73: ='Юнит-экономика'!$D$8*(1+B73)-'Юнит-экономика'!$D$10-N('Входные данные'!$F$33)*N('Входные данные'!$F$34)*'Юнит-экономика'!$D$8*(1+B73) -> 700000 | E73: =MAX(0,1+N('Входные данные'!$F$69)*B73/0.1) -> 1 | F73: =Воронка!$D$18*E73 -> 2.1 | G73: =F73*D73*N('Входные данные'!$F$32) -> 1470000 | H73: =N('Входные данные'!$F$39)*MAX(0,D73) -> 140000
B74: Реакция спроса на цену (elas) не задана — пока множитель = 100%; результат — верхняя граница при повышении цены.
B76: 9. I1 = гибрид: маржа проекта на заказ (База) от доли заказов партнёра и платы проекту
B77: строки: доля заказов партнёра q | столбцы: плата проекту, % от чека
C78: 0 | D78: 0.1 | E78: 0.15 | F78: 0.2
B79: 0 | C79: =((1-$B79)*'Юнит-экономика'!$D$20+$B79*C$78*'Юнит-экономика'!$D$8)*N('Входные данные'!$F$32) -> 500000 | D79: =((1-$B79)*'Юнит-экономика'!$D$20+$B79*D$78*'Юнит-экономика'!$D$8)*N('Входные данные'!$F$32) -> 500000 | E79: =((1-$B79)*'Юнит-экономика'!$D$20+$B79*E$78*'Юнит-экономика'!$D$8)*N('Входные данные'!$F$32) -> 500000 | F79: =((1-$B79)*'Юнит-экономика'!$D$20+$B79*F$78*'Юнит-экономика'!$D$8)*N('Входные данные'!$F$32) -> 500000
B80: 0.1 | C80: =((1-$B80)*'Юнит-экономика'!$D$20+$B80*C$78*'Юнит-экономика'!$D$8)*N('Входные данные'!$F$32) -> 450000 | D80: =((1-$B80)*'Юнит-экономика'!$D$20+$B80*D$78*'Юнит-экономика'!$D$8)*N('Входные данные'!$F$32) -> 460000 | E80: =((1-$B80)*'Юнит-экономика'!$D$20+$B80*E$78*'Юнит-экономика'!$D$8)*N('Входные данные'!$F$32) -> 465000 | F80: =((1-$B80)*'Юнит-экономика'!$D$20+$B80*F$78*'Юнит-экономика'!$D$8)*N('Входные данные'!$F$32) -> 470000
B81: 0.2 | C81: =((1-$B81)*'Юнит-экономика'!$D$20+$B81*C$78*'Юнит-экономика'!$D$8)*N('Входные данные'!$F$32) -> 400000 | D81: =((1-$B81)*'Юнит-экономика'!$D$20+$B81*D$78*'Юнит-экономика'!$D$8)*N('Входные данные'!$F$32) -> 420000 | E81: =((1-$B81)*'Юнит-экономика'!$D$20+$B81*E$78*'Юнит-экономика'!$D$8)*N('Входные данные'!$F$32) -> 430000 | F81: =((1-$B81)*'Юнит-экономика'!$D$20+$B81*F$78*'Юнит-экономика'!$D$8)*N('Входные данные'!$F$32) -> 440000
B82: 0.3 | C82: =((1-$B82)*'Юнит-экономика'!$D$20+$B82*C$78*'Юнит-экономика'!$D$8)*N('Входные данные'!$F$32) -> 350000 | D82: =((1-$B82)*'Юнит-экономика'!$D$20+$B82*D$78*'Юнит-экономика'!$D$8)*N('Входные данные'!$F$32) -> 380000 | E82: =((1-$B82)*'Юнит-экономика'!$D$20+$B82*E$78*'Юнит-экономика'!$D$8)*N('Входные данные'!$F$32) -> 395000 | F82: =((1-$B82)*'Юнит-экономика'!$D$20+$B82*F$78*'Юнит-экономика'!$D$8)*N('Входные данные'!$F$32) -> 410000
B83: 0.5 | C83: =((1-$B83)*'Юнит-экономика'!$D$20+$B83*C$78*'Юнит-экономика'!$D$8)*N('Входные данные'!$F$32) -> 250000 | D83: =((1-$B83)*'Юнит-экономика'!$D$20+$B83*D$78*'Юнит-экономика'!$D$8)*N('Входные данные'!$F$32) -> 300000 | E83: =((1-$B83)*'Юнит-экономика'!$D$20+$B83*E$78*'Юнит-экономика'!$D$8)*N('Входные данные'!$F$32) -> 325000 | F83: =((1-$B83)*'Юнит-экономика'!$D$20+$B83*F$78*'Юнит-экономика'!$D$8)*N('Входные данные'!$F$32) -> 350000
B84: При плате 0 каждый процент уходящих заказов съедает маржу; 10–20% — гипотеза из 05 для агрегатора
B86: 10. D10: заказы и маржа проекта в месяц (База, выбранный I1) от доли заказов, сохраняющихся при нейтральном тексте
B87: строки: доля сохранившихся заказов | столбцы: показатель
C88: Заказов в месяц | D88: Маржа в месяц, сум | E88: Потеря к б+, сум
B89: 0 | C89: =Воронка!$D$12*$B89 -> 0 | D89: =Воронка!$D$12*$B89*'Юнит-экономика'!$D$32 -> 0 | E89: =Воронка!$D$12*(1-$B89)*'Юнит-экономика'!$D$32 -> 1050000
B90: 0.1 | C90: =Воронка!$D$12*$B90 -> 0.21 | D90: =Воронка!$D$12*$B90*'Юнит-экономика'!$D$32 -> 105000 | E90: =Воронка!$D$12*(1-$B90)*'Юнит-экономика'!$D$32 -> 945000
B91: 0.25 | C91: =Воронка!$D$12*$B91 -> 0.525 | D91: =Воронка!$D$12*$B91*'Юнит-экономика'!$D$32 -> 262500 | E91: =Воронка!$D$12*(1-$B91)*'Юнит-экономика'!$D$32 -> 787500
B92: 0.5 | C92: =Воронка!$D$12*$B92 -> 1.05 | D92: =Воронка!$D$12*$B92*'Юнит-экономика'!$D$32 -> 525000 | E92: =Воронка!$D$12*(1-$B92)*'Юнит-экономика'!$D$32 -> 525000
B93: 0.75 | C93: =Воронка!$D$12*$B93 -> 1.575 | D93: =Воронка!$D$12*$B93*'Юнит-экономика'!$D$32 -> 787500 | E93: =Воронка!$D$12*(1-$B93)*'Юнит-экономика'!$D$32 -> 262500
B94: 1 | C94: =Воронка!$D$12*$B94 -> 2.1 | D94: =Воронка!$D$12*$B94*'Юнит-экономика'!$D$32 -> 1050000 | E94: =Воронка!$D$12*(1-$B94)*'Юнит-экономика'!$D$32 -> 0

Sheet Проверка
A1: Проверка модели
A2: Статусы: OK, ОШИБКА (нужно исправить формулу), НЕТ ДАННЫХ (формулы верны, нужен ввод владельца).
B3: Общий статус: | C3: =IF(COUNTIF(D6:D25,"ОШИБКА")>0,"ЕСТЬ ОШИБКИ",IF(COUNTIF(D6:D25,"НЕТ ДАННЫХ")>0,"ФОРМУЛЫ ОК, НЕ ХВАТАЕТ ДАННЫХ ВЛАДЕЛЬЦА","ВСЁ ОК")) -> ФОРМУЛЫ ОК, НЕ ХВАТАЕТ ДАННЫХ ВЛАДЕЛЬЦА
A5: № | B5: Проверка | C5: Значение | D5: Статус | E5: Комментарий
A6: C01 | B6: Ошибки формул: Входные данные | C6: =SUMPRODUCT(--ISERROR('Входные данные'!E13:G69)) -> 0 | D6: =IF(C6=0,"OK","ОШИБКА") -> OK
A7: C02 | B7: Ошибки формул: Юнит-экономика | C7: =SUMPRODUCT(--ISERROR('Юнит-экономика'!C5:E40)) -> 0 | D7: =IF(C7=0,"OK","ОШИБКА") -> OK
A8: C03 | B8: Ошибки формул: Воронка | C8: =SUMPRODUCT(--ISERROR(Воронка!C5:E25)) -> 0 | D8: =IF(C8=0,"OK","ОШИБКА") -> OK
A9: C04 | B9: Ошибки формул: Сценарии_BEP | C9: =SUMPRODUCT(--ISERROR(Сценарии_BEP!C5:P102)) -> 0 | D9: =IF(C9=0,"OK","ОШИБКА") -> OK
A10: C05 | B10: Ошибки формул: D10_I1 | C10: =SUMPRODUCT(--ISERROR(D10_I1!C4:F60)) -> 0 | D10: =IF(C10=0,"OK","ОШИБКА") -> OK
A11: C06 | B11: Ошибки формул: Чувствительность | C11: =SUMPRODUCT(--ISERROR(Чувствительность!B4:H98)) -> 0 | D11: =IF(C11=0,"OK","ОШИБКА") -> OK
A12: C07 | B12: Тождество юнит-экономики: выручка − прямые затраты − комиссия − маржа = 0 (по 3 сценариям) | C12: =ABS('Юнит-экономика'!$C$8-'Юнит-экономика'!$C$10-'Юнит-экономика'!$C$19-'Юнит-экономика'!$C$20)+ABS('Юнит-экономика'!$D$8-'Юнит-экономика'!$D$10-'Юнит-экономика'!$D$19-'Юнит-экономика'!$D$20)+ABS('Юнит-экономика'!$E$8-'Юнит-экономика'!$E$10-'Юнит-экономика'!$E$19-'Юнит-экономика'!$E$20) -> 0 | D12: =IF(C12<0.001,"OK","ОШИБКА") -> OK
A13: C08 | B13: Маржа при методе 1 равна вводу владельца | C13: =IF(AND(N('Входные данные'!$E$20)=1,'Юнит-экономика'!$C$8>0),ABS('Юнит-экономика'!$C$12-N('Входные данные'!$E$21)),0)+IF(AND(N('Входные данные'!$F$20)=1,'Юнит-экономика'!$D$8>0),ABS('Юнит-экономика'!$D$12-N('Входные данные'!$F$21)),0)+IF(AND(N('Входные данные'!$G$20)=1,'Юнит-экономика'!$E$8>0),ABS('Юнит-экономика'!$E$12-N('Входные данные'!$G$21)),0) -> 0 | D13: =IF(C13<0.001,"OK","ОШИБКА") -> OK | E13: Проверяется, когда выручка > 0
A14: C09 | B14: Воронка: заказы = расчёты × c1 × c2 × инкрементальность | C14: =ABS(Воронка!$C$12-N('Входные данные'!$E$42)*N('Входные данные'!$E$44)*N('Входные данные'!$E$45)*N('Входные данные'!$E$46))+ABS(Воронка!$D$12-N('Входные данные'!$F$42)*N('Входные данные'!$F$44)*N('Входные данные'!$F$45)*N('Входные данные'!$F$46))+ABS(Воронка!$E$12-N('Входные данные'!$G$42)*N('Входные данные'!$G$44)*N('Входные данные'!$G$45)*N('Входные данные'!$G$46)) -> 0 | D14: =IF(C14<0.001,"OK","ОШИБКА") -> OK
A15: C10 | B15: Помесячная модель: итог за 12 мес = −разработка + сумма операций (по 3 сценариям) | C15: =ABS(Сценарии_BEP!O61-(Сценарии_BEP!C60+Сценарии_BEP!P58))+ABS(Сценарии_BEP!O78-(Сценарии_BEP!C77+Сценарии_BEP!P75))+ABS(Сценарии_BEP!O95-(Сценарии_BEP!C94+Сценарии_BEP!P92)) -> 0 | D15: =IF(C15<0.001,"OK","ОШИБКА") -> OK
A16: C11 | B16: Помесячная модель выходит на режим: заказы в 12-м месяце = режим Воронки | C16: =IF(N('Входные данные'!$F$47)>12,0,ABS(Сценарии_BEP!O54-Воронка!$C$18)+ABS(Сценарии_BEP!O71-Воронка!$D$18)+ABS(Сценарии_BEP!O88-Воронка!$E$18)) -> 0 | D16: =IF(C16<0.001,"OK","ОШИБКА") -> OK | E16: Проверка пропускается, если время выхода на режим больше 12 мес
A17: C12 | B17: D10_I1: выбранное сочетание совпадает с основным расчётом (лист БУ) | C17: =ABS(INDEX(D10_I1!C11:F11,1,(N('Входные данные'!$E$30)-1)*2+N('Входные данные'!$E$31))-Сценарии_BEP!$C$36)+ABS(INDEX(D10_I1!C24:F24,1,(N('Входные данные'!$F$30)-1)*2+N('Входные данные'!$F$31))-Сценарии_BEP!$D$36)+ABS(INDEX(D10_I1!C37:F37,1,(N('Входные данные'!$G$30)-1)*2+N('Входные данные'!$G$31))-Сценарии_BEP!$E$36) -> 0 | D17: =IF(C17<0.001,"OK","ОШИБКА") -> OK
A18: C13 | B18: Доли и конверсии лежат в диапазоне 0–100% | C18: =IF(AND(MIN('Входные данные'!E21:G21)>=0,MAX('Входные данные'!E21:G21)<=1,MIN('Входные данные'!E32:G32)>=0,MAX('Входные данные'!E32:G32)<=1,MIN('Входные данные'!E33:G33)>=0,MAX('Входные данные'!E33:G33)<=1,MIN('Входные данные'!E34:G34)>=0,MAX('Входные данные'!E34:G34)<=1,MIN('Входные данные'!E35:G35)>=0,MAX('Входные данные'!E35:G35)<=1,MIN('Входные данные'!E36:G36)>=0,MAX('Входные данные'!E36:G36)<=1,MIN('Входные данные'!E37:G37)>=0,MAX('Входные данные'!E37:G37)<=1,MIN('Входные данные'!E39:G39)>=0,MAX('Входные данные'!E39:G39)<=1,MIN('Входные данные'!E44:G44)>=0,MAX('Входные данные'!E44:G44)<=1,MIN('Входные данные'!E45:G45)>=0,MAX('Входные данные'!E45:G45)<=1,MIN('Входные данные'!E46:G46)>=0,MAX('Входные данные'!E46:G46)<=1,MIN('Входные данные'!E60:G60)>=0,MAX('Входные данные'!E60:G60)<=1,MIN('Входные данные'!E61:G61)>=0,MAX('Входные данные'!E61:G61)<=1,MIN('Входные данные'!E62:G62)>=0,MAX('Входные данные'!E62:G62)<=1),0,1) -> 0 | D18: =IF(C18=0,"OK","ОШИБКА") -> OK
A19: C14 | B19: Переключатели допустимы (метод 1/2, I1 1/2, D10 1/2, часы 0/1/2/3) | C19: =IF(AND(OR('Входные данные'!F20=1,'Входные данные'!F20=2),OR('Входные данные'!F30=1,'Входные данные'!F30=2),OR('Входные данные'!F31=1,'Входные данные'!F31=2),OR(N('Входные данные'!F52)=0,N('Входные данные'!F52)=1,N('Входные данные'!F52)=2,N('Входные данные'!F52)=3)),0,1) -> 0 | D19: =IF(C19=0,"OK","ОШИБКА") -> OK
A20: C15 | B20: Метод 2 выбран, но построчные затраты пусты (маржа вышла бы 100%) | C20: =IF(AND('Входные данные'!F20=2,'Юнит-экономика'!$D$9=0),1,0) -> 0 | D20: =IF(C20=0,"OK","ОШИБКА") -> OK
A21: C16 | B21: Пустых входов «нужно от Темура» (из 21) | C21: =IF('Входные данные'!F16="",1,0)+IF('Входные данные'!F17="",1,0)+IF('Входные данные'!F22="",1,0)+IF('Входные данные'!F23="",1,0)+IF('Входные данные'!F24="",1,0)+IF('Входные данные'!F25="",1,0)+IF('Входные данные'!F26="",1,0)+IF('Входные данные'!F27="",1,0)+IF('Входные данные'!F28="",1,0)+IF('Входные данные'!F43="",1,0)+IF('Входные данные'!F50="",1,0)+IF('Входные данные'!F52="",1,0)+IF('Входные данные'!F53="",1,0)+IF('Входные данные'!F57="",1,0)+IF('Входные данные'!F58="",1,0)+IF('Входные данные'!F59="",1,0)+IF('Входные данные'!F64="",1,0)+IF('Входные данные'!F65="",1,0)+IF('Входные данные'!F66="",1,0)+IF('Входные данные'!F67="",1,0)+IF('Входные данные'!F69="",1,0) -> 21 | D21: =IF(C21=0,"OK","НЕТ ДАННЫХ") -> НЕТ ДАННЫХ | E21: Список вопросов — лист «Вопросы к Темуру»
A22: C17 | B22: Единицы часов не заданы: труд команды не оценён | C22: =IF(N('Входные данные'!F52)=0,1,0) -> 1 | D22: =IF(C22=0,"OK","НЕТ ДАННЫХ") -> НЕТ ДАННЫХ
A23: C18 | B23: Единицы часов заданы, а длительность этапа нет: разработка и труд занижены | C23: =IF(AND(N('Входные данные'!F52)>0,N('Входные данные'!F53)<=0),1,0) -> 0 | D23: =IF(C23=0,"OK","НЕТ ДАННЫХ") -> OK
A24: C19 | B24: Ставки не заданы: труд команды = 0 | C24: =IF(AND(N('Входные данные'!F57)=0,N('Входные данные'!F58)=0,N('Входные данные'!F59)=0),1,0) -> 1 | D24: =IF(C24=0,"OK","НЕТ ДАННЫХ") -> НЕТ ДАННЫХ
A25: C20 | B25: Затраты на разработку не заданы: окупаемость разработки не считается | C25: =IF(Сценарии_BEP!$D$24<=0,1,0) -> 1 | D25: =IF(C25=0,"OK","НЕТ ДАННЫХ") -> НЕТ ДАННЫХ
B27: Баланс допущений (по статусам строк во «Входные данные»)
B28: [факт] | C28: =SUMPRODUCT(--(LEFT('Входные данные'!D13:D69,6)="[факт]")) -> 9
B29: [гипотеза] (включая [проверить]) | C29: =SUMPRODUCT(--(LEFT('Входные данные'!D13:D69,10)="[гипотеза]")) -> 14
B30: [заглушка] | C30: =SUMPRODUCT(--(LEFT('Входные данные'!D13:D69,10)="[заглушка]")) -> 3
B31: нужно от Темура | C31: =SUMPRODUCT(--(LEFT('Входные данные'!D13:D69,15)="нужно от Темура")) -> 21
B32: [выбор] | C32: =SUMPRODUCT(--(LEFT('Входные данные'!D13:D69,7)="[выбор]")) -> 1
B33: Всего параметров | C33: =SUM(C28:C32) -> 48 | D33: =IF(C33=48,"OK","ОШИБКА") -> OK | E33: Сумма по статусам должна равняться числу параметров
B34: Драйверы выручки (объём, c1, c2, инкрементальность, маржа): из них [факт] | C34: =IF(LEFT('Входные данные'!D42,6)="[факт]",1,0)+IF(LEFT('Входные данные'!D44,6)="[факт]",1,0)+IF(LEFT('Входные данные'!D45,6)="[факт]",1,0)+IF(LEFT('Входные данные'!D46,6)="[факт]",1,0)+IF(LEFT('Входные данные'!D21,6)="[факт]",1,0) -> 0 | E34: из 5: основной вывод модели держится на гипотезах и заглушках
B36: Граничные случаи (прогон скриптом при создании файла; каждый — отдельная копия книги с пересчётом)
A37: № | B37: Случай | C37: Ошибок формул | D37: Результат | E37: Что показали
A38: T01 | B38: Исходное состояние: все «нужно от Темура» пусты | C38: 0 | D38: OK | E38: Считается без ошибок; 4 проверки честно показывают «НЕТ ДАННЫХ». База: БУ 2,0 заказа в месяц, покрывает только хостинг.
A39: T02 | B39: Маржа заказа = 0% во всех сценариях | C39: 0 | D39: OK | E39: БУ показывает «нет БУ», допустимое привлечение 0, деления на ноль нет.
A40: T03 | B40: Конверсия расчёт → интерес = 0 | C40: 0 | D40: OK | E40: БУ в расчётах — «нет БУ»; результат −1 млн сум в месяц (расходы без дохода).
A41: T04 | B41: Расчётов уровня 1 в месяц = 0 | C41: 0 | D41: OK | E41: Результат −1 млн сум в месяц; БУ считается без ошибок.
A42: T05 | B42: Потолок привлечения = 0 | C42: 0 | D42: OK | E42: Допустимо на заказ 0; отношение комиссии к потолку — «н/д».
A43: T06 | B43: Цена отчёта = 0 | C43: 0 | D43: OK | E43: Маржа 0, БУ «нет БУ», ошибок нет.
A44: T07 | B44: Метод маржи 2 при пустых построчных затратах | C44: 0 | D44: Ловушка отловлена | E44: Маржа вышла бы 100% (1 млн сум на заказ); проверка C15 даёт ОШИБКА, общий статус «ЕСТЬ ОШИБКИ». Это ожидаемо: метод 2 включают только с данными.
A45: T08 | B45: НДС включён, ставка 12% (тестовое значение, не факт) | C45: 0 | D45: OK | E45: Тестовые значения (ставка НДС — не факт): маржа на заказ 446 тыс. вместо 500 тыс., БУ 2,24 заказа.
A46: T09 | B46: Часы в неделю, этап 3 мес, ставки по 100 000, разовые 5 млн (тестовые значения) | C46: 0 | D46: OK | E46: Тестовые значения: труд 7,6 млн сум в месяц, разработка 92,75 млн; БУ полная 17,2 заказа в месяц, окупаемости нет. Ставки взяты для проверки, не как оценка.
A47: T10 | B47: Часы на весь этап при длительности этапа 0 | C47: 0 | D47: OK | E47: Защита от деления на ноль: постоянный труд = 0, разработка считается.
A48: T11 | B48: I1 = гибрид и D10 = нейтральный текст | C48: 0 | D48: OK | E48: Результат −790 тыс. сум в месяц, совпадает с листом D10_I1 (проверка C12).
A49: T12 | B49: Выход на режим: 0 мес | C49: 0 | D49: OK | E49: Коэффициент выхода на режим = 1, без деления на ноль.
... A53: T16 | B53: Нарушение границ: конверсия расчёт → интерес = 150% | C53: 0 | D53: Ловушка отловлена | E53: Конверсия 150%: проверка C13 даёт ОШИБКА (выход за границы 0–100%).
