Workbook

Sheet Входные данные
A1: Модель этапа 1 HomePrice.uz v0.2 — Входные данные
A2: Единицы: сум, если не указано иное. Формулы других листов читают только этот лист. Ячейка «База» (столбец F) — то, что вы вводите; «Пессимист» и «Оптимист» берутся из неё, если не заданы отдельно. Ответы владельца от 18.10.2026 (форма) внесены.
A4: Цветовая разметка
B5: [факт] — известно от владельца или из документов (18.10.2026); [проверить] — со слов, не сверено с учётом
B6: [гипотеза] — предположение; часть помечена [проверить]
B7: [заглушка] — временное значение до данных (market_sizing.xlsx и др.), не оценка
B8: нужно от Темура — пусто, пока нет данных; модель считает пустое как 0 и сообщает об этом в листе «Проверка»
B9: [выбор] — переключатель модели
B10: Статус проверки модели: | C10: =Проверка!C3 -> ФОРМУЛЫ ОК, НЕ ХВАТАЕТ ДАННЫХ ВЛАДЕЛЬЦА
A12: № | B12: Параметр | C12: Ед. | D12: Статус | E12: Пессимист | F12: База | G12: Оптимист | H12: Источник | I12: Комментарий / что нужно
A13: A. Цена отчёта уровня 3 и срок
A14: P01 | B14: Доля заказов по ~800 тыс. сум | C14: % | D14: [факт][проверить] | E14: =IF(F14="","",F14) -> 0.15 | F14: 0.15 | G14: =IF(F14="","",F14) -> 0.15 | H14: Владелец, форма 18.10.2026, вопрос 1 | I14: Оценка по памяти, не выгрузка из учёта.
A15: P02 | B15: Доля заказов по ~1 млн сум | C15: % | D15: [факт][проверить] | E15: =IF(F15="","",F15) -> 0.75 | F15: 0.75 | G15: =IF(F15="","",F15) -> 0.75 | H15: Владелец, форма 18.10.2026, вопрос 1 | I15: То же.
A16: P03 | B16: Доля заказов дороже 1 млн сум | C16: % | D16: [факт][проверить] | E16: =IF(F16="","",F16) -> 0.1 | F16: 0.1 | G16: =IF(F16="","",F16) -> 0.1 | H16: Владелец, форма 18.10.2026, вопрос 1 | I16: То же. Сумма трёх долей должна быть 100% (проверка C).
A17: P04 | B17: Цена «лёгкого» заказа | C17: сум | D17: [факт] | E17: =IF(F17="","",F17) -> 800000 | F17: 800000 | G17: =IF(F17="","",F17) -> 800000 | H17: Владелец, форма 18.10.2026, вопрос 1 | I17: «Бывает, что делаем и за 800 000».
A18: P05 | B18: Цена обычного заказа | C18: сум | D18: [факт] | E18: =IF(F18="","",F18) -> 1000000 | F18: 1000000 | G18: =IF(F18="","",F18) -> 1000000 | H18: Владелец, форма 18.10.2026, вопрос 1; 05_4P | I18: Средний по Ташкенту.
A19: P06 | B19: Типичная цена заказа «дороже» | C19: сум | D19: [факт][проверить] | E19: =IF(F19="","",F19) -> 1500000 | F19: 1500000 | G19: =IF(F19="","",F19) -> 1500000 | H19: Владелец, форма 18.10.2026, вопрос 1 | I19: Оценка.
A20: P07 | B20: Средняя цена отчёта (формула по долям выше) | C20: сум | D20: [факт][проверить] | E20: =IF(F20="","",F20) -> 1020000 | F20: =F14*F17+F15*F18+F16*F19 -> 1020000 | G20: =IF(F20="","",F20) -> 1020000 | H20: Расчёт по долям и ценам | I20: Формула в столбце «База»: можно заменить числом.
A21: P08 | B21: Срок отчёта | C21: дней | D21: [факт] | E21: =IF(F21="","",F21) -> 2 | F21: 2 | G21: =IF(F21="","",F21) -> 2 | H21: 05_4P; 02_Marketing_Context | I21: Цель — 1 день. В расчёте не используется.
A22: P09 | B22: Цена включает НДС? (1 = да, 0 = нет) | C22: 1/0 | D22: [факт] | E22: =IF(F22="","",F22) -> 0 | F22: 0 | G22: =IF(F22="","",F22) -> 0 | H22: Владелец, форма 18.10.2026, вопрос 2 | I22: KMT не платит НДС.
A23: P10 | B23: Ставка НДС | C23: % | D23: [факт] | E23: =IF(F23="","",F23) -> 0 | F23: 0 | G23: =IF(F23="","",F23) -> 0 | H23: Владелец, форма 18.10.2026, вопрос 2 | I23: 0, так как KMT не плательщик. Статус Bizzone по НДС не уточнялся.
A24: P11 | B24: Курс сум за доллар (справочно) | C24: сум/$ | D24: [гипотеза][проверить] | E24: =IF(F24="","",F24) -> 12000 | F24: 12000 | G24: =IF(F24="","",F24) -> 12000 | H24: 05_4P, 14_Rebaseline п.4.1 | I24: Только для пересчёта допустимой стоимости привлечения в доллары. Проверить на дату.
A25: B. Прибыль (маржа) и прямые затраты одного заказа
A26: P12 | B26: Метод маржи (1 = процент, 2 = построчно, 3 = средняя прибыль в сумах) | C26: 1/2/3 | D26: [выбор] | E26: =IF(F26="","",F26) -> 3 | F26: 3 | G26: =IF(F26="","",F26) -> 3 | H26: Решение модели | I26: 3 — по ответу владельца (вопрос 3). 2 — построчно, пока считается как проверка.
A27: P13 | B27: Средняя прибыль с одного заказа (метод 3) | C27: сум/заказ | D27: [факт][проверить] | E27: 300000 | F27: 400000 | G27: 700000 | H27: Владелец, форма 18.10.2026, вопрос 3 и 5 | I27: Пессимист — самая маленькая (300 тыс.), База — средняя (400 тыс.) со слов. Оптимист 700 тыс. — [гипотеза]: построчные затраты из вопросов 4–5 дают 700 тыс.; разница с 400 тыс. — возможно, административные расходы и офис, которые для дополнительного заказа не растут. Максимум 900 тыс. не используется (одиночный заказ).
A28: P14 | B28: Маржа, % выручки (метод 1, прежняя оценка ≈50%) | C28: % | D28: [гипотеза] | E28: 0.3 | F28: 0.5 | G28: 0.5 | H28: Владелец 18.10 (первая оценка); пессимист — заглушка из 14 п.4.1 | I28: Не используется при методе 3. Оставлена для сравнения.
A29: P15 | B29: Гонорар или зарплата оценщика | C29: сум/заказ | D29: [факт] | E29: =IF(F29="","",F29) -> 100000 | F29: 100000 | G29: =IF(F29="","",F29) -> 100000 | H29: Владелец, форма 18.10.2026, вопрос 5 | I29: Для метода 2 и сверки с вопросом 3.
A30: P16 | B30: Выезд (стоимость × доля заказов с выездом) | C30: сум/заказ | D30: [факт] | E30: =IF(F30="","",F30) -> 100000 | F30: 100000 | G30: =IF(F30="","",F30) -> 100000 | H30: Владелец, форма 18.10.2026, вопрос 4 | I30: 100 000 сум на выезд, нужен у 100% заказов.
A31: P17 | B31: Проверка документов, оформление отчёта | C31: сум/заказ | D31: [факт] | E31: =IF(F31="","",F31) -> 20000 | F31: 20000 | G31: =IF(F31="","",F31) -> 20000 | H31: Владелец, форма 18.10.2026, вопрос 5
A32: P18 | B32: Налоги и сборы с заказа | C32: сум/заказ | D32: [факт] | E32: =IF(F32="","",F32) -> 70000 | F32: 70000 | G32: =IF(F32="","",F32) -> 70000 | H32: Владелец, форма 18.10.2026, вопрос 5
A33: P19 | B33: Платёжные и банковские комиссии | C33: сум/заказ | D33: [факт] | E33: =IF(F33="","",F33) -> 0 | F33: 0 | G33: =IF(F33="","",F33) -> 0 | H33: Владелец, форма 18.10.2026, вопрос 5 | I33: Банк включён в строку «прочее» (dc6).
A34: P20 | B34: Прочее: связь, печать, банк | C34: сум/заказ | D34: [факт] | E34: =IF(F34="","",F34) -> 10000 | F34: 10000 | G34: =IF(F34="","",F34) -> 10000 | H34: Владелец, форма 18.10.2026, вопрос 5
A35: P21 | B35: Юридические и страховые расходы (ответственность оценщика) | C35: сум/заказ | D35: нужно от Темура | E35: =IF(F35="","",F35) | G35: =IF(F35="","",F35) | H35: — | I35: Не спрашивалось. Администратор и офис, которые владелец вычитал в вопросе 3, в вопросе 5 не названы — см. сверку в «Юнит-экономика».
A36: C. Решения I1, D10, агрегатор и партнёры
A37: P22 | B37: I1: кому идут заказы (1 = только KMT, 2 = агрегатор: часть заказов уходит партнёрам с комиссией проекту) | C37: 1/2 | D37: [выбор] | E37: =IF(F37="","",F37) -> 2 | F37: 2 | G37: =IF(F37="","",F37) -> 2 | H37: Решение за владельцем; в 08 не записано | I37: Ответы на вопросы 13–14 прочитаны как намерение подключить партнёров. Переключатель 1 даёт вариант «только KMT»; оба варианта рядом — в листе D10_I1.
A38: P23 | B38: D10: что видит клиент после оценки (1 = блок KMT с контактами без формы, 2 = нейтральный текст) | C38: 1/2 | D38: [выбор] | E38: =IF(F38="","",F38) -> 1 | F38: 1 | G38: =IF(F38="","",F38) -> 1 | H38: Владелец 18.10: блок KMT с контактами, без формы до A4 | I38: Решение за владельцем. Блок «только KMT» не совместим с передачей 70% заказов партнёрам: для партнёров нужен нейтральный список оценщиков (D10-г, не смоделирован).
A39: P24 | B39: Берёт ли проект (Bizzone) комиссию и с заказов, идущих в KMT? (1 = да, 0 = нет) | C39: 1/0 | D39: [факт] | E39: =IF(F39="","",F39) -> 1 | F39: 1 | G39: =IF(F39="","",F39) -> 1 | H39: Владелец, форма 18.10.2026, вопрос 13 | I39: «Да, и с заказов KMT».
A40: P25 | B40: Комиссия сайта как агрегатора, % от суммы договора без НДС | C40: % | D40: [факт] | E40: =IF(F40="","",F40) -> 0.1 | F40: 0.1 | G40: =IF(F40="","",F40) -> 0.1 | H40: Владелец 18.10; Владелец, форма 18.10.2026, вопрос 13 | I40: Платит оценочная компания-партнёр. Для заказов KMT — межгрупповой платёж.
A41: P26 | B41: Доля заказов с сайта, которая уходит партнёрам (после их подключения) | C41: % | D41: [гипотеза] | E41: =IF(F41="","",F41) -> 0.7 | F41: 0.7 | G41: =IF(F41="","",F41) -> 0.7 | H41: Владелец, форма 18.10.2026, вопрос 14 | I41: Оценка владельца. Работает только при I1 = 2.
A42: P27 | B42: Партнёры принимают заказы после месяца №… от запуска | C42: мес | D42: [гипотеза] | E42: 9 | F42: 6 | G42: 3 | H42: Владелец, форма 18.10.2026, вопрос 14 | I42: База = «через 6 месяцев» со слов владельца. Пессимист и оптимист ±3 месяца — моя гипотеза, не данные.
A43: P28 | B43: Средний договор партнёра, без НДС | C43: сум | D43: [гипотеза] | E43: =IF(F43="","",F43) -> 1000000 | F43: 1000000 | G43: =IF(F43="","",F43) -> 1000000 | H43: Владелец, форма 18.10.2026, вопрос 14 | I43: Совпадает с чеком KMT; сколько платят партнёры, неизвестно.
A44: P29 | B44: Доля прибыли KMT (после комиссии), передаваемая проекту | C44: % | D44: [факт] | E44: =IF(F44="","",F44) -> 0 | F44: 0 | G44: =IF(F44="","",F44) -> 0 | H44: Владелец, форма 18.10.2026, вопрос 16 | I44: Вся прибыль заказа остаётся в KMT; проект получает только комиссию. Если нужно иначе — сюда.
A45: P30 | B45: Доля заказов от рекомендателей (банк, брокер, нотариус) с вознаграждением | C45: % | D45: нужно от Темура | E45: =IF(F45="","",F45) | G45: =IF(F45="","",F45) | H45: Владелец, форма 18.10.2026, вопрос 15 | I45: Платить планируют 10% от чека, но сколько заказов придёт этим путём — не известно. Пусто = 0.
A46: P31 | B46: Вознаграждение рекомендателю, % от чека | C46: % | D46: [факт] | E46: =IF(F46="","",F46) -> 0.1 | F46: 0.1 | G46: =IF(F46="","",F46) -> 0.1 | H46: Владелец, форма 18.10.2026, вопрос 15 | I46: Планируют платить 10%. Допустимость — вопрос юристу (14 п.4.3).
A47: P32 | B47: D10 = нейтральный текст: какая доля заказов сохраняется относительно блока KMT | C47: % | D47: [заглушка] | E47: =IF(F47="","",F47) -> 0.25 | F47: 0.25 | G47: =IF(F47="","",F47) -> 0.25 | H47: — | I47: Данных нет. Измерять по кликам на первых 100 результатах (14 п.4.2).
A48: D. Допустимое привлечение, мощность и пороги
A49: P33 | B49: Потолок доли дохода с заказа на привлечение | C49: % | D49: [гипотеза] | E49: =IF(F49="","",F49) -> 0.2 | F49: 0.2 | G49: =IF(F49="","",F49) -> 0.2 | H49: 14_Rebaseline п.4.1: рабочий потолок 20%, только для расчётов | I49: Не измерено на этом рынке. Пересмотр на неделе 8–10.
A50: P34 | B50: Маркетинговый бюджет в месяц (постоянный) | C50: сум/мес | D50: [факт] | E50: =IF(F50="","",F50) -> 0 | F50: 0 | G50: =IF(F50="","",F50) -> 0 | H50: 08_Decisions п.5; Владелец, форма 18.10.2026, вопрос 12 | I50: Постоянного бюджета нет; разовая проба — в блоке H.
A51: P35 | B51: Заказов в месяц у KMT сейчас | C51: шт/мес | D51: [факт] | E51: =IF(F51="","",F51) -> 10 | F51: 10 | G51: =IF(F51="","",F51) -> 10 | H51: Владелец, форма 18.10.2026, вопрос 17
A52: P36 | B52: Максимум заказов в месяц без найма | C52: шт/мес | D52: [факт] | E52: =IF(F52="","",F52) -> 20 | F52: 20 | G52: =IF(F52="","",F52) -> 20 | H52: Владелец, форма 18.10.2026, вопрос 17 | I52: Запас для заказов с сайта = максимум − сейчас. Пусто или 0 = ограничения нет.
A53: P37 | B53: Приемлемый срок окупаемости | C53: мес | D53: [факт] | E53: =IF(F53="","",F53) -> 3 | F53: 3 | G53: =IF(F53="","",F53) -> 3 | H53: Владелец, форма 18.10.2026, вопрос 12 | I53: Сравнивается с результатом листа «Сценарии_BEP».
A54: E. Воронка
A55: P38 | B55: Расчётов уровня 1 в месяц (в режиме) | C55: шт/мес | D55: [заглушка] | E55: 100 | F55: 300 | G55: 900 | H55: Оставлено по решению владельца (вопрос 20); market_sizing.xlsx пока не подключён | I55: Не прогноз. Это самое слабое место модели.
A56: P39 | B56: Конверсия посетитель → расчёт | C56: % | D56: нужно от Темура | E56: =IF(F56="","",F56) | G56: =IF(F56="","",F56) | H56: Измерять (E2) | I56: Данных воронки нет. Пусто = число посетителей не считается.
A57: P40 | B57: Конверсия расчёт → интерес (контакт или клик по блоку KMT) | C57: % | D57: [гипотеза] | E57: 0.15 | F57: 0.2 | G57: 0.25 | H57: 05_4P: контакт 15–25% от ур.1 | I57: До A4 контактов нет: измеряется анонимным кликом по блоку KMT.
A58: P41 | B58: Конверсия интерес → заказ уровня 3 | C58: % | D58: [гипотеза] | E58: 0.05 | F58: 0.05 | G58: 0.05 | H58: Владелец, форма 18.10.2026, вопрос 20 (5% в сценариях «Осторожный» и «Базовый»; «Оптимистичный» оставлен по умолчанию 5%) | I58: Ввод владельца заменил мои 2% / 3,5% / 5% из 05_4P. Во всех трёх сценариях одно значение: разброс сценариев занижен. Таблицы с 2% и 3,5% — в «Чувствительности».
A59: P42 | B59: Доля заказов, которых KMT не получил бы без HomePrice | C59: % | D59: [гипотеза] | E59: =IF(F59="","",F59) -> 0.9 | F59: 0.9 | G59: =IF(F59="","",F59) -> 0.9 | H59: Владелец, форма 18.10.2026, вопрос 18 | I59: «Почти все (около 90%)».
A60: P43 | B60: Месяцев выхода на режим | C60: мес | D60: [гипотеза] | E60: =IF(F60="","",F60) -> 2 | F60: 2 | G60: =IF(F60="","",F60) -> 2 | H60: 05_4P: органика 6–8 недель | I60: Линейный рост объёма от 0 до режима.
A61: F. Постоянные операционные расходы (в месяц)
A62: P44 | B62: Хостинг и сервисы | C62: сум/мес | D62: [факт] | E62: =IF(F62="","",F62) -> 1000000 | F62: 1000000 | G62: =IF(F62="","",F62) -> 1000000 | H62: Владелец, форма 18.10.2026, вопрос 9 | I62: Сервер в РУз, домен, Telegram-бот, аналитика, SMS-сервис, ИИ-ассистент, резервные копии; без НДС; останется таким.
A63: P45 | B63: SMS-рассылки + колл-центр + другое | C63: сум/мес | D63: [факт] | E63: =IF(F63="","",F63) -> 6500000 | F63: 6500000 | G63: =IF(F63="","",F63) -> 6500000 | H63: Владелец, форма 18.10.2026, вопрос 10 | I63: 1 000 000 SMS + 5 000 000 колл-центр + 500 000 другое. Колл-центр — самая большая статья: проверить, нужен ли он с первого месяца.
A64: G. Часы команды и ставки
A65: P46 | B65: Единицы часов (1 = в неделю, 2 = в месяц, 3 = на весь этап 1) | C65: 1/2/3 | D65: [факт] | E65: =IF(F65="","",F65) -> 1 | F65: 1 | G65: =IF(F65="","",F65) -> 1 | H65: Владелец, форма 18.10.2026, вопрос 6 | I65: Все трое — в неделю.
A66: P47 | B66: Длительность этапа 1 (разработка и запуск) | C66: мес | D66: [факт] | E66: =IF(F66="","",F66) -> 3 | F66: 3 | G66: =IF(F66="","",F66) -> 3 | H66: Владелец, форма 18.10.2026, вопрос 6 | I66: Разработка идёт до запуска; 12 месяцев работы считаются после неё.
A67: P48 | B67: Часы: Темур | C67: ч/период | D67: [факт] | E67: 20 | F67: 17.5 | G67: 15 | H67: Владелец 18.10: 15–20 | I67: Пессимист = 20, оптимист = 15.
A68: P49 | B68: Часы: Равшан | C68: ч/период | D68: [факт] | E68: 20 | F68: 17.5 | G68: 15 | H68: Владелец 18.10: 15–20 | I68: Так же.
A69: P50 | B69: Часы: Азиз | C69: ч/период | D69: [факт] | E69: =IF(F69="","",F69) -> 50 | F69: 50 | G69: =IF(F69="","",F69) -> 50 | H69: Владелец 18.10: 50 | I69: 50 часов в неделю: больше полной занятости (40 ч).
A70: P51 | B70: Как читать ставку (1 = сум за час, 2 = сум за месяц полной занятости, пропорционально часам, 3 = сум за месяц как есть, независимо от часов) | C70: 1/2/3 | D70: [выбор] | E70: =IF(F70="","",F70) -> 2 | F70: 2 | G70: =IF(F70="","",F70) -> 2 | H70: Владелец, форма 18.10.2026, вопрос 8: «по рыночной ставке, сум за месяц» | I70: Чтение 2 — мой выбор [проверить]: ставка = рыночная цена полного месяца, оплачиваются фактические часы. Чтение 3 даёт другой результат (см. «Чувствительность», таблица 12).
A71: P52 | B71: Часов в неделю при полной занятости | C71: ч/нед | D71: [гипотеза] | E71: =IF(F71="","",F71) -> 40 | F71: 40 | G71: =IF(F71="","",F71) -> 40 | H71: — | I71: Нужно только для чтения 2.
A72: P53 | B72: Ставка: Темур | C72: сум/мес | D72: [факт][проверить] | E72: =IF(F72="","",F72) -> 20000000 | F72: 20000000 | G72: =IF(F72="","",F72) -> 20000000 | H72: Владелец, форма 18.10.2026, вопрос 8 | I72: Рыночная ставка по оценке владельца.
A73: P54 | B73: Ставка: Равшан | C73: сум/мес | D73: [факт][проверить] | E73: =IF(F73="","",F73) -> 20000000 | F73: 20000000 | G73: =IF(F73="","",F73) -> 20000000 | H73: Владелец, форма 18.10.2026, вопрос 8
A74: P55 | B74: Ставка: Азиз | C74: сум/мес | D74: [факт][проверить] | E74: =IF(F74="","",F74) -> 5000000 | F74: 5000000 | G74: =IF(F74="","",F74) -> 5000000 | H74: Владелец, форма 18.10.2026, вопрос 8
A75: P56 | B75: Доля часов Темура на разработку и запуск (разово) | C75: % | D75: [факт] | E75: =IF(F75="","",F75) -> 1 | F75: 1 | G75: =IF(F75="","",F75) -> 1 | H75: Владелец, форма 18.10.2026, вопрос 7 | I75: 100%: после запуска Темур в расчёте не работает. Проверить, так ли это на самом деле (контент, партнёры).
A76: P57 | B76: Доля часов Равшана на разработку и запуск (разово) | C76: % | D76: [факт] | E76: =IF(F76="","",F76) -> 1 | F76: 1 | G76: =IF(F76="","",F76) -> 1 | H76: Владелец, форма 18.10.2026, вопрос 7
A77: P58 | B77: Доля часов Азиза на разработку и запуск (разово) | C77: % | D77: [факт] | E77: =IF(F77="","",F77) -> 0.8 | F77: 0.8 | G77: =IF(F77="","",F77) -> 0.8 | H77: Владелец, форма 18.10.2026, вопрос 7 | I77: Остальные 20% — постоянная работа.
A78: H. Разовые расходы разработки и запуска (вне операционных)
A79: P59 | B79: Юрист, документы pd.gov.uz | C79: сум | D79: [факт] | E79: =IF(F79="","",F79) -> 500000 | F79: 500000 | G79: =IF(F79="","",F79) -> 500000 | H79: Владелец, форма 18.10.2026, вопрос 11
A80: P60 | B80: Пошлины и регистрации | C80: сум | D80: [факт][проверить] | E80: =IF(F80="","",F80) -> 0 | F80: 0 | G80: =IF(F80="","",F80) -> 0 | H80: Владелец, форма 18.10.2026, вопрос 11 | I80: 0 со слов; проверить, действительно ли пошлин нет.
A81: P61 | B81: Договоры Click/Payme, платёжная интеграция | C81: сум | D81: [факт][проверить] | E81: =IF(F81="","",F81) -> 0 | F81: 0 | G81: =IF(F81="","",F81) -> 0 | H81: Владелец, форма 18.10.2026, вопрос 11 | I81: 0 со слов; проверить.
A82: P62 | B82: Внешняя разработка, дизайн | C82: сум | D82: [факт] | E82: =IF(F82="","",F82) -> 3000000 | F82: 3000000 | G82: =IF(F82="","",F82) -> 3000000 | H82: Владелец, форма 18.10.2026, вопрос 11
A83: P63 | B83: Пробная реклама (разово) | C83: сум | D83: [факт] | E83: =IF(F83="","",F83) -> 1000000 | F83: 1000000 | G83: =IF(F83="","",F83) -> 1000000 | H83: Владелец, форма 18.10.2026, вопрос 12 | I83: Предел потерь на пробу привлечения (микротест).
A84: I. Реакция спроса на цену (для проверки цены ±10% и ±20%)
A85: P64 | B85: Изменение числа заказов при росте цены на 10% | C85: доля | D85: [гипотеза] | E85: =IF(F85="","",F85) -> -0.175 | F85: -0.175 | G85: =IF(F85="","",F85) -> -0.175 | H85: Владелец, форма 18.10.2026, вопрос 19: «заметно меньше (на 15–20%)» | I85: Взята середина диапазона.
B87: Рынок: размер подтянуть из market_sizing.xlsx, когда он будет готов (сейчас — заглушка в строке «Расчётов уровня 1 в месяц»).

Sheet Вопросы к Темуру
A1: Вопросы к Темуру: что осталось уточнить после ответов 18.10.2026
A2: Красных входов осталось немного; главный вопрос — размер рынка (market_sizing.xlsx), без него сценарии объёма остаются заглушкой.
A4: № | B4: Вопрос | C4: Зачем (какие ячейки) | D4: Формат ответа
A5: Q1 | B5: Прибыль с заказа: вы назвали среднюю 400 тыс. сум, а построчные затраты (гонорар 100 тыс., выезд 100 тыс., документы 20 тыс., налоги 70 тыс., прочее 10 тыс.) дают 700 тыс. Что входит в оставшиеся 300 тыс. (администратор, офис, юридические)? Они растут с каждым заказом или это постоянные расходы? | C5: margin_abs, dc7. Если постоянные — для дополнительного заказа прибыль ближе к 700 тыс. | D5: Список статей и сумма
A6: Q2 | B6: Ставки 20 / 20 / 5 млн сум в месяц: это цена полного месяца (40 ч в неделю), из которой оплачиваются фактические часы, или сумма за ваши фактические часы как есть? Сейчас принято первое. | C6: rate_mode. Разница видна в таблице 12 листа «Чувствительность» | D6: 1 / 2 / 3
A7: Q3 | B7: Темур и Равшан — 100% на разработку: после запуска их время в проекте не считается. Так и есть? Кто ведёт контент, партнёров, ответы клиентам после запуска? | C7: dT, dR. Влияет на постоянные расходы | D7: Доли %
A8: Q4 | B8: Колл-центр 5 млн сум в месяц с первого месяца: нужен ли он при нескольких заказах в месяц? Это самая большая статья после труда. | C8: oth. Меняет БУ в разы | D8: Да/нет и сумма
A9: Q5 | B9: Конверсия интерес → заказ: вы ввели 5% в сценариях «Осторожный» и «Базовый» (в «Оптимистичном» осталось 5% по умолчанию). Все три сценария на 5% — это намеренно? Если да, чем «Осторожный» хуже? Мои исходные 2% / 3,5% есть в таблицах чувствительности. | C9: c2 | D9: Три числа
A10: Q6 | B10: Вознаграждение рекомендателям 10%: для скольких заказов из 100 планируется (банки, брокеры, нотариусы)? Юрист: допустимо ли оно? | C10: share_ref. Пока 0 | D10: Доля %, решение юриста
A11: Q7 | B11: Договор между Bizzone и KMT о комиссии 10% с заказов KMT: оформляется или только идея? Платит ли комиссию партнёр сверху к своей цене или из неё? | C11: agg_kmt, fee | D11: Да/нет
A12: Q8 | B12: Партнёры берут 70% заказов с сайта через 6 месяцев. Достаточно ли 3–5 партнёров на такую долю? А «блок KMT с контактами» (D10 б+) при этом остаётся? Он не передаёт заказы партнёрам. | C12: sp, pstart, sel_i1, sel_d10 (решения за вами) | D12: Решение
A13: Q9 | B13: Статус Bizzone по НДС: комиссия сайта 10% облагается НДС? | C13: fee, vat_incl | D13: Да/нет и ставка
A14: Q10 | B14: Когда будет готов market_sizing.xlsx и какая доля рынка достижима? Сейчас объём расчётов — заглушка 100 / 300 / 900 в месяц. | C14: calcs (главная неопределённость модели) | D14: Дата и доля
A15: Q11 | B15: Нулевые пошлины и платёжная интеграция (Click/Payme): действительно ноль? | C15: ot2, ot3 | D15: Да/нет и сумма
A16: Q12 | B16: Доли заказов 15% / 75% / 10% по цене — по памяти или по учёту? Можно ли выгрузить последние 30 заказов (цена, прибыль)? | C16: p800, p1m, pHigh, margin_abs | D16: Выгрузка без ФИО

Sheet Юнит-экономика
A1: Юнит-экономика заказа уровня 3 (отчёт KMT) и комиссия агрегатора
A2: Все числа — из листа «Входные данные». «Владелец» = KMT и проект вместе (комиссия внутри группы взаимно гасится). «Проект» = только Bizzone.
B4: Показатель | C4: Пессимист | D4: База | E4: Оптимист | F4: Комментарий
B5: 1. Выручка и прямые затраты заказа KMT
B6: Средняя цена отчёта | C6: =N('Входные данные'!$E$20) -> 1020000 | D6: =N('Входные данные'!$F$20) -> 1020000 | E6: =N('Входные данные'!$G$20) -> 1020000 | F6: По долям заказов 800 тыс. / 1 млн / дороже (вопрос 1)
B7: НДС в цене | C7: =IF(N('Входные данные'!$E$22)=1,'Юнит-экономика'!$C$6-'Юнит-экономика'!$C$6/(1+N('Входные данные'!$E$23)),0) -> 0 | D7: =IF(N('Входные данные'!$F$22)=1,'Юнит-экономика'!$D$6-'Юнит-экономика'!$D$6/(1+N('Входные данные'!$F$23)),0) -> 0 | E7: =IF(N('Входные данные'!$G$22)=1,'Юнит-экономика'!$E$6-'Юнит-экономика'!$E$6/(1+N('Входные данные'!$G$23)),0) -> 0 | F7: [факт] KMT не платит НДС
B8: Выручка без НДС | C8: ='Юнит-экономика'!$C$6-'Юнит-экономика'!$C$7 -> 1020000 | D8: ='Юнит-экономика'!$D$6-'Юнит-экономика'!$D$7 -> 1020000 | E8: ='Юнит-экономика'!$E$6-'Юнит-экономика'!$E$7 -> 1020000
B9: Сумма построчных прямых затрат (метод 2) | C9: =N('Входные данные'!$E$29)+N('Входные данные'!$E$30)+N('Входные данные'!$E$31)+N('Входные данные'!$E$32)+N('Входные данные'!$E$33)+N('Входные данные'!$E$34)+N('Входные данные'!$E$35) -> 300000 | D9: =N('Входные данные'!$F$29)+N('Входные данные'!$F$30)+N('Входные данные'!$F$31)+N('Входные данные'!$F$32)+N('Входные данные'!$F$33)+N('Входные данные'!$F$34)+N('Входные данные'!$F$35) -> 300000 | E9: =N('Входные данные'!$G$29)+N('Входные данные'!$G$30)+N('Входные данные'!$G$31)+N('Входные данные'!$G$32)+N('Входные данные'!$G$33)+N('Входные данные'!$G$34)+N('Входные данные'!$G$35) -> 300000 | F9: Вопросы 4–5; юридические и страховые (dc7) не названы
B10: Прибыль заказа по оценке владельца (методы 1 и 3) | C10: =IF(N('Входные данные'!$E$26)=1,'Юнит-экономика'!$C$8*N('Входные данные'!$E$28),N('Входные данные'!$E$27)) -> 300000 | D10: =IF(N('Входные данные'!$F$26)=1,'Юнит-экономика'!$D$8*N('Входные данные'!$F$28),N('Входные данные'!$F$27)) -> 400000 | E10: =IF(N('Входные данные'!$G$26)=1,'Юнит-экономика'!$E$8*N('Входные данные'!$G$28),N('Входные данные'!$G$27)) -> 700000 | F10: Метод 3: средняя прибыль со слов владельца
B11: Прямые затраты на заказ | C11: =IF(N('Входные данные'!$E$26)=2,'Юнит-экономика'!$C$9,'Юнит-экономика'!$C$8-'Юнит-экономика'!$C$10) -> 720000 | D11: =IF(N('Входные данные'!$F$26)=2,'Юнит-экономика'!$D$9,'Юнит-экономика'!$D$8-'Юнит-экономика'!$D$10) -> 620000 | E11: =IF(N('Входные данные'!$G$26)=2,'Юнит-экономика'!$E$9,'Юнит-экономика'!$E$8-'Юнит-экономика'!$E$10) -> 320000 | F11: При методе 3 затраты = выручка − средняя прибыль
B12: Прибыль заказа до комиссий | C12: ='Юнит-экономика'!$C$8-'Юнит-экономика'!$C$11 -> 300000 | D12: ='Юнит-экономика'!$D$8-'Юнит-экономика'!$D$11 -> 400000 | E12: ='Юнит-экономика'!$E$8-'Юнит-экономика'!$E$11 -> 700000
B13: Прибыль, % выручки | C13: =IF('Юнит-экономика'!$C$8>0,'Юнит-экономика'!$C$12/'Юнит-экономика'!$C$8,0) -> 0.29411765 | D13: =IF('Юнит-экономика'!$D$8>0,'Юнит-экономика'!$D$12/'Юнит-экономика'!$D$8,0) -> 0.39215686 | E13: =IF('Юнит-экономика'!$E$8>0,'Юнит-экономика'!$E$12/'Юнит-экономика'!$E$8,0) -> 0.68627451
B14: Источник прибыли | C14: =IF(N('Входные данные'!$E$26)=2,IF('Юнит-экономика'!$C$9=0,"НЕТ ДАННЫХ: строки пусты","построчно"),IF(N('Входные данные'!$E$26)=3,"средняя со слов владельца [проверить]","процент владельца [проверить]")) -> средняя со слов владельца [проверить] | D14: =IF(N('Входные данные'!$F$26)=2,IF('Юнит-экономика'!$D$9=0,"НЕТ ДАННЫХ: строки пусты","построчно"),IF(N('Входные данные'!$F$26)=3,"средняя со слов владельца [проверить]","процент владельца [проверить]")) -> средняя со слов владельца [проверить] | E14: =IF(N('Входные данные'!$G$26)=2,IF('Юнит-экономика'!$E$9=0,"НЕТ ДАННЫХ: строки пусты","построчно"),IF(N('Входные данные'!$G$26)=3,"средняя со слов владельца [проверить]","процент владельца [проверить]")) -> средняя со слов владельца [проверить]
B15: Сверка: прибыль по построчным затратам (выручка − сумма строк) | C15: ='Юнит-экономика'!$C$8-'Юнит-экономика'!$C$9 -> 720000 | D15: ='Юнит-экономика'!$D$8-'Юнит-экономика'!$D$9 -> 720000 | E15: ='Юнит-экономика'!$E$8-'Юнит-экономика'!$E$9 -> 720000 | F15: Верхняя граница: в строках нет администратора и офиса, которые владелец вычел в вопросе 3
B16: Сверка: построчная прибыль минус прибыль владельца | C16: ='Юнит-экономика'!$C$15-'Юнит-экономика'!$C$10 -> 420000 | D16: ='Юнит-экономика'!$D$15-'Юнит-экономика'!$D$10 -> 320000 | E16: ='Юнит-экономика'!$E$15-'Юнит-экономика'!$E$10 -> 20000 | F16: Расхождение = то, что владелец вычел сверх строк вопросов 4–5. Если это постоянные расходы, дополнительный заказ их не увеличит
B18: 2. Вознаграждение рекомендателю (банк, брокер, нотариус)
B19: Вознаграждение за заказ, пришедший через рекомендателя | C19: =N('Входные данные'!$E$46)*'Юнит-экономика'!$C$8 -> 102000 | D19: =N('Входные данные'!$F$46)*'Юнит-экономика'!$D$8 -> 102000 | E19: =N('Входные данные'!$G$46)*'Юнит-экономика'!$E$8 -> 102000 | F19: [факт] планируют 10% от чека
B20: Прибыль такого заказа после вознаграждения | C20: ='Юнит-экономика'!$C$12-'Юнит-экономика'!$C$19 -> 198000 | D20: ='Юнит-экономика'!$D$12-'Юнит-экономика'!$D$19 -> 298000 | E20: ='Юнит-экономика'!$E$12-'Юнит-экономика'!$E$19 -> 598000
B21: Вознаграждение съедает, % прибыли | C21: =IF('Юнит-экономика'!$C$12>0,'Юнит-экономика'!$C$19/'Юнит-экономика'!$C$12,0) -> 0.34 | D21: =IF('Юнит-экономика'!$D$12>0,'Юнит-экономика'!$D$19/'Юнит-экономика'!$D$12,0) -> 0.255 | E21: =IF('Юнит-экономика'!$E$12>0,'Юнит-экономика'!$E$19/'Юнит-экономика'!$E$12,0) -> 0.14571429
B22: Вознаграждение на средний заказ (с учётом доли рекомендателей) | C22: =N('Входные данные'!$E$45)*'Юнит-экономика'!$C$19 -> 0 | D22: =N('Входные данные'!$F$45)*'Юнит-экономика'!$D$19 -> 0 | E22: =N('Входные данные'!$G$45)*'Юнит-экономика'!$E$19 -> 0 | F22: Доля рекомендателей не известна (нужно от Темура): пока 0
B23: Прибыль среднего заказа KMT после вознаграждения | C23: ='Юнит-экономика'!$C$12-'Юнит-экономика'!$C$22 -> 300000 | D23: ='Юнит-экономика'!$D$12-'Юнит-экономика'!$D$22 -> 400000 | E23: ='Юнит-экономика'!$E$12-'Юнит-экономика'!$E$22 -> 700000 | F23: До комиссии проекту
B25: 3. Комиссия сайта как агрегатора и доходы на один заказ с сайта
B26: Комиссия проекта с заказа KMT | C26: =N('Входные данные'!$E$39)*N('Входные данные'!$E$40)*'Юнит-экономика'!$C$8 -> 102000 | D26: =N('Входные данные'!$F$39)*N('Входные данные'!$F$40)*'Юнит-экономика'!$D$8 -> 102000 | E26: =N('Входные данные'!$G$39)*N('Входные данные'!$G$40)*'Юнит-экономика'!$E$8 -> 102000 | F26: 10% от суммы договора без НДС; платёж KMT → проект (внутри группы)
B27: Комиссия проекта с заказа партнёра | C27: =N('Входные данные'!$E$40)*N('Входные данные'!$E$43) -> 100000 | D27: =N('Входные данные'!$F$40)*N('Входные данные'!$F$43) -> 100000 | E27: =N('Входные данные'!$G$40)*N('Входные данные'!$G$43) -> 100000 | F27: Платит партнёр; реальный приход группы
B28: Прибыль KMT с заказа после комиссии проекту | C28: ='Юнит-экономика'!$C$23-'Юнит-экономика'!$C$26 -> 198000 | D28: ='Юнит-экономика'!$D$23-'Юнит-экономика'!$D$26 -> 298000 | E28: ='Юнит-экономика'!$E$23-'Юнит-экономика'!$E$26 -> 598000
B29: Доход проекта (Bizzone) с заказа KMT | C29: ='Юнит-экономика'!$C$26+N('Входные данные'!$E$44)*'Юнит-экономика'!$C$28 -> 102000 | D29: ='Юнит-экономика'!$D$26+N('Входные данные'!$F$44)*'Юнит-экономика'!$D$28 -> 102000 | E29: ='Юнит-экономика'!$E$26+N('Входные данные'!$G$44)*'Юнит-экономика'!$E$28 -> 102000 | F29: Комиссия + доля прибыли KMT (по умолчанию 0)
B30: I1 = только KMT: доход владельца на заказ сайта | C30: ='Юнит-экономика'!$C$23 -> 300000 | D30: ='Юнит-экономика'!$D$23 -> 400000 | E30: ='Юнит-экономика'!$E$23 -> 700000
B31: I1 = только KMT: доход проекта на заказ сайта | C31: ='Юнит-экономика'!$C$29 -> 102000 | D31: ='Юнит-экономика'!$D$29 -> 102000 | E31: ='Юнит-экономика'!$E$29 -> 102000
B32: I1 = агрегатор: доход владельца на заказ сайта (после подключения партнёров) | C32: =(1-N('Входные данные'!$E$41))*'Юнит-экономика'!$C$23+N('Входные данные'!$E$41)*'Юнит-экономика'!$C$27 -> 160000 | D32: =(1-N('Входные данные'!$F$41))*'Юнит-экономика'!$D$23+N('Входные данные'!$F$41)*'Юнит-экономика'!$D$27 -> 190000 | E32: =(1-N('Входные данные'!$G$41))*'Юнит-экономика'!$E$23+N('Входные данные'!$G$41)*'Юнит-экономика'!$E$27 -> 280000 | F32: Заказы партнёров приносят только комиссию, остальные — прибыль KMT
B33: I1 = агрегатор: доход проекта на заказ сайта | C33: =(1-N('Входные данные'!$E$41))*'Юнит-экономика'!$C$29+N('Входные данные'!$E$41)*'Юнит-экономика'!$C$27 -> 100600 | D33: =(1-N('Входные данные'!$F$41))*'Юнит-экономика'!$D$29+N('Входные данные'!$F$41)*'Юнит-экономика'!$D$27 -> 100600 | E33: =(1-N('Входные данные'!$G$41))*'Юнит-экономика'!$E$29+N('Входные данные'!$G$41)*'Юнит-экономика'!$E$27 -> 100600
B34: Выбранный вариант: доход владельца на заказ сайта | C34: =IF(N('Входные данные'!$E$37)=2,'Юнит-экономика'!$C$32,'Юнит-экономика'!$C$30) -> 160000 | D34: =IF(N('Входные данные'!$F$37)=2,'Юнит-экономика'!$D$32,'Юнит-экономика'!$D$30) -> 190000 | E34: =IF(N('Входные данные'!$G$37)=2,'Юнит-экономика'!$E$32,'Юнит-экономика'!$E$30) -> 280000 | F34: Без учёта ограничения мощности KMT
B35: Выбранный вариант: доход проекта на заказ сайта | C35: =IF(N('Входные данные'!$E$37)=2,'Юнит-экономика'!$C$33,'Юнит-экономика'!$C$31) -> 100600 | D35: =IF(N('Входные данные'!$F$37)=2,'Юнит-экономика'!$D$33,'Юнит-экономика'!$D$31) -> 100600 | E35: =IF(N('Входные данные'!$G$37)=2,'Юнит-экономика'!$E$33,'Юнит-экономика'!$E$31) -> 100600 | F35: Только комиссия: прибыль KMT проекту не передаётся
B37: 4. Допустимая стоимость привлечения (потолок = доля дохода)
B38: Допустимо на один заказ (по доходу владельца) | C38: =N('Входные данные'!$E$49)*MAX(0,'Юнит-экономика'!$C$34) -> 32000 | D38: =N('Входные данные'!$F$49)*MAX(0,'Юнит-экономика'!$D$34) -> 38000 | E38: =N('Входные данные'!$G$49)*MAX(0,'Юнит-экономика'!$E$34) -> 56000 | F38: [гипотеза] 20% (14, п.4.1)
B39: Допустимо на один заказ (только по доходу проекта) | C39: =N('Входные данные'!$E$49)*MAX(0,'Юнит-экономика'!$C$35) -> 20120 | D39: =N('Входные данные'!$F$49)*MAX(0,'Юнит-экономика'!$D$35) -> 20120 | E39: =N('Входные данные'!$G$49)*MAX(0,'Юнит-экономика'!$E$35) -> 20120 | F39: Если платит один проект, допустимо на порядок меньше
B40: Допустимо на один «интерес» (контакт, клик) | C40: ='Юнит-экономика'!$C$38*N('Входные данные'!$E$58) -> 1600 | D40: ='Юнит-экономика'!$D$38*N('Входные данные'!$F$58) -> 1900 | E40: ='Юнит-экономика'!$E$38*N('Входные данные'!$G$58) -> 2800
B41: Допустимо на один расчёт уровня 1 | C41: ='Юнит-экономика'!$C$38*N('Входные данные'!$E$57)*N('Входные данные'!$E$58)*N('Входные данные'!$E$59) -> 216 | D41: ='Юнит-экономика'!$D$38*N('Входные данные'!$F$57)*N('Входные данные'!$F$58)*N('Входные данные'!$F$59) -> 342 | E41: ='Юнит-экономика'!$E$38*N('Входные данные'!$G$57)*N('Входные данные'!$G$58)*N('Входные данные'!$G$59) -> 630 | F41: Платный трафик на потребительский калькулятор окупается только при очень дешёвом клике
B42: То же, долларов | C42: =IF(N('Входные данные'!$E$24)>0,'Юнит-экономика'!$C$41/N('Входные данные'!$E$24),0) -> 0.018 | D42: =IF(N('Входные данные'!$F$24)>0,'Юнит-экономика'!$D$41/N('Входные данные'!$F$24),0) -> 0.0285 | E42: =IF(N('Входные данные'!$G$24)>0,'Юнит-экономика'!$E$41/N('Входные данные'!$G$24),0) -> 0.0525
B43: Вознаграждение рекомендателю больше потолка привлечения в … раз | C43: =IF(AND('Юнит-экономика'!$C$20>0,N('Входные данные'!$E$49)>0),'Юнит-экономика'!$C$19/(N('Входные данные'!$E$49)*'Юнит-экономика'!$C$20),"н/д") -> 2.5757576 | D43: =IF(AND('Юнит-экономика'!$D$20>0,N('Входные данные'!$F$49)>0),'Юнит-экономика'!$D$19/(N('Входные данные'!$F$49)*'Юнит-экономика'!$D$20),"н/д") -> 1.7114094 | E43: =IF(AND('Юнит-экономика'!$E$20>0,N('Входные данные'!$G$49)>0),'Юнит-экономика'!$E$19/(N('Входные данные'!$G$49)*'Юнит-экономика'!$E$20),"н/д") -> 0.85284281 | F43: Если >1, вознаграждение выше потолка 20% и вводить его нельзя без пересмотра потолка

Sheet Воронка
A1: Воронка: посетитель → расчёт → интерес → заказ, и куда идут заказы
A2: Конверсии из 05_4P — гипотезы (c2 заменена вводом владельца). Режим = после выхода на режим и подключения партнёров.
B4: Показатель | C4: Пессимист | D4: База | E4: Оптимист | F4: Комментарий
B5: Посетителей в месяц | C5: =IF(N('Входные данные'!$E$56)>0,N('Входные данные'!$E$55)/N('Входные данные'!$E$56),"нужно измерить") -> нужно измерить | D5: =IF(N('Входные данные'!$F$56)>0,N('Входные данные'!$F$55)/N('Входные данные'!$F$56),"нужно измерить") -> нужно измерить | E5: =IF(N('Входные данные'!$G$56)>0,N('Входные данные'!$G$55)/N('Входные данные'!$G$56),"нужно измерить") -> нужно измерить | F5: Нужна конверсия посетитель → расчёт (нужно от Темура / E2)
B6: Расчётов уровня 1 в месяц | C6: =N('Входные данные'!$E$55) -> 100 | D6: =N('Входные данные'!$F$55) -> 300 | E6: =N('Входные данные'!$G$55) -> 900 | F6: [заглушка] до market_sizing.xlsx
B7: Конверсия расчёт → интерес | C7: =N('Входные данные'!$E$57) -> 0.15 | D7: =N('Входные данные'!$F$57) -> 0.2 | E7: =N('Входные данные'!$G$57) -> 0.25 | F7: [гипотеза] 05_4P
B8: Интересов в месяц | C8: =Воронка!$C$6*Воронка!$C$7 -> 15 | D8: =Воронка!$D$6*Воронка!$D$7 -> 60 | E8: =Воронка!$E$6*Воронка!$E$7 -> 225
B9: Конверсия интерес → заказ | C9: =N('Входные данные'!$E$58) -> 0.05 | D9: =N('Входные данные'!$F$58) -> 0.05 | E9: =N('Входные данные'!$G$58) -> 0.05 | F9: [гипотеза] ввод владельца 5%
B10: Заказов уровня 3 в месяц (всего) | C10: =Воронка!$C$8*Воронка!$C$9 -> 0.75 | D10: =Воронка!$D$8*Воронка!$D$9 -> 3 | E10: =Воронка!$E$8*Воронка!$E$9 -> 11.25
B11: Доля инкрементальных заказов | C11: =N('Входные данные'!$E$59) -> 0.9 | D11: =N('Входные данные'!$F$59) -> 0.9 | E11: =N('Входные данные'!$G$59) -> 0.9 | F11: [гипотеза] около 90% со слов владельца
B12: Инкрементальных заказов в месяц | C12: =Воронка!$C$10*Воронка!$C$11 -> 0.675 | D12: =Воронка!$D$10*Воронка!$D$11 -> 2.7 | E12: =Воронка!$E$10*Воронка!$E$11 -> 10.125
B13: Сквозная конверсия расчёт → инкрементальный заказ | C13: =Воронка!$C$7*Воронка!$C$9*Воронка!$C$11 -> 0.00675 | D13: =Воронка!$D$7*Воронка!$D$9*Воронка!$D$11 -> 0.009 | E13: =Воронка!$E$7*Воронка!$E$9*Воронка!$E$11 -> 0.01125
B14: Расчётов на один заказ | C14: =IF(Воронка!$C$13>0,1/Воронка!$C$13,"нет конверсии") -> 148.14815 | D14: =IF(Воронка!$D$13>0,1/Воронка!$D$13,"нет конверсии") -> 111.11111 | E14: =IF(Воронка!$E$13>0,1/Воронка!$E$13,"нет конверсии") -> 88.888889
B16: Влияние D10, мощность KMT и партнёры (режим)
B17: Множитель потока по выбранному D10 | C17: =IF(N('Входные данные'!$E$38)=2,N('Входные данные'!$E$47),1) -> 1 | D17: =IF(N('Входные данные'!$F$38)=2,N('Входные данные'!$F$47),1) -> 1 | E17: =IF(N('Входные данные'!$G$38)=2,N('Входные данные'!$G$47),1) -> 1 | F17: б+ = 100%; нейтральный текст = доля m_a [заглушка]
B18: Заказов с сайта в месяц (режим, с учётом D10) | C18: =Воронка!$C$12*Воронка!$C$17 -> 0.675 | D18: =Воронка!$D$12*Воронка!$D$17 -> 2.7 | E18: =Воронка!$E$12*Воронка!$E$17 -> 10.125
B19: Запас мощности KMT: заказов в месяц сверх нынешних | C19: =IF(N('Входные данные'!$E$52)>0,MAX(0,N('Входные данные'!$E$52)-N('Входные данные'!$E$51)),1000000000) -> 10 | D19: =IF(N('Входные данные'!$F$52)>0,MAX(0,N('Входные данные'!$F$52)-N('Входные данные'!$F$51)),1000000000) -> 10 | E19: =IF(N('Входные данные'!$G$52)>0,MAX(0,N('Входные данные'!$G$52)-N('Входные данные'!$G$51)),1000000000) -> 10 | F19: Максимум без найма − сейчас. 1 000 000 000 = ограничения нет (мощность не задана)
B20: Доля заказов, уходящая партнёрам (режим) | C20: =IF(N('Входные данные'!$E$37)=2,N('Входные данные'!$E$41),0) -> 0.7 | D20: =IF(N('Входные данные'!$F$37)=2,N('Входные данные'!$F$41),0) -> 0.7 | E20: =IF(N('Входные данные'!$G$37)=2,N('Входные данные'!$G$41),0) -> 0.7 | F20: Только при I1 = 2, после подключения партнёров
B21: Заказов, направленных в KMT, в месяц | C21: =Воронка!$C$18*(1-Воронка!$C$20) -> 0.2025 | D21: =Воронка!$D$18*(1-Воронка!$D$20) -> 0.81 | E21: =Воронка!$E$18*(1-Воронка!$E$20) -> 3.0375
B22: Заказов, которые KMT возьмёт (в пределах мощности) | C22: =MIN(Воронка!$C$21,Воронка!$C$19) -> 0.2025 | D22: =MIN(Воронка!$D$21,Воронка!$D$19) -> 0.81 | E22: =MIN(Воронка!$E$21,Воронка!$E$19) -> 3.0375
B23: Заказов теряется из-за мощности KMT | C23: =Воронка!$C$21-Воронка!$C$22 -> 0 | D23: =Воронка!$D$21-Воронка!$D$22 -> 0 | E23: =Воронка!$E$21-Воронка!$E$22 -> 0 | F23: Без найма людей эти заказы не выполнить
B24: Заказов уходит партнёрам в месяц | C24: =Воронка!$C$18*Воронка!$C$20 -> 0.4725 | D24: =Воронка!$D$18*Воронка!$D$20 -> 1.89 | E24: =Воронка!$E$18*Воронка!$E$20 -> 7.0875
B25: Выручка заказов в KMT, сум/мес (без НДС) | C25: =Воронка!$C$22*'Юнит-экономика'!$C$8 -> 206550 | D25: =Воронка!$D$22*'Юнит-экономика'!$D$8 -> 826200 | E25: =Воронка!$E$22*'Юнит-экономика'!$E$8 -> 3098250
B26: Доход проекта (Bizzone), сум/мес в режиме | C26: =Воронка!$C$22*'Юнит-экономика'!$C$29+Воронка!$C$24*'Юнит-экономика'!$C$27 -> 67905 | D26: =Воронка!$D$22*'Юнит-экономика'!$D$29+Воронка!$D$24*'Юнит-экономика'!$D$27 -> 271620 | E26: =Воронка!$E$22*'Юнит-экономика'!$E$29+Воронка!$E$24*'Юнит-экономика'!$E$27 -> 1018575 | F26: Комиссии с заказов KMT и партнёров
B27: Прибыль KMT после комиссии, сум/мес в режиме | C27: =Воронка!$C$22*'Юнит-экономика'!$C$28*(1-N('Входные данные'!$E$44)) -> 40095 | D27: =Воронка!$D$22*'Юнит-экономика'!$D$28*(1-N('Входные данные'!$F$44)) -> 241380 | E27: =Воронка!$E$22*'Юнит-экономика'!$E$28*(1-N('Входные данные'!$G$44)) -> 1816425
B28: Доход владельца (KMT + проект), сум/мес в режиме | C28: =Воронка!$C$26+Воронка!$C$27 -> 108000 | D28: =Воронка!$D$26+Воронка!$D$27 -> 513000 | E28: =Воронка!$E$26+Воронка!$E$27 -> 2835000 | F28: Комиссия KMT → проект в сумме гасится

Sheet Сценарии_BEP
A1: Точка безубыточности и окупаемость этапа 1 (три сценария)
A2: Разработка и запуск (этап 1, 3 мес) считаются отдельно до запуска; после запуска — 12 месяцев работы. Два взгляда: владелец (KMT + проект) и проект (Bizzone) отдельно.
B4: Показатель | C4: Пессимист | D4: База | E4: Оптимист | F4: Комментарий
B5: 1. Операционные расходы в месяц (после запуска)
B6: Хостинг и сервисы | C6: =N('Входные данные'!$E$62) -> 1000000 | D6: =N('Входные данные'!$F$62) -> 1000000 | E6: =N('Входные данные'!$G$62) -> 1000000 | F6: [факт]
B7: SMS, колл-центр, прочее | C7: =N('Входные данные'!$E$63) -> 6500000 | D7: =N('Входные данные'!$F$63) -> 6500000 | E7: =N('Входные данные'!$G$63) -> 6500000 | F7: [факт] 1 + 5 + 0,5 млн
B8: Маркетинг (постоянный бюджет) | C8: =N('Входные данные'!$E$50) -> 0 | D8: =N('Входные данные'!$F$50) -> 0 | E8: =N('Входные данные'!$G$50) -> 0 | F8: [факт] постоянного бюджета нет
B9: Денежные операционные расходы | C9: =Сценарии_BEP!$C$6+Сценарии_BEP!$C$7+Сценарии_BEP!$C$8 -> 7500000 | D9: =Сценарии_BEP!$D$6+Сценарии_BEP!$D$7+Сценарии_BEP!$D$8 -> 7500000 | E9: =Сценарии_BEP!$E$6+Сценарии_BEP!$E$7+Сценарии_BEP!$E$8 -> 7500000
B10: Часов в месяц на 1 час «периода» | C10: =IF(N('Входные данные'!$E$65)=1,52/12,IF(N('Входные данные'!$E$65)=2,1,IF(AND(N('Входные данные'!$E$65)=3,N('Входные данные'!$E$66)>0),1/N('Входные данные'!$E$66),0))) -> 4.3333333 | D10: =IF(N('Входные данные'!$F$65)=1,52/12,IF(N('Входные данные'!$F$65)=2,1,IF(AND(N('Входные данные'!$F$65)=3,N('Входные данные'!$F$66)>0),1/N('Входные данные'!$F$66),0))) -> 4.3333333 | E10: =IF(N('Входные данные'!$G$65)=1,52/12,IF(N('Входные данные'!$G$65)=2,1,IF(AND(N('Входные данные'!$G$65)=3,N('Входные данные'!$G$66)>0),1/N('Входные данные'!$G$66),0))) -> 4.3333333 | F10: 0, пока не заданы единицы часов
B11: Часов в месяц: Темур | C11: =N('Входные данные'!$E$67)*Сценарии_BEP!$C$10 -> 86.666667 | D11: =N('Входные данные'!$F$67)*Сценарии_BEP!$D$10 -> 75.833333 | E11: =N('Входные данные'!$G$67)*Сценарии_BEP!$E$10 -> 65
B12: Часов в месяц: Равшан | C12: =N('Входные данные'!$E$68)*Сценарии_BEP!$C$10 -> 86.666667 | D12: =N('Входные данные'!$F$68)*Сценарии_BEP!$D$10 -> 75.833333 | E12: =N('Входные данные'!$G$68)*Сценарии_BEP!$E$10 -> 65
B13: Часов в месяц: Азиз | C13: =N('Входные данные'!$E$69)*Сценарии_BEP!$C$10 -> 216.66667 | D13: =N('Входные данные'!$F$69)*Сценарии_BEP!$D$10 -> 216.66667 | E13: =N('Входные данные'!$G$69)*Сценарии_BEP!$E$10 -> 216.66667
B14: Стоимость месяца работы (все часы): Темур | C14: =IF(N('Входные данные'!$E$70)=1,Сценарии_BEP!$C$11*N('Входные данные'!$E$72),IF(N('Входные данные'!$E$70)=2,IF(N('Входные данные'!$E$71)>0,Сценарии_BEP!$C$11/(N('Входные данные'!$E$71)*52/12)*N('Входные данные'!$E$72),0),N('Входные данные'!$E$72))) -> 10000000 | D14: =IF(N('Входные данные'!$F$70)=1,Сценарии_BEP!$D$11*N('Входные данные'!$F$72),IF(N('Входные данные'!$F$70)=2,IF(N('Входные данные'!$F$71)>0,Сценарии_BEP!$D$11/(N('Входные данные'!$F$71)*52/12)*N('Входные данные'!$F$72),0),N('Входные данные'!$F$72))) -> 8750000 | E14: =IF(N('Входные данные'!$G$70)=1,Сценарии_BEP!$E$11*N('Входные данные'!$G$72),IF(N('Входные данные'!$G$70)=2,IF(N('Входные данные'!$G$71)>0,Сценарии_BEP!$E$11/(N('Входные данные'!$G$71)*52/12)*N('Входные данные'!$G$72),0),N('Входные данные'!$G$72))) -> 7500000 | F14: Чтение ставки задаётся параметром rate_mode
B15: Стоимость месяца работы (все часы): Равшан | C15: =IF(N('Входные данные'!$E$70)=1,Сценарии_BEP!$C$12*N('Входные данные'!$E$73),IF(N('Входные данные'!$E$70)=2,IF(N('Входные данные'!$E$71)>0,Сценарии_BEP!$C$12/(N('Входные данные'!$E$71)*52/12)*N('Входные данные'!$E$73),0),N('Входные данные'!$E$73))) -> 10000000 | D15: =IF(N('Входные данные'!$F$70)=1,Сценарии_BEP!$D$12*N('Входные данные'!$F$73),IF(N('Входные данные'!$F$70)=2,IF(N('Входные данные'!$F$71)>0,Сценарии_BEP!$D$12/(N('Входные данные'!$F$71)*52/12)*N('Входные данные'!$F$73),0),N('Входные данные'!$F$73))) -> 8750000 | E15: =IF(N('Входные данные'!$G$70)=1,Сценарии_BEP!$E$12*N('Входные данные'!$G$73),IF(N('Входные данные'!$G$70)=2,IF(N('Входные данные'!$G$71)>0,Сценарии_BEP!$E$12/(N('Входные данные'!$G$71)*52/12)*N('Входные данные'!$G$73),0),N('Входные данные'!$G$73))) -> 7500000 | F15: Чтение ставки задаётся параметром rate_mode
B16: Стоимость месяца работы (все часы): Азиз | C16: =IF(N('Входные данные'!$E$70)=1,Сценарии_BEP!$C$13*N('Входные данные'!$E$74),IF(N('Входные данные'!$E$70)=2,IF(N('Входные данные'!$E$71)>0,Сценарии_BEP!$C$13/(N('Входные данные'!$E$71)*52/12)*N('Входные данные'!$E$74),0),N('Входные данные'!$E$74))) -> 6250000 | D16: =IF(N('Входные данные'!$F$70)=1,Сценарии_BEP!$D$13*N('Входные данные'!$F$74),IF(N('Входные данные'!$F$70)=2,IF(N('Входные данные'!$F$71)>0,Сценарии_BEP!$D$13/(N('Входные данные'!$F$71)*52/12)*N('Входные данные'!$F$74),0),N('Входные данные'!$F$74))) -> 6250000 | E16: =IF(N('Входные данные'!$G$70)=1,Сценарии_BEP!$E$13*N('Входные данные'!$G$74),IF(N('Входные данные'!$G$70)=2,IF(N('Входные данные'!$G$71)>0,Сценарии_BEP!$E$13/(N('Входные данные'!$G$71)*52/12)*N('Входные данные'!$G$74),0),N('Входные данные'!$G$74))) -> 6250000 | F16: Чтение ставки задаётся параметром rate_mode
B17: Труд, постоянная часть: Темур | C17: =Сценарии_BEP!$C$14*(1-N('Входные данные'!$E$75)) -> 0 | D17: =Сценарии_BEP!$D$14*(1-N('Входные данные'!$F$75)) -> 0 | E17: =Сценарии_BEP!$E$14*(1-N('Входные данные'!$G$75)) -> 0 | F17: стоимость месяца × (1 − доля разработки)
B18: Труд, постоянная часть: Равшан | C18: =Сценарии_BEP!$C$15*(1-N('Входные данные'!$E$76)) -> 0 | D18: =Сценарии_BEP!$D$15*(1-N('Входные данные'!$F$76)) -> 0 | E18: =Сценарии_BEP!$E$15*(1-N('Входные данные'!$G$76)) -> 0 | F18: стоимость месяца × (1 − доля разработки)
B19: Труд, постоянная часть: Азиз | C19: =Сценарии_BEP!$C$16*(1-N('Входные данные'!$E$77)) -> 1250000 | D19: =Сценарии_BEP!$D$16*(1-N('Входные данные'!$F$77)) -> 1250000 | E19: =Сценарии_BEP!$E$16*(1-N('Входные данные'!$G$77)) -> 1250000 | F19: стоимость месяца × (1 − доля разработки)
B20: Труд команды (постоянная часть), сум/мес | C20: =Сценарии_BEP!$C$17+Сценарии_BEP!$C$18+Сценарии_BEP!$C$19 -> 1250000 | D20: =Сценарии_BEP!$D$17+Сценарии_BEP!$D$18+Сценарии_BEP!$D$19 -> 1250000 | E20: =Сценарии_BEP!$E$17+Сценарии_BEP!$E$18+Сценарии_BEP!$E$19 -> 1250000 | F20: Условная стоимость времени, не денежный расход
B21: Полные операционные расходы, сум/мес | C21: =Сценарии_BEP!$C$9+Сценарии_BEP!$C$20 -> 8750000 | D21: =Сценарии_BEP!$D$9+Сценарии_BEP!$D$20 -> 8750000 | E21: =Сценарии_BEP!$E$9+Сценарии_BEP!$E$20 -> 8750000
B23: 2. Разработка и запуск (разово, до запуска, отдельно от операционных)
B24: Разработка и запуск: Темур | C24: =Сценарии_BEP!$C$14*N('Входные данные'!$E$75)*N('Входные данные'!$E$66) -> 30000000 | D24: =Сценарии_BEP!$D$14*N('Входные данные'!$F$75)*N('Входные данные'!$F$66) -> 26250000 | E24: =Сценарии_BEP!$E$14*N('Входные данные'!$G$75)*N('Входные данные'!$G$66) -> 22500000 | F24: стоимость месяца × доля разработки × месяцев этапа
B25: Разработка и запуск: Равшан | C25: =Сценарии_BEP!$C$15*N('Входные данные'!$E$76)*N('Входные данные'!$E$66) -> 30000000 | D25: =Сценарии_BEP!$D$15*N('Входные данные'!$F$76)*N('Входные данные'!$F$66) -> 26250000 | E25: =Сценарии_BEP!$E$15*N('Входные данные'!$G$76)*N('Входные данные'!$G$66) -> 22500000 | F25: стоимость месяца × доля разработки × месяцев этапа
B26: Разработка и запуск: Азиз | C26: =Сценарии_BEP!$C$16*N('Входные данные'!$E$77)*N('Входные данные'!$E$66) -> 15000000 | D26: =Сценарии_BEP!$D$16*N('Входные данные'!$F$77)*N('Входные данные'!$F$66) -> 15000000 | E26: =Сценарии_BEP!$E$16*N('Входные данные'!$G$77)*N('Входные данные'!$G$66) -> 15000000 | F26: стоимость месяца × доля разработки × месяцев этапа
B27: Разработка: труд команды | C27: =Сценарии_BEP!$C$24+Сценарии_BEP!$C$25+Сценарии_BEP!$C$26 -> 75000000 | D27: =Сценарии_BEP!$D$24+Сценарии_BEP!$D$25+Сценарии_BEP!$D$26 -> 67500000 | E27: =Сценарии_BEP!$E$24+Сценарии_BEP!$E$25+Сценарии_BEP!$E$26 -> 60000000
B28: Разовые внешние расходы (включая пробную рекламу) | C28: =N('Входные данные'!$E$79)+N('Входные данные'!$E$80)+N('Входные данные'!$E$81)+N('Входные данные'!$E$82)+N('Входные данные'!$E$83) -> 4500000 | D28: =N('Входные данные'!$F$79)+N('Входные данные'!$F$80)+N('Входные данные'!$F$81)+N('Входные данные'!$F$82)+N('Входные данные'!$F$83) -> 4500000 | E28: =N('Входные данные'!$G$79)+N('Входные данные'!$G$80)+N('Входные данные'!$G$81)+N('Входные данные'!$G$82)+N('Входные данные'!$G$83) -> 4500000 | F28: [факт] 0,5 + 3 + 1 млн
B29: Разработка и запуск, итого | C29: =Сценарии_BEP!$C$27+Сценарии_BEP!$C$28 -> 79500000 | D29: =Сценарии_BEP!$D$27+Сценарии_BEP!$D$28 -> 72000000 | E29: =Сценарии_BEP!$E$27+Сценарии_BEP!$E$28 -> 64500000
B30: Из них денежные расходы (без условной стоимости труда) | C30: =Сценарии_BEP!$C$28 -> 4500000 | D30: =Сценарии_BEP!$D$28 -> 4500000 | E30: =Сценарии_BEP!$E$28 -> 4500000
B32: 3. Точка безубыточности в режиме (на выбранном варианте I1; без учёта мощности KMT)
B33: Доход владельца на заказ с сайта | C33: ='Юнит-экономика'!$C$34 -> 160000 | D33: ='Юнит-экономика'!$D$34 -> 190000 | E33: ='Юнит-экономика'!$E$34 -> 280000
B34: Доход проекта на заказ с сайта | C34: ='Юнит-экономика'!$C$35 -> 100600 | D34: ='Юнит-экономика'!$D$35 -> 100600 | E34: ='Юнит-экономика'!$E$35 -> 100600 | F34: Только комиссия
B35: Сквозная конверсия расчёт → заказ (с учётом D10) | C35: =Воронка!$C$13*Воронка!$C$17 -> 0.00675 | D35: =Воронка!$D$13*Воронка!$D$17 -> 0.009 | E35: =Воронка!$E$13*Воронка!$E$17 -> 0.01125
B36: БУ владельца, денежная: заказов с сайта в месяц | C36: =IF(Сценарии_BEP!$C$33>0,Сценарии_BEP!$C$9/Сценарии_BEP!$C$33,"нет БУ") -> 46.875 | D36: =IF(Сценарии_BEP!$D$33>0,Сценарии_BEP!$D$9/Сценарии_BEP!$D$33,"нет БУ") -> 39.473684 | E36: =IF(Сценарии_BEP!$E$33>0,Сценарии_BEP!$E$9/Сценарии_BEP!$E$33,"нет БУ") -> 26.785714
B37: БУ владельца, полная: заказов с сайта в месяц | C37: =IF(Сценарии_BEP!$C$33>0,Сценарии_BEP!$C$21/Сценарии_BEP!$C$33,"нет БУ") -> 54.6875 | D37: =IF(Сценарии_BEP!$D$33>0,Сценарии_BEP!$D$21/Сценарии_BEP!$D$33,"нет БУ") -> 46.052632 | E37: =IF(Сценарии_BEP!$E$33>0,Сценарии_BEP!$E$21/Сценарии_BEP!$E$33,"нет БУ") -> 31.25
B38: БУ владельца, денежная: расчётов уровня 1 в месяц | C38: =IF(AND(ISNUMBER(Сценарии_BEP!$C$36),Сценарии_BEP!$C$35>0),Сценарии_BEP!$C$36/Сценарии_BEP!$C$35,"нет БУ") -> 6944.4444 | D38: =IF(AND(ISNUMBER(Сценарии_BEP!$D$36),Сценарии_BEP!$D$35>0),Сценарии_BEP!$D$36/Сценарии_BEP!$D$35,"нет БУ") -> 4385.9649 | E38: =IF(AND(ISNUMBER(Сценарии_BEP!$E$36),Сценарии_BEP!$E$35>0),Сценарии_BEP!$E$36/Сценарии_BEP!$E$35,"нет БУ") -> 2380.9524
B39: БУ владельца, полная: расчётов уровня 1 в месяц | C39: =IF(AND(ISNUMBER(Сценарии_BEP!$C$37),Сценарии_BEP!$C$35>0),Сценарии_BEP!$C$37/Сценарии_BEP!$C$35,"нет БУ") -> 8101.8519 | D39: =IF(AND(ISNUMBER(Сценарии_BEP!$D$37),Сценарии_BEP!$D$35>0),Сценарии_BEP!$D$37/Сценарии_BEP!$D$35,"нет БУ") -> 5116.9591 | E39: =IF(AND(ISNUMBER(Сценарии_BEP!$E$37),Сценарии_BEP!$E$35>0),Сценарии_BEP!$E$37/Сценарии_BEP!$E$35,"нет БУ") -> 2777.7778
B40: БУ проекта, полная: заказов с сайта в месяц | C40: =IF(Сценарии_BEP!$C$34>0,Сценарии_BEP!$C$21/Сценарии_BEP!$C$34,"нет БУ") -> 86.978131 | D40: =IF(Сценарии_BEP!$D$34>0,Сценарии_BEP!$D$21/Сценарии_BEP!$D$34,"нет БУ") -> 86.978131 | E40: =IF(Сценарии_BEP!$E$34>0,Сценарии_BEP!$E$21/Сценарии_BEP!$E$34,"нет БУ") -> 86.978131
B41: БУ проекта, полная: расчётов уровня 1 в месяц | C41: =IF(AND(ISNUMBER(Сценарии_BEP!$C$40),Сценарии_BEP!$C$35>0),Сценарии_BEP!$C$40/Сценарии_BEP!$C$35,"нет БУ") -> 12885.649 | D41: =IF(AND(ISNUMBER(Сценарии_BEP!$D$40),Сценарии_BEP!$D$35>0),Сценарии_BEP!$D$40/Сценарии_BEP!$D$35,"нет БУ") -> 9664.2368 | E41: =IF(AND(ISNUMBER(Сценарии_BEP!$E$40),Сценарии_BEP!$E$35>0),Сценарии_BEP!$E$40/Сценарии_BEP!$E$35,"нет БУ") -> 7731.3894
B42: Хватит ли мощности KMT на заказы при полной БУ владельца | C42: =IF(ISNUMBER(Сценарии_BEP!$C$37),IF(Сценарии_BEP!$C$37*(1-Воронка!$C$20)<=Воронка!$C$19,"хватает","НЕ хватает: упрёмся в мощность KMT"),"н/д") -> НЕ хватает: упрёмся в мощность KMT | D42: =IF(ISNUMBER(Сценарии_BEP!$D$37),IF(Сценарии_BEP!$D$37*(1-Воронка!$D$20)<=Воронка!$D$19,"хватает","НЕ хватает: упрёмся в мощность KMT"),"н/д") -> НЕ хватает: упрёмся в мощность KMT | E42: =IF(ISNUMBER(Сценарии_BEP!$E$37),IF(Сценарии_BEP!$E$37*(1-Воронка!$E$20)<=Воронка!$E$19,"хватает","НЕ хватает: упрёмся в мощность KMT"),"н/д") -> хватает | F42: Нужно заказов в KMT при БУ против запаса мощности (вопрос 17)
B43: Объём сценария / БУ владельца полная (расчёты), раз | C43: =IF(ISNUMBER(Сценарии_BEP!$C$39),Воронка!$C$6/Сценарии_BEP!$C$39,"н/д") -> 0.012342857 | D43: =IF(ISNUMBER(Сценарии_BEP!$D$39),Воронка!$D$6/Сценарии_BEP!$D$39,"н/д") -> 0.058628571 | E43: =IF(ISNUMBER(Сценарии_BEP!$E$39),Воронка!$E$6/Сценарии_BEP!$E$39,"н/д") -> 0.324 | F43: Меньше 1 — сценарий не покрывает расходы
B44: Результат владельца в режиме до труда (доход − денежные), сум/мес | C44: =Воронка!$C$28-Сценарии_BEP!$C$9 -> -7392000 | D44: =Воронка!$D$28-Сценарии_BEP!$D$9 -> -6987000 | E44: =Воронка!$E$28-Сценарии_BEP!$E$9 -> -4665000
B45: Результат владельца в режиме с трудом, сум/мес | C45: =Воронка!$C$28-Сценарии_BEP!$C$21 -> -8642000 | D45: =Воронка!$D$28-Сценарии_BEP!$D$21 -> -8237000 | E45: =Воронка!$E$28-Сценарии_BEP!$E$21 -> -5915000 | F45: С учётом мощности KMT и партнёров
B46: Результат проекта (Bizzone) в режиме с трудом, сум/мес | C46: =Воронка!$C$26-Сценарии_BEP!$C$21 -> -8682095 | D46: =Воронка!$D$26-Сценарии_BEP!$D$21 -> -8478380 | E46: =Воронка!$E$26-Сценарии_BEP!$E$21 -> -7731425 | F46: Проект несёт все расходы, получает только комиссию
B47: Простая окупаемость разработки владельцем, мес | C47: =IF(Сценарии_BEP!$C$29<=0,"нет данных о затратах на разработку",IF(Сценарии_BEP!$C$45>0,Сценарии_BEP!$C$29/Сценарии_BEP!$C$45,"не окупается")) -> не окупается | D47: =IF(Сценарии_BEP!$D$29<=0,"нет данных о затратах на разработку",IF(Сценарии_BEP!$D$45>0,Сценарии_BEP!$D$29/Сценарии_BEP!$D$45,"не окупается")) -> не окупается | E47: =IF(Сценарии_BEP!$E$29<=0,"нет данных о затратах на разработку",IF(Сценарии_BEP!$E$45>0,Сценарии_BEP!$E$29/Сценарии_BEP!$E$45,"не окупается")) -> не окупается | F47: Разработка ÷ месячный результат в режиме
B48: Простая окупаемость разработки проектом, мес | C48: =IF(Сценарии_BEP!$C$29<=0,"нет данных о затратах на разработку",IF(Сценарии_BEP!$C$46>0,Сценарии_BEP!$C$29/Сценарии_BEP!$C$46,"не окупается")) -> не окупается | D48: =IF(Сценарии_BEP!$D$29<=0,"нет данных о затратах на разработку",IF(Сценарии_BEP!$D$46>0,Сценарии_BEP!$D$29/Сценарии_BEP!$D$46,"не окупается")) -> не окупается | E48: =IF(Сценарии_BEP!$E$29<=0,"нет данных о затратах на разработку",IF(Сценарии_BEP!$E$46>0,Сценарии_BEP!$E$29/Сценарии_BEP!$E$46,"не окупается")) -> не окупается
B49: Приемлемый срок окупаемости владельца (параметр), мес | C49: =N('Входные данные'!$E$53) -> 3 | D49: =N('Входные данные'!$F$53) -> 3 | E49: =N('Входные данные'!$G$53) -> 3 | F49: [факт] 3 месяца
B50: Окупается ли в приемлемый срок (владелец, простая окупаемость) | C50: =IF(ISNUMBER(Сценарии_BEP!$C$47),IF(Сценарии_BEP!$C$47<=Сценарии_BEP!$C$49,"да","нет"),"нет") -> нет | D50: =IF(ISNUMBER(Сценарии_BEP!$D$47),IF(Сценарии_BEP!$D$47<=Сценарии_BEP!$D$49,"да","нет"),"нет") -> нет | E50: =IF(ISNUMBER(Сценарии_BEP!$E$47),IF(Сценарии_BEP!$E$47<=Сценарии_BEP!$E$49,"да","нет"),"нет") -> нет | F50: Сравнение с порогом владельца
B52: 4. Итоги 12 месяцев после запуска (с выходом на режим и подключением партнёров)
B53: Заказов с сайта за 12 мес | C53: =P76 -> 7.7625 | D53: =P102 -> 31.05 | E53: =P128 -> 116.4375
B54: из них берёт KMT | C54: =P78 -> 6.345 | D54: =P104 -> 19.71 | E54: =P130 -> 52.4
B55: из них уходит партнёрам | C55: =P80 -> 1.4175 | D55: =P106 -> 11.34 | E55: =P132 -> 63.7875
B56: теряется из-за мощности KMT | C56: =P79 -> 0 | D56: =P105 -> 0 | E56: =P131 -> 0.25
B57: Доход проекта за 12 мес (комиссии) | C57: =P82 -> 788940 | D57: =P108 -> 3144420 | E57: =P134 -> 11723550
B58: Доход владельца за 12 мес (KMT + проект) | C58: =P84 -> 2045250 | D58: =P110 -> 9018000 | E58: =P136 -> 43058750
B59: Операционные расходы за 12 мес (полные) | C59: =P85 -> 105000000 | D59: =P111 -> 105000000 | E59: =P137 -> 105000000
B60: Операционный результат владельца за 12 мес | C60: =P86 -> -102954750 | D60: =P112 -> -95982000 | E60: =P138 -> -61941250
B61: Операционный результат проекта за 12 мес | C61: =P87 -> -104211060 | D61: =P113 -> -101855580 | E61: =P139 -> -93276450
B62: Итог владельца за 12 мес с разработкой | C62: =O91 -> -182454750 | D62: =O117 -> -167982000 | E62: =O143 -> -126441250
B63: Итог проекта за 12 мес с разработкой | C63: =O92 -> -183711060 | D63: =O118 -> -173855580 | E63: =O144 -> -157776450
B64: Месяц окупаемости операций (владелец) | C64: =IF(COUNT(D93:O93)=0,"не окупается за 12 мес",MIN(D93:O93)) -> не окупается за 12 мес | D64: =IF(COUNT(D119:O119)=0,"не окупается за 12 мес",MIN(D119:O119)) -> не окупается за 12 мес | E64: =IF(COUNT(D145:O145)=0,"не окупается за 12 мес",MIN(D145:O145)) -> не окупается за 12 мес
B65: Месяц окупаемости с разработкой (владелец) | C65: =IF(COUNT(D94:O94)=0,"не окупается за 12 мес",MIN(D94:O94)) -> не окупается за 12 мес | D65: =IF(COUNT(D120:O120)=0,"не окупается за 12 мес",MIN(D120:O120)) -> не окупается за 12 мес | E65: =IF(COUNT(D146:O146)=0,"не окупается за 12 мес",MIN(D146:O146)) -> не окупается за 12 мес
B66: Месяц окупаемости с разработкой (проект) | C66: =IF(COUNT(D95:O95)=0,"не окупается за 12 мес",MIN(D95:O95)) -> не окупается за 12 мес | D66: =IF(COUNT(D121:O121)=0,"не окупается за 12 мес",MIN(D121:O121)) -> не окупается за 12 мес | E66: =IF(COUNT(D147:O147)=0,"не окупается за 12 мес",MIN(D147:O147)) -> не окупается за 12 мес
B67: Уложился ли владелец в приемлемый срок окупаемости | C67: =IF(ISNUMBER(C65),IF(C65<=N('Входные данные'!$E$53),"да","нет"),"нет") -> нет | D67: =IF(ISNUMBER(D65),IF(D65<=N('Входные данные'!$F$53),"да","нет"),"нет") -> нет | E67: =IF(ISNUMBER(E65),IF(E65<=N('Входные данные'!$G$53),"да","нет"),"нет") -> нет
B68: Окупаемость — по накопленному результату. Если результат в режиме отрицателен, окупаемости нет при любом сроке. Заказы сверх запаса мощности KMT считаются потерянными (найм не моделируется).
B72: Помесячно: Пессимист
B73: Месяц (0 = разработка) | C73: 0 | D73: 1 | E73: 2 | F73: 3 | G73: 4 | H73: 5 | I73: 6 | J73: 7 | K73: 8 | L73: 9 | M73: 10 | N73: 11 | O73: 12 | P73: Итого
B74: Коэффициент выхода на режим | D74: =IF(N('Входные данные'!$E$60)<=0,1,MIN(1,D73/N('Входные данные'!$E$60))) -> 0.5 | E74: =IF(N('Входные данные'!$E$60)<=0,1,MIN(1,E73/N('Входные данные'!$E$60))) -> 1 | F74: =IF(N('Входные данные'!$E$60)<=0,1,MIN(1,F73/N('Входные данные'!$E$60))) -> 1 | G74: =IF(N('Входные данные'!$E$60)<=0,1,MIN(1,G73/N('Входные данные'!$E$60))) -> 1 | H74: =IF(N('Входные данные'!$E$60)<=0,1,MIN(1,H73/N('Входные данные'!$E$60))) -> 1 | I74: =IF(N('Входные данные'!$E$60)<=0,1,MIN(1,I73/N('Входные данные'!$E$60))) -> 1 | J74: =IF(N('Входные данные'!$E$60)<=0,1,MIN(1,J73/N('Входные данные'!$E$60))) -> 1 | K74: =IF(N('Входные данные'!$E$60)<=0,1,MIN(1,K73/N('Входные данные'!$E$60))) -> 1 | ... O74: =IF(N('Входные данные'!$E$60)<=0,1,MIN(1,O73/N('Входные данные'!$E$60))) -> 1
B75: Расчётов уровня 1 | D75: =Воронка!$C$6*D74 -> 50 | E75: =Воронка!$C$6*E74 -> 100 | F75: =Воронка!$C$6*F74 -> 100 | G75: =Воронка!$C$6*G74 -> 100 | H75: =Воронка!$C$6*H74 -> 100 | I75: =Воронка!$C$6*I74 -> 100 | J75: =Воронка!$C$6*J74 -> 100 | K75: =Воронка!$C$6*K74 -> 100 | ... O75: =Воронка!$C$6*O74 -> 100 | P75: =SUM(D75:O75) -> 1150
B76: Заказов с сайта | D76: =D75*Воронка!$C$13*Воронка!$C$17 -> 0.3375 | E76: =E75*Воронка!$C$13*Воронка!$C$17 -> 0.675 | F76: =F75*Воронка!$C$13*Воронка!$C$17 -> 0.675 | G76: =G75*Воронка!$C$13*Воронка!$C$17 -> 0.675 | H76: =H75*Воронка!$C$13*Воронка!$C$17 -> 0.675 | I76: =I75*Воронка!$C$13*Воронка!$C$17 -> 0.675 | J76: =J75*Воронка!$C$13*Воронка!$C$17 -> 0.675 | K76: =K75*Воронка!$C$13*Воронка!$C$17 -> 0.675 | ... O76: =O75*Воронка!$C$13*Воронка!$C$17 -> 0.675 | P76: =SUM(D76:O76) -> 7.7625
B77: Доля заказов партнёрам | D77: =IF(AND(N('Входные данные'!$E$37)=2,D73>N('Входные данные'!$E$42)),N('Входные данные'!$E$41),0) -> 0 | E77: =IF(AND(N('Входные данные'!$E$37)=2,E73>N('Входные данные'!$E$42)),N('Входные данные'!$E$41),0) -> 0 | F77: =IF(AND(N('Входные данные'!$E$37)=2,F73>N('Входные данные'!$E$42)),N('Входные данные'!$E$41),0) -> 0 | G77: =IF(AND(N('Входные данные'!$E$37)=2,G73>N('Входные данные'!$E$42)),N('Входные данные'!$E$41),0) -> 0 | H77: =IF(AND(N('Входные данные'!$E$37)=2,H73>N('Входные данные'!$E$42)),N('Входные данные'!$E$41),0) -> 0 | I77: =IF(AND(N('Входные данные'!$E$37)=2,I73>N('Входные данные'!$E$42)),N('Входные данные'!$E$41),0) -> 0 | J77: =IF(AND(N('Входные данные'!$E$37)=2,J73>N('Входные данные'!$E$42)),N('Входные данные'!$E$41),0) -> 0 | K77: =IF(AND(N('Входные данные'!$E$37)=2,K73>N('Входные данные'!$E$42)),N('Входные данные'!$E$41),0) -> 0 | ... O77: =IF(AND(N('Входные данные'!$E$37)=2,O73>N('Входные данные'!$E$42)),N('Входные данные'!$E$41),0) -> 0.7
B78: Заказов берёт KMT (в пределах мощности) | D78: =MIN(D76*(1-D77),Воронка!$C$19) -> 0.3375 | E78: =MIN(E76*(1-E77),Воронка!$C$19) -> 0.675 | F78: =MIN(F76*(1-F77),Воронка!$C$19) -> 0.675 | G78: =MIN(G76*(1-G77),Воронка!$C$19) -> 0.675 | H78: =MIN(H76*(1-H77),Воронка!$C$19) -> 0.675 | I78: =MIN(I76*(1-I77),Воронка!$C$19) -> 0.675 | J78: =MIN(J76*(1-J77),Воронка!$C$19) -> 0.675 | K78: =MIN(K76*(1-K77),Воронка!$C$19) -> 0.675 | ... O78: =MIN(O76*(1-O77),Воронка!$C$19) -> 0.2025 | P78: =SUM(D78:O78) -> 6.345
B79: Заказов теряется из-за мощности | D79: =D76*(1-D77)-D78 -> 0 | E79: =E76*(1-E77)-E78 -> 0 | F79: =F76*(1-F77)-F78 -> 0 | G79: =G76*(1-G77)-G78 -> 0 | H79: =H76*(1-H77)-H78 -> 0 | I79: =I76*(1-I77)-I78 -> 0 | J79: =J76*(1-J77)-J78 -> 0 | K79: =K76*(1-K77)-K78 -> 0 | ... O79: =O76*(1-O77)-O78 -> 0 | P79: =SUM(D79:O79) -> 0
B80: Заказов у партнёров | D80: =D76*D77 -> 0 | E80: =E76*E77 -> 0 | F80: =F76*F77 -> 0 | G80: =G76*G77 -> 0 | H80: =H76*H77 -> 0 | I80: =I76*I77 -> 0 | J80: =J76*J77 -> 0 | K80: =K76*K77 -> 0 | ... O80: =O76*O77 -> 0.4725 | P80: =SUM(D80:O80) -> 1.4175
B81: Выручка заказов в KMT (без НДС) | D81: =D78*'Юнит-экономика'!$C$8 -> 344250 | E81: =E78*'Юнит-экономика'!$C$8 -> 688500 | F81: =F78*'Юнит-экономика'!$C$8 -> 688500 | G81: =G78*'Юнит-экономика'!$C$8 -> 688500 | H81: =H78*'Юнит-экономика'!$C$8 -> 688500 | I81: =I78*'Юнит-экономика'!$C$8 -> 688500 | J81: =J78*'Юнит-экономика'!$C$8 -> 688500 | K81: =K78*'Юнит-экономика'!$C$8 -> 688500 | ... O81: =O78*'Юнит-экономика'!$C$8 -> 206550 | P81: =SUM(D81:O81) -> 6471900
B82: Доход проекта (комиссии) | D82: =D78*'Юнит-экономика'!$C$29+D80*'Юнит-экономика'!$C$27 -> 34425 | E82: =E78*'Юнит-экономика'!$C$29+E80*'Юнит-экономика'!$C$27 -> 68850 | F82: =F78*'Юнит-экономика'!$C$29+F80*'Юнит-экономика'!$C$27 -> 68850 | G82: =G78*'Юнит-экономика'!$C$29+G80*'Юнит-экономика'!$C$27 -> 68850 | H82: =H78*'Юнит-экономика'!$C$29+H80*'Юнит-экономика'!$C$27 -> 68850 | I82: =I78*'Юнит-экономика'!$C$29+I80*'Юнит-экономика'!$C$27 -> 68850 | J82: =J78*'Юнит-экономика'!$C$29+J80*'Юнит-экономика'!$C$27 -> 68850 | K82: =K78*'Юнит-экономика'!$C$29+K80*'Юнит-экономика'!$C$27 -> 68850 | ... O82: =O78*'Юнит-экономика'!$C$29+O80*'Юнит-экономика'!$C$27 -> 67905 | P82: =SUM(D82:O82) -> 788940
B83: Прибыль KMT после комиссии | D83: =D78*'Юнит-экономика'!$C$28*(1-N('Входные данные'!$E$44)) -> 66825 | E83: =E78*'Юнит-экономика'!$C$28*(1-N('Входные данные'!$E$44)) -> 133650 | F83: =F78*'Юнит-экономика'!$C$28*(1-N('Входные данные'!$E$44)) -> 133650 | G83: =G78*'Юнит-экономика'!$C$28*(1-N('Входные данные'!$E$44)) -> 133650 | H83: =H78*'Юнит-экономика'!$C$28*(1-N('Входные данные'!$E$44)) -> 133650 | I83: =I78*'Юнит-экономика'!$C$28*(1-N('Входные данные'!$E$44)) -> 133650 | J83: =J78*'Юнит-экономика'!$C$28*(1-N('Входные данные'!$E$44)) -> 133650 | K83: =K78*'Юнит-экономика'!$C$28*(1-N('Входные данные'!$E$44)) -> 133650 | ... O83: =O78*'Юнит-экономика'!$C$28*(1-N('Входные данные'!$E$44)) -> 40095 | P83: =SUM(D83:O83) -> 1256310
B84: Доход владельца (KMT + проект) | D84: =D82+D83 -> 101250 | E84: =E82+E83 -> 202500 | F84: =F82+F83 -> 202500 | G84: =G82+G83 -> 202500 | H84: =H82+H83 -> 202500 | I84: =I82+I83 -> 202500 | J84: =J82+J83 -> 202500 | K84: =K82+K83 -> 202500 | ... O84: =O82+O83 -> 108000 | P84: =SUM(D84:O84) -> 2045250
B85: Операционные расходы (полные) | D85: =Сценарии_BEP!$C$21 -> 8750000 | E85: =Сценарии_BEP!$C$21 -> 8750000 | F85: =Сценарии_BEP!$C$21 -> 8750000 | G85: =Сценарии_BEP!$C$21 -> 8750000 | H85: =Сценарии_BEP!$C$21 -> 8750000 | I85: =Сценарии_BEP!$C$21 -> 8750000 | J85: =Сценарии_BEP!$C$21 -> 8750000 | K85: =Сценарии_BEP!$C$21 -> 8750000 | ... O85: =Сценарии_BEP!$C$21 -> 8750000 | P85: =SUM(D85:O85) -> 105000000
B86: Операционный результат владельца | D86: =D84-D85 -> -8648750 | E86: =E84-E85 -> -8547500 | F86: =F84-F85 -> -8547500 | G86: =G84-G85 -> -8547500 | H86: =H84-H85 -> -8547500 | I86: =I84-I85 -> -8547500 | J86: =J84-J85 -> -8547500 | K86: =K84-K85 -> -8547500 | ... O86: =O84-O85 -> -8642000 | P86: =SUM(D86:O86) -> -102954750
B87: Операционный результат проекта | D87: =D82-D85 -> -8715575 | E87: =E82-E85 -> -8681150 | F87: =F82-F85 -> -8681150 | G87: =G82-G85 -> -8681150 | H87: =H82-H85 -> -8681150 | I87: =I82-I85 -> -8681150 | J87: =J82-J85 -> -8681150 | K87: =K82-K85 -> -8681150 | ... O87: =O82-O85 -> -8682095 | P87: =SUM(D87:O87) -> -104211060
B88: Накопленный операционный: владелец | C88: 0 | D88: =C88+D86 -> -8648750 | E88: =D88+E86 -> -17196250 | F88: =E88+F86 -> -25743750 | G88: =F88+G86 -> -34291250 | H88: =G88+H86 -> -42838750 | I88: =H88+I86 -> -51386250 | J88: =I88+J86 -> -59933750 | K88: =J88+K86 -> -68481250 | ... O88: =N88+O86 -> -102954750
B89: Накопленный операционный: проект | C89: 0 | D89: =C89+D87 -> -8715575 | E89: =D89+E87 -> -17396725 | F89: =E89+F87 -> -26077875 | G89: =F89+G87 -> -34759025 | H89: =G89+H87 -> -43440175 | I89: =H89+I87 -> -52121325 | J89: =I89+J87 -> -60802475 | K89: =J89+K87 -> -69483625 | ... O89: =N89+O87 -> -104211060
B90: Разработка и запуск (разово) | C90: =-Сценарии_BEP!$C$29 -> -79500000 | D90: 0 | E90: 0 | F90: 0 | G90: 0 | H90: 0 | I90: 0 | J90: 0 | K90: 0 | L90: 0 | M90: 0 | N90: 0 | O90: 0 | P90: =C90 -> -79500000
B91: Накопленный итог с разработкой: владелец | C91: =C90 -> -79500000 | D91: =C91+D86+D90 -> -88148750 | E91: =D91+E86+E90 -> -96696250 | F91: =E91+F86+F90 -> -105243750 | G91: =F91+G86+G90 -> -113791250 | H91: =G91+H86+H90 -> -122338750 | I91: =H91+I86+I90 -> -130886250 | J91: =I91+J86+J90 -> -139433750 | K91: =J91+K86+K90 -> -147981250 | ... O91: =N91+O86+O90 -> -182454750
B92: Накопленный итог с разработкой: проект | C92: =C90 -> -79500000 | D92: =C92+D87+D90 -> -88215575 | E92: =D92+E87+E90 -> -96896725 | F92: =E92+F87+F90 -> -105577875 | G92: =F92+G87+G90 -> -114259025 | H92: =G92+H87+H90 -> -122940175 | I92: =H92+I87+I90 -> -131621325 | J92: =I92+J87+J90 -> -140302475 | K92: =J92+K87+K90 -> -148983625 | ... O92: =N92+O87+O90 -> -183711060
B93: Флаг: операции окупились (владелец), месяц | D93: =IF(D88>=0,D73,"") | E93: =IF(E88>=0,E73,"") | F93: =IF(F88>=0,F73,"") | G93: =IF(G88>=0,G73,"") | H93: =IF(H88>=0,H73,"") | I93: =IF(I88>=0,I73,"") | J93: =IF(J88>=0,J73,"") | K93: =IF(K88>=0,K73,"") | ... O93: =IF(O88>=0,O73,"")
B94: Флаг: окупилось с разработкой (владелец), месяц | D94: =IF(D91>=0,D73,"") | E94: =IF(E91>=0,E73,"") | F94: =IF(F91>=0,F73,"") | G94: =IF(G91>=0,G73,"") | H94: =IF(H91>=0,H73,"") | I94: =IF(I91>=0,I73,"") | J94: =IF(J91>=0,J73,"") | K94: =IF(K91>=0,K73,"") | ... O94: =IF(O91>=0,O73,"")
B95: Флаг: окупилось с разработкой (проект), месяц | D95: =IF(D92>=0,D73,"") | E95: =IF(E92>=0,E73,"") | F95: =IF(F92>=0,F73,"") | G95: =IF(G92>=0,G73,"") | H95: =IF(H92>=0,H73,"") | I95: =IF(I92>=0,I73,"") | J95: =IF(J92>=0,J73,"") | K95: =IF(K92>=0,K73,"") | ... O95: =IF(O92>=0,O73,"")
B98: Помесячно: База
B99: Месяц (0 = разработка) | C99: 0 | D99: 1 | E99: 2 | F99: 3 | G99: 4 | H99: 5 | I99: 6 | J99: 7 | K99: 8 | L99: 9 | M99: 10 | N99: 11 | O99: 12 | P99: Итого
B100: Коэффициент выхода на режим | D100: =IF(N('Входные данные'!$F$60)<=0,1,MIN(1,D99/N('Входные данные'!$F$60))) -> 0.5 | E100: =IF(N('Входные данные'!$F$60)<=0,1,MIN(1,E99/N('Входные данные'!$F$60))) -> 1 | F100: =IF(N('Входные данные'!$F$60)<=0,1,MIN(1,F99/N('Входные данные'!$F$60))) -> 1 | G100: =IF(N('Входные данные'!$F$60)<=0,1,MIN(1,G99/N('Входные данные'!$F$60))) -> 1 | H100: =IF(N('Входные данные'!$F$60)<=0,1,MIN(1,H99/N('Входные данные'!$F$60))) -> 1 | I100: =IF(N('Входные данные'!$F$60)<=0,1,MIN(1,I99/N('Входные данные'!$F$60))) -> 1 | J100: =IF(N('Входные данные'!$F$60)<=0,1,MIN(1,J99/N('Входные данные'!$F$60))) -> 1 | K100: =IF(N('Входные данные'!$F$60)<=0,1,MIN(1,K99/N('Входные данные'!$F$60))) -> 1 | ... O100: =IF(N('Входные данные'!$F$60)<=0,1,MIN(1,O99/N('Входные данные'!$F$60))) -> 1
B101: Расчётов уровня 1 | D101: =Воронка!$D$6*D100 -> 150 | E101: =Воронка!$D$6*E100 -> 300 | F101: =Воронка!$D$6*F100 -> 300 | G101: =Воронка!$D$6*G100 -> 300 | H101: =Воронка!$D$6*H100 -> 300 | I101: =Воронка!$D$6*I100 -> 300 | J101: =Воронка!$D$6*J100 -> 300 | K101: =Воронка!$D$6*K100 -> 300 | ... O101: =Воронка!$D$6*O100 -> 300 | P101: =SUM(D101:O101) -> 3450
B102: Заказов с сайта | D102: =D101*Воронка!$D$13*Воронка!$D$17 -> 1.35 | E102: =E101*Воронка!$D$13*Воронка!$D$17 -> 2.7 | F102: =F101*Воронка!$D$13*Воронка!$D$17 -> 2.7 | G102: =G101*Воронка!$D$13*Воронка!$D$17 -> 2.7 | H102: =H101*Воронка!$D$13*Воронка!$D$17 -> 2.7 | I102: =I101*Воронка!$D$13*Воронка!$D$17 -> 2.7 | J102: =J101*Воронка!$D$13*Воронка!$D$17 -> 2.7 | K102: =K101*Воронка!$D$13*Воронка!$D$17 -> 2.7 | ... O102: =O101*Воронка!$D$13*Воронка!$D$17 -> 2.7 | P102: =SUM(D102:O102) -> 31.05
B103: Доля заказов партнёрам | D103: =IF(AND(N('Входные данные'!$F$37)=2,D99>N('Входные данные'!$F$42)),N('Входные данные'!$F$41),0) -> 0 | E103: =IF(AND(N('Входные данные'!$F$37)=2,E99>N('Входные данные'!$F$42)),N('Входные данные'!$F$41),0) -> 0 | F103: =IF(AND(N('Входные данные'!$F$37)=2,F99>N('Входные данные'!$F$42)),N('Входные данные'!$F$41),0) -> 0 | G103: =IF(AND(N('Входные данные'!$F$37)=2,G99>N('Входные данные'!$F$42)),N('Входные данные'!$F$41),0) -> 0 | H103: =IF(AND(N('Входные данные'!$F$37)=2,H99>N('Входные данные'!$F$42)),N('Входные данные'!$F$41),0) -> 0 | I103: =IF(AND(N('Входные данные'!$F$37)=2,I99>N('Входные данные'!$F$42)),N('Входные данные'!$F$41),0) -> 0 | J103: =IF(AND(N('Входные данные'!$F$37)=2,J99>N('Входные данные'!$F$42)),N('Входные данные'!$F$41),0) -> 0.7 | K103: =IF(AND(N('Входные данные'!$F$37)=2,K99>N('Входные данные'!$F$42)),N('Входные данные'!$F$41),0) -> 0.7 | ... O103: =IF(AND(N('Входные данные'!$F$37)=2,O99>N('Входные данные'!$F$42)),N('Входные данные'!$F$41),0) -> 0.7
B104: Заказов берёт KMT (в пределах мощности) | D104: =MIN(D102*(1-D103),Воронка!$D$19) -> 1.35 | E104: =MIN(E102*(1-E103),Воронка!$D$19) -> 2.7 | F104: =MIN(F102*(1-F103),Воронка!$D$19) -> 2.7 | G104: =MIN(G102*(1-G103),Воронка!$D$19) -> 2.7 | H104: =MIN(H102*(1-H103),Воронка!$D$19) -> 2.7 | I104: =MIN(I102*(1-I103),Воронка!$D$19) -> 2.7 | J104: =MIN(J102*(1-J103),Воронка!$D$19) -> 0.81 | K104: =MIN(K102*(1-K103),Воронка!$D$19) -> 0.81 | ... O104: =MIN(O102*(1-O103),Воронка!$D$19) -> 0.81 | P104: =SUM(D104:O104) -> 19.71
B105: Заказов теряется из-за мощности | D105: =D102*(1-D103)-D104 -> 0 | E105: =E102*(1-E103)-E104 -> 0 | F105: =F102*(1-F103)-F104 -> 0 | G105: =G102*(1-G103)-G104 -> 0 | H105: =H102*(1-H103)-H104 -> 0 | I105: =I102*(1-I103)-I104 -> 0 | J105: =J102*(1-J103)-J104 -> 0 | K105: =K102*(1-K103)-K104 -> 0 | ... O105: =O102*(1-O103)-O104 -> 0 | P105: =SUM(D105:O105) -> 0
B106: Заказов у партнёров | D106: =D102*D103 -> 0 | E106: =E102*E103 -> 0 | F106: =F102*F103 -> 0 | G106: =G102*G103 -> 0 | H106: =H102*H103 -> 0 | I106: =I102*I103 -> 0 | J106: =J102*J103 -> 1.89 | K106: =K102*K103 -> 1.89 | ... O106: =O102*O103 -> 1.89 | P106: =SUM(D106:O106) -> 11.34
B107: Выручка заказов в KMT (без НДС) | D107: =D104*'Юнит-экономика'!$D$8 -> 1377000 | E107: =E104*'Юнит-экономика'!$D$8 -> 2754000 | F107: =F104*'Юнит-экономика'!$D$8 -> 2754000 | G107: =G104*'Юнит-экономика'!$D$8 -> 2754000 | H107: =H104*'Юнит-экономика'!$D$8 -> 2754000 | I107: =I104*'Юнит-экономика'!$D$8 -> 2754000 | J107: =J104*'Юнит-экономика'!$D$8 -> 826200 | K107: =K104*'Юнит-экономика'!$D$8 -> 826200 | ... O107: =O104*'Юнит-экономика'!$D$8 -> 826200 | P107: =SUM(D107:O107) -> 20104200
B108: Доход проекта (комиссии) | D108: =D104*'Юнит-экономика'!$D$29+D106*'Юнит-экономика'!$D$27 -> 137700 | E108: =E104*'Юнит-экономика'!$D$29+E106*'Юнит-экономика'!$D$27 -> 275400 | F108: =F104*'Юнит-экономика'!$D$29+F106*'Юнит-экономика'!$D$27 -> 275400 | G108: =G104*'Юнит-экономика'!$D$29+G106*'Юнит-экономика'!$D$27 -> 275400 | H108: =H104*'Юнит-экономика'!$D$29+H106*'Юнит-экономика'!$D$27 -> 275400 | I108: =I104*'Юнит-экономика'!$D$29+I106*'Юнит-экономика'!$D$27 -> 275400 | J108: =J104*'Юнит-экономика'!$D$29+J106*'Юнит-экономика'!$D$27 -> 271620 | K108: =K104*'Юнит-экономика'!$D$29+K106*'Юнит-экономика'!$D$27 -> 271620 | ... O108: =O104*'Юнит-экономика'!$D$29+O106*'Юнит-экономика'!$D$27 -> 271620 | P108: =SUM(D108:O108) -> 3144420
B109: Прибыль KMT после комиссии | D109: =D104*'Юнит-экономика'!$D$28*(1-N('Входные данные'!$F$44)) -> 402300 | E109: =E104*'Юнит-экономика'!$D$28*(1-N('Входные данные'!$F$44)) -> 804600 | F109: =F104*'Юнит-экономика'!$D$28*(1-N('Входные данные'!$F$44)) -> 804600 | G109: =G104*'Юнит-экономика'!$D$28*(1-N('Входные данные'!$F$44)) -> 804600 | H109: =H104*'Юнит-экономика'!$D$28*(1-N('Входные данные'!$F$44)) -> 804600 | I109: =I104*'Юнит-экономика'!$D$28*(1-N('Входные данные'!$F$44)) -> 804600 | J109: =J104*'Юнит-экономика'!$D$28*(1-N('Входные данные'!$F$44)) -> 241380 | K109: =K104*'Юнит-экономика'!$D$28*(1-N('Входные данные'!$F$44)) -> 241380 | ... O109: =O104*'Юнит-экономика'!$D$28*(1-N('Входные данные'!$F$44)) -> 241380 | P109: =SUM(D109:O109) -> 5873580
...

Sheet D10_I1
A1: Влияние решений D10 и I1: по два варианта, четыре сочетания
A2: Режим (после выхода на режим и подключения партнёров, с ограничением мощности KMT). I1: A = только KMT, B = агрегатор (партнёры берут долю заказов). D10: б+ = блок KMT с контактами, а = нейтральный текст.
B4: Сценарий: Пессимист
B5: Показатель | C5: I1=A · D10=б+ | D5: I1=A · D10=а | E5: I1=B · D10=б+ | F5: I1=B · D10=а
B6: Множитель потока D10 | C6: 1 | D6: =N('Входные данные'!$E$47) -> 0.25 | E6: 1 | F6: =N('Входные данные'!$E$47) -> 0.25
B7: Заказов с сайта в месяц | C7: =Воронка!$C$12*C6 -> 0.675 | D7: =Воронка!$C$12*D6 -> 0.16875 | E7: =Воронка!$C$12*E6 -> 0.675 | F7: =Воронка!$C$12*F6 -> 0.16875
B8: Доля партнёров | C8: 0 | D8: 0 | E8: =N('Входные данные'!$E$41) -> 0.7 | F8: =N('Входные данные'!$E$41) -> 0.7
B9: Заказов берёт KMT (в пределах мощности) | C9: =MIN(C7*(1-C8),Воронка!$C$19) -> 0.675 | D9: =MIN(D7*(1-D8),Воронка!$C$19) -> 0.16875 | E9: =MIN(E7*(1-E8),Воронка!$C$19) -> 0.2025 | F9: =MIN(F7*(1-F8),Воронка!$C$19) -> 0.050625
B10: Заказов у партнёров | C10: =C7*C8 -> 0 | D10: =D7*D8 -> 0 | E10: =E7*E8 -> 0.4725 | F10: =F7*F8 -> 0.118125
B11: Доход владельца на заказ сайта (без мощности) | C11: =(1-C8)*'Юнит-экономика'!$C$23+C8*'Юнит-экономика'!$C$27 -> 300000 | D11: =(1-D8)*'Юнит-экономика'!$C$23+D8*'Юнит-экономика'!$C$27 -> 300000 | E11: =(1-E8)*'Юнит-экономика'!$C$23+E8*'Юнит-экономика'!$C$27 -> 160000 | F11: =(1-F8)*'Юнит-экономика'!$C$23+F8*'Юнит-экономика'!$C$27 -> 160000
B12: Доход владельца в месяц | C12: =C13+C9*'Юнит-экономика'!$C$28*(1-N('Входные данные'!$E$44)) -> 202500 | D12: =D13+D9*'Юнит-экономика'!$C$28*(1-N('Входные данные'!$E$44)) -> 50625 | E12: =E13+E9*'Юнит-экономика'!$C$28*(1-N('Входные данные'!$E$44)) -> 108000 | F12: =F13+F9*'Юнит-экономика'!$C$28*(1-N('Входные данные'!$E$44)) -> 27000
B13: Доход проекта в месяц (комиссии) | C13: =C9*'Юнит-экономика'!$C$29+C10*'Юнит-экономика'!$C$27 -> 68850 | D13: =D9*'Юнит-экономика'!$C$29+D10*'Юнит-экономика'!$C$27 -> 17212.5 | E13: =E9*'Юнит-экономика'!$C$29+E10*'Юнит-экономика'!$C$27 -> 67905 | F13: =F9*'Юнит-экономика'!$C$29+F10*'Юнит-экономика'!$C$27 -> 16976.25
B14: Полные операционные расходы в месяц | C14: =Сценарии_BEP!$C$21 -> 8750000 | D14: =Сценарии_BEP!$C$21 -> 8750000 | E14: =Сценарии_BEP!$C$21 -> 8750000 | F14: =Сценарии_BEP!$C$21 -> 8750000
B15: Результат владельца в месяц | C15: =C12-C14 -> -8547500 | D15: =D12-D14 -> -8699375 | E15: =E12-E14 -> -8642000 | F15: =F12-F14 -> -8723000
B16: Результат проекта в месяц | C16: =C13-C14 -> -8681150 | D16: =D13-D14 -> -8732787.5 | E16: =E13-E14 -> -8682095 | F16: =F13-F14 -> -8733023.8
B17: Разница результата владельца с (A, б+) | C17: =C15-$C15 -> 0 | D17: =D15-$C15 -> -151875 | E17: =E15-$C15 -> -94500 | F17: =F15-$C15 -> -175500
B18: БУ владельца: заказов с сайта в месяц | C18: =IF(C11>0,C14/C11,"нет БУ") -> 29.166667 | D18: =IF(D11>0,D14/D11,"нет БУ") -> 29.166667 | E18: =IF(E11>0,E14/E11,"нет БУ") -> 54.6875 | F18: =IF(F11>0,F14/F11,"нет БУ") -> 54.6875
B19: БУ владельца: расчётов уровня 1 в месяц | C19: =IF(AND(ISNUMBER(C18),Воронка!$C$13*C6>0),C18/(Воронка!$C$13*C6),"нет БУ") -> 4320.9877 | D19: =IF(AND(ISNUMBER(D18),Воронка!$C$13*D6>0),D18/(Воронка!$C$13*D6),"нет БУ") -> 17283.951 | E19: =IF(AND(ISNUMBER(E18),Воронка!$C$13*E6>0),E18/(Воронка!$C$13*E6),"нет БУ") -> 8101.8519 | F19: =IF(AND(ISNUMBER(F18),Воронка!$C$13*F6>0),F18/(Воронка!$C$13*F6),"нет БУ") -> 32407.407
B20: Простая окупаемость разработки владельцем, мес | C20: =IF(Сценарии_BEP!$C$29<=0,"нет данных о разработке",IF(C15>0,Сценарии_BEP!$C$29/C15,"не окупается")) -> не окупается | D20: =IF(Сценарии_BEP!$C$29<=0,"нет данных о разработке",IF(D15>0,Сценарии_BEP!$C$29/D15,"не окупается")) -> не окупается | E20: =IF(Сценарии_BEP!$C$29<=0,"нет данных о разработке",IF(E15>0,Сценарии_BEP!$C$29/E15,"не окупается")) -> не окупается | F20: =IF(Сценарии_BEP!$C$29<=0,"нет данных о разработке",IF(F15>0,Сценарии_BEP!$C$29/F15,"не окупается")) -> не окупается
B22: Сценарий: База
B23: Показатель | C23: I1=A · D10=б+ | D23: I1=A · D10=а | E23: I1=B · D10=б+ | F23: I1=B · D10=а
B24: Множитель потока D10 | C24: 1 | D24: =N('Входные данные'!$F$47) -> 0.25 | E24: 1 | F24: =N('Входные данные'!$F$47) -> 0.25
B25: Заказов с сайта в месяц | C25: =Воронка!$D$12*C24 -> 2.7 | D25: =Воронка!$D$12*D24 -> 0.675 | E25: =Воронка!$D$12*E24 -> 2.7 | F25: =Воронка!$D$12*F24 -> 0.675
B26: Доля партнёров | C26: 0 | D26: 0 | E26: =N('Входные данные'!$F$41) -> 0.7 | F26: =N('Входные данные'!$F$41) -> 0.7
B27: Заказов берёт KMT (в пределах мощности) | C27: =MIN(C25*(1-C26),Воронка!$D$19) -> 2.7 | D27: =MIN(D25*(1-D26),Воронка!$D$19) -> 0.675 | E27: =MIN(E25*(1-E26),Воронка!$D$19) -> 0.81 | F27: =MIN(F25*(1-F26),Воронка!$D$19) -> 0.2025
B28: Заказов у партнёров | C28: =C25*C26 -> 0 | D28: =D25*D26 -> 0 | E28: =E25*E26 -> 1.89 | F28: =F25*F26 -> 0.4725
B29: Доход владельца на заказ сайта (без мощности) | C29: =(1-C26)*'Юнит-экономика'!$D$23+C26*'Юнит-экономика'!$D$27 -> 400000 | D29: =(1-D26)*'Юнит-экономика'!$D$23+D26*'Юнит-экономика'!$D$27 -> 400000 | E29: =(1-E26)*'Юнит-экономика'!$D$23+E26*'Юнит-экономика'!$D$27 -> 190000 | F29: =(1-F26)*'Юнит-экономика'!$D$23+F26*'Юнит-экономика'!$D$27 -> 190000
B30: Доход владельца в месяц | C30: =C31+C27*'Юнит-экономика'!$D$28*(1-N('Входные данные'!$F$44)) -> 1080000 | D30: =D31+D27*'Юнит-экономика'!$D$28*(1-N('Входные данные'!$F$44)) -> 270000 | E30: =E31+E27*'Юнит-экономика'!$D$28*(1-N('Входные данные'!$F$44)) -> 513000 | F30: =F31+F27*'Юнит-экономика'!$D$28*(1-N('Входные данные'!$F$44)) -> 128250
B31: Доход проекта в месяц (комиссии) | C31: =C27*'Юнит-экономика'!$D$29+C28*'Юнит-экономика'!$D$27 -> 275400 | D31: =D27*'Юнит-экономика'!$D$29+D28*'Юнит-экономика'!$D$27 -> 68850 | E31: =E27*'Юнит-экономика'!$D$29+E28*'Юнит-экономика'!$D$27 -> 271620 | F31: =F27*'Юнит-экономика'!$D$29+F28*'Юнит-экономика'!$D$27 -> 67905
B32: Полные операционные расходы в месяц | C32: =Сценарии_BEP!$D$21 -> 8750000 | D32: =Сценарии_BEP!$D$21 -> 8750000 | E32: =Сценарии_BEP!$D$21 -> 8750000 | F32: =Сценарии_BEP!$D$21 -> 8750000
B33: Результат владельца в месяц | C33: =C30-C32 -> -7670000 | D33: =D30-D32 -> -8480000 | E33: =E30-E32 -> -8237000 | F33: =F30-F32 -> -8621750
B34: Результат проекта в месяц | C34: =C31-C32 -> -8474600 | D34: =D31-D32 -> -8681150 | E34: =E31-E32 -> -8478380 | F34: =F31-F32 -> -8682095
B35: Разница результата владельца с (A, б+) | C35: =C33-$C33 -> 0 | D35: =D33-$C33 -> -810000 | E35: =E33-$C33 -> -567000 | F35: =F33-$C33 -> -951750
B36: БУ владельца: заказов с сайта в месяц | C36: =IF(C29>0,C32/C29,"нет БУ") -> 21.875 | D36: =IF(D29>0,D32/D29,"нет БУ") -> 21.875 | E36: =IF(E29>0,E32/E29,"нет БУ") -> 46.052632 | F36: =IF(F29>0,F32/F29,"нет БУ") -> 46.052632
B37: БУ владельца: расчётов уровня 1 в месяц | C37: =IF(AND(ISNUMBER(C36),Воронка!$D$13*C24>0),C36/(Воронка!$D$13*C24),"нет БУ") -> 2430.5556 | D37: =IF(AND(ISNUMBER(D36),Воронка!$D$13*D24>0),D36/(Воронка!$D$13*D24),"нет БУ") -> 9722.2222 | E37: =IF(AND(ISNUMBER(E36),Воронка!$D$13*E24>0),E36/(Воронка!$D$13*E24),"нет БУ") -> 5116.9591 | F37: =IF(AND(ISNUMBER(F36),Воронка!$D$13*F24>0),F36/(Воронка!$D$13*F24),"нет БУ") -> 20467.836
B38: Простая окупаемость разработки владельцем, мес | C38: =IF(Сценарии_BEP!$D$29<=0,"нет данных о разработке",IF(C33>0,Сценарии_BEP!$D$29/C33,"не окупается")) -> не окупается | D38: =IF(Сценарии_BEP!$D$29<=0,"нет данных о разработке",IF(D33>0,Сценарии_BEP!$D$29/D33,"не окупается")) -> не окупается | E38: =IF(Сценарии_BEP!$D$29<=0,"нет данных о разработке",IF(E33>0,Сценарии_BEP!$D$29/E33,"не окупается")) -> не окупается | F38: =IF(Сценарии_BEP!$D$29<=0,"нет данных о разработке",IF(F33>0,Сценарии_BEP!$D$29/F33,"не окупается")) -> не окупается
B40: Сценарий: Оптимист
B41: Показатель | C41: I1=A · D10=б+ | D41: I1=A · D10=а | E41: I1=B · D10=б+ | F41: I1=B · D10=а
B42: Множитель потока D10 | C42: 1 | D42: =N('Входные данные'!$G$47) -> 0.25 | E42: 1 | F42: =N('Входные данные'!$G$47) -> 0.25
B43: Заказов с сайта в месяц | C43: =Воронка!$E$12*C42 -> 10.125 | D43: =Воронка!$E$12*D42 -> 2.53125 | E43: =Воронка!$E$12*E42 -> 10.125 | F43: =Воронка!$E$12*F42 -> 2.53125
B44: Доля партнёров | C44: 0 | D44: 0 | E44: =N('Входные данные'!$G$41) -> 0.7 | F44: =N('Входные данные'!$G$41) -> 0.7
B45: Заказов берёт KMT (в пределах мощности) | C45: =MIN(C43*(1-C44),Воронка!$E$19) -> 10 | D45: =MIN(D43*(1-D44),Воронка!$E$19) -> 2.53125 | E45: =MIN(E43*(1-E44),Воронка!$E$19) -> 3.0375 | F45: =MIN(F43*(1-F44),Воронка!$E$19) -> 0.759375
B46: Заказов у партнёров | C46: =C43*C44 -> 0 | D46: =D43*D44 -> 0 | E46: =E43*E44 -> 7.0875 | F46: =F43*F44 -> 1.771875
B47: Доход владельца на заказ сайта (без мощности) | C47: =(1-C44)*'Юнит-экономика'!$E$23+C44*'Юнит-экономика'!$E$27 -> 700000 | D47: =(1-D44)*'Юнит-экономика'!$E$23+D44*'Юнит-экономика'!$E$27 -> 700000 | E47: =(1-E44)*'Юнит-экономика'!$E$23+E44*'Юнит-экономика'!$E$27 -> 280000 | F47: =(1-F44)*'Юнит-экономика'!$E$23+F44*'Юнит-экономика'!$E$27 -> 280000
B48: Доход владельца в месяц | C48: =C49+C45*'Юнит-экономика'!$E$28*(1-N('Входные данные'!$G$44)) -> 7000000 | D48: =D49+D45*'Юнит-экономика'!$E$28*(1-N('Входные данные'!$G$44)) -> 1771875 | E48: =E49+E45*'Юнит-экономика'!$E$28*(1-N('Входные данные'!$G$44)) -> 2835000 | F48: =F49+F45*'Юнит-экономика'!$E$28*(1-N('Входные данные'!$G$44)) -> 708750
B49: Доход проекта в месяц (комиссии) | C49: =C45*'Юнит-экономика'!$E$29+C46*'Юнит-экономика'!$E$27 -> 1020000 | D49: =D45*'Юнит-экономика'!$E$29+D46*'Юнит-экономика'!$E$27 -> 258187.5 | E49: =E45*'Юнит-экономика'!$E$29+E46*'Юнит-экономика'!$E$27 -> 1018575 | F49: =F45*'Юнит-экономика'!$E$29+F46*'Юнит-экономика'!$E$27 -> 254643.75
B50: Полные операционные расходы в месяц | C50: =Сценарии_BEP!$E$21 -> 8750000 | D50: =Сценарии_BEP!$E$21 -> 8750000 | E50: =Сценарии_BEP!$E$21 -> 8750000 | F50: =Сценарии_BEP!$E$21 -> 8750000
B51: Результат владельца в месяц | C51: =C48-C50 -> -1750000 | D51: =D48-D50 -> -6978125 | E51: =E48-E50 -> -5915000 | F51: =F48-F50 -> -8041250
B52: Результат проекта в месяц | C52: =C49-C50 -> -7730000 | D52: =D49-D50 -> -8491812.5 | E52: =E49-E50 -> -7731425 | F52: =F49-F50 -> -8495356.2
B53: Разница результата владельца с (A, б+) | C53: =C51-$C51 -> 0 | D53: =D51-$C51 -> -5228125 | E53: =E51-$C51 -> -4165000 | F53: =F51-$C51 -> -6291250
B54: БУ владельца: заказов с сайта в месяц | C54: =IF(C47>0,C50/C47,"нет БУ") -> 12.5 | D54: =IF(D47>0,D50/D47,"нет БУ") -> 12.5 | E54: =IF(E47>0,E50/E47,"нет БУ") -> 31.25 | F54: =IF(F47>0,F50/F47,"нет БУ") -> 31.25
B55: БУ владельца: расчётов уровня 1 в месяц | C55: =IF(AND(ISNUMBER(C54),Воронка!$E$13*C42>0),C54/(Воронка!$E$13*C42),"нет БУ") -> 1111.1111 | D55: =IF(AND(ISNUMBER(D54),Воронка!$E$13*D42>0),D54/(Воронка!$E$13*D42),"нет БУ") -> 4444.4444 | E55: =IF(AND(ISNUMBER(E54),Воронка!$E$13*E42>0),E54/(Воронка!$E$13*E42),"нет БУ") -> 2777.7778 | F55: =IF(AND(ISNUMBER(F54),Воронка!$E$13*F42>0),F54/(Воронка!$E$13*F42),"нет БУ") -> 11111.111
B56: Простая окупаемость разработки владельцем, мес | C56: =IF(Сценарии_BEP!$E$29<=0,"нет данных о разработке",IF(C51>0,Сценарии_BEP!$E$29/C51,"не окупается")) -> не окупается | D56: =IF(Сценарии_BEP!$E$29<=0,"нет данных о разработке",IF(D51>0,Сценарии_BEP!$E$29/D51,"не окупается")) -> не окупается | E56: =IF(Сценарии_BEP!$E$29<=0,"нет данных о разработке",IF(E51>0,Сценарии_BEP!$E$29/E51,"не окупается")) -> не окупается | F56: =IF(Сценарии_BEP!$E$29<=0,"нет данных о разработке",IF(F51>0,Сценарии_BEP!$E$29/F51,"не окупается")) -> не окупается
B58: Цена решений (доход владельца, сум в месяц)
B59: Показатель | C59: Пессимист | D59: База | E59: Оптимист | F59: Как читать
B60: Цена нейтрального текста при I1=A (б+ минус а) | C60: =$C$12-$D$12 -> 151875 | D60: =$C$30-$D$30 -> 810000 | E60: =$C$48-$D$48 -> 5228125 | F60: Сколько дохода в месяц теряется от отказа от блока KMT. Выгода нейтральности не измерена
B61: Цена агрегатора при D10=б+ (A минус B; плюс — агрегатор невыгоден) | C61: =$C$12-$E$12 -> 94500 | D61: =$C$30-$E$30 -> 567000 | E61: =$C$48-$E$48 -> 4165000 | F61: Сколько дохода в месяц уходит партнёрам за вычетом комиссии 10%; плюс — гибрид теряет, минус — выигрывает
B63: Не смоделировано: форма заказа (D10-в, после A4–A8), список оценщиков (D10-г), публичный пул с произвольной комиссией (I1-B прежней нумерации), белая марка (I1-D).
B64: Сочетание «I1 = B» с «D10 = б+» внутренне противоречиво: блок только с контактами KMT не передаёт заказы партнёрам. Это решение за владельцем; здесь показаны оба.
B65: Заглушка m_a: заменить данными (клики по блоку KMT на первых 100 результатах). Выгода нейтральности (доверие Общества и партнёров) в деньгах не оценена.

Sheet Чувствительность
A1: Чувствительность
A2: Оси сеток (синий шрифт) — перебор для чувствительности, не оценки. Все ячейки результатов — формулы; расчёт идёт от столбца «База».
B4: 1. Заказов с сайта в месяц (База): конверсия расчёт→интерес × интерес→заказ
B5: строки: расчёт→интерес | столбцы: интерес→заказ
C6: 0.01 | D6: 0.02 | E6: 0.035 | F6: 0.05 | G6: 0.07
B7: 0.1 | C7: =Воронка!$D$6*$B7*C$6*Воронка!$D$11*Воронка!$D$17 -> 0.27 | D7: =Воронка!$D$6*$B7*D$6*Воронка!$D$11*Воронка!$D$17 -> 0.54 | E7: =Воронка!$D$6*$B7*E$6*Воронка!$D$11*Воронка!$D$17 -> 0.945 | F7: =Воронка!$D$6*$B7*F$6*Воронка!$D$11*Воронка!$D$17 -> 1.35 | G7: =Воронка!$D$6*$B7*G$6*Воронка!$D$11*Воронка!$D$17 -> 1.89
B8: 0.15 | C8: =Воронка!$D$6*$B8*C$6*Воронка!$D$11*Воронка!$D$17 -> 0.405 | D8: =Воронка!$D$6*$B8*D$6*Воронка!$D$11*Воронка!$D$17 -> 0.81 | E8: =Воронка!$D$6*$B8*E$6*Воронка!$D$11*Воронка!$D$17 -> 1.4175 | F8: =Воронка!$D$6*$B8*F$6*Воронка!$D$11*Воронка!$D$17 -> 2.025 | G8: =Воронка!$D$6*$B8*G$6*Воронка!$D$11*Воронка!$D$17 -> 2.835
B9: 0.2 | C9: =Воронка!$D$6*$B9*C$6*Воронка!$D$11*Воронка!$D$17 -> 0.54 | D9: =Воронка!$D$6*$B9*D$6*Воронка!$D$11*Воронка!$D$17 -> 1.08 | E9: =Воронка!$D$6*$B9*E$6*Воронка!$D$11*Воронка!$D$17 -> 1.89 | F9: =Воронка!$D$6*$B9*F$6*Воронка!$D$11*Воронка!$D$17 -> 2.7 | G9: =Воронка!$D$6*$B9*G$6*Воронка!$D$11*Воронка!$D$17 -> 3.78
B10: 0.25 | C10: =Воронка!$D$6*$B10*C$6*Воронка!$D$11*Воронка!$D$17 -> 0.675 | D10: =Воронка!$D$6*$B10*D$6*Воронка!$D$11*Воронка!$D$17 -> 1.35 | E10: =Воронка!$D$6*$B10*E$6*Воронка!$D$11*Воронка!$D$17 -> 2.3625 | F10: =Воронка!$D$6*$B10*F$6*Воронка!$D$11*Воронка!$D$17 -> 3.375 | G10: =Воронка!$D$6*$B10*G$6*Воронка!$D$11*Воронка!$D$17 -> 4.725
B11: 0.3 | C11: =Воронка!$D$6*$B11*C$6*Воронка!$D$11*Воронка!$D$17 -> 0.81 | D11: =Воронка!$D$6*$B11*D$6*Воронка!$D$11*Воронка!$D$17 -> 1.62 | E11: =Воронка!$D$6*$B11*E$6*Воронка!$D$11*Воронка!$D$17 -> 2.835 | F11: =Воронка!$D$6*$B11*F$6*Воронка!$D$11*Воронка!$D$17 -> 4.05 | G11: =Воронка!$D$6*$B11*G$6*Воронка!$D$11*Воронка!$D$17 -> 5.67
B12: Объём расчётов — заглушка. Колонка 5% — ввод владельца; 2% и 3,5% — мои исходные гипотезы из 05_4P
B14: 2. Результат владельца в месяц (База, полные расходы), сум: c1 × c2
B15: строки: расчёт→интерес | столбцы: интерес→заказ
C16: 0.01 | D16: 0.02 | E16: 0.035 | F16: 0.05 | G16: 0.07
B17: 0.1 | C17: =(MIN(Воронка!$D$6*$B17*C$16*Воронка!$D$11*Воронка!$D$17*(1-Воронка!$D$20),Воронка!$D$19)*'Юнит-экономика'!$D$23+Воронка!$D$6*$B17*C$16*Воронка!$D$11*Воронка!$D$17*Воронка!$D$20*'Юнит-экономика'!$D$27)-Сценарии_BEP!$D$21 -> -8698700 | D17: =(MIN(Воронка!$D$6*$B17*D$16*Воронка!$D$11*Воронка!$D$17*(1-Воронка!$D$20),Воронка!$D$19)*'Юнит-экономика'!$D$23+Воронка!$D$6*$B17*D$16*Воронка!$D$11*Воронка!$D$17*Воронка!$D$20*'Юнит-экономика'!$D$27)-Сценарии_BEP!$D$21 -> -8647400 | E17: =(MIN(Воронка!$D$6*$B17*E$16*Воронка!$D$11*Воронка!$D$17*(1-Воронка!$D$20),Воронка!$D$19)*'Юнит-экономика'!$D$23+Воронка!$D$6*$B17*E$16*Воронка!$D$11*Воронка!$D$17*Воронка!$D$20*'Юнит-экономика'!$D$27)-Сценарии_BEP!$D$21 -> -8570450 | F17: =(MIN(Воронка!$D$6*$B17*F$16*Воронка!$D$11*Воронка!$D$17*(1-Воронка!$D$20),Воронка!$D$19)*'Юнит-экономика'!$D$23+Воронка!$D$6*$B17*F$16*Воронка!$D$11*Воронка!$D$17*Воронка!$D$20*'Юнит-экономика'!$D$27)-Сценарии_BEP!$D$21 -> -8493500 | G17: =(MIN(Воронка!$D$6*$B17*G$16*Воронка!$D$11*Воронка!$D$17*(1-Воронка!$D$20),Воронка!$D$19)*'Юнит-экономика'!$D$23+Воронка!$D$6*$B17*G$16*Воронка!$D$11*Воронка!$D$17*Воронка!$D$20*'Юнит-экономика'!$D$27)-Сценарии_BEP!$D$21 -> -8390900
B18: 0.15 | C18: =(MIN(Воронка!$D$6*$B18*C$16*Воронка!$D$11*Воронка!$D$17*(1-Воронка!$D$20),Воронка!$D$19)*'Юнит-экономика'!$D$23+Воронка!$D$6*$B18*C$16*Воронка!$D$11*Воронка!$D$17*Воронка!$D$20*'Юнит-экономика'!$D$27)-Сценарии_BEP!$D$21 -> -8673050 | D18: =(MIN(Воронка!$D$6*$B18*D$16*Воронка!$D$11*Воронка!$D$17*(1-Воронка!$D$20),Воронка!$D$19)*'Юнит-экономика'!$D$23+Воронка!$D$6*$B18*D$16*Воронка!$D$11*Воронка!$D$17*Воронка!$D$20*'Юнит-экономика'!$D$27)-Сценарии_BEP!$D$21 -> -8596100 | E18: =(MIN(Воронка!$D$6*$B18*E$16*Воронка!$D$11*Воронка!$D$17*(1-Воронка!$D$20),Воронка!$D$19)*'Юнит-экономика'!$D$23+Воронка!$D$6*$B18*E$16*Воронка!$D$11*Воронка!$D$17*Воронка!$D$20*'Юнит-экономика'!$D$27)-Сценарии_BEP!$D$21 -> -8480675 | F18: =(MIN(Воронка!$D$6*$B18*F$16*Воронка!$D$11*Воронка!$D$17*(1-Воронка!$D$20),Воронка!$D$19)*'Юнит-экономика'!$D$23+Воронка!$D$6*$B18*F$16*Воронка!$D$11*Воронка!$D$17*Воронка!$D$20*'Юнит-экономика'!$D$27)-Сценарии_BEP!$D$21 -> -8365250 | G18: =(MIN(Воронка!$D$6*$B18*G$16*Воронка!$D$11*Воронка!$D$17*(1-Воронка!$D$20),Воронка!$D$19)*'Юнит-экономика'!$D$23+Воронка!$D$6*$B18*G$16*Воронка!$D$11*Воронка!$D$17*Воронка!$D$20*'Юнит-экономика'!$D$27)-Сценарии_BEP!$D$21 -> -8211350
B19: 0.2 | C19: =(MIN(Воронка!$D$6*$B19*C$16*Воронка!$D$11*Воронка!$D$17*(1-Воронка!$D$20),Воронка!$D$19)*'Юнит-экономика'!$D$23+Воронка!$D$6*$B19*C$16*Воронка!$D$11*Воронка!$D$17*Воронка!$D$20*'Юнит-экономика'!$D$27)-Сценарии_BEP!$D$21 -> -8647400 | D19: =(MIN(Воронка!$D$6*$B19*D$16*Воронка!$D$11*Воронка!$D$17*(1-Воронка!$D$20),Воронка!$D$19)*'Юнит-экономика'!$D$23+Воронка!$D$6*$B19*D$16*Воронка!$D$11*Воронка!$D$17*Воронка!$D$20*'Юнит-экономика'!$D$27)-Сценарии_BEP!$D$21 -> -8544800 | E19: =(MIN(Воронка!$D$6*$B19*E$16*Воронка!$D$11*Воронка!$D$17*(1-Воронка!$D$20),Воронка!$D$19)*'Юнит-экономика'!$D$23+Воронка!$D$6*$B19*E$16*Воронка!$D$11*Воронка!$D$17*Воронка!$D$20*'Юнит-экономика'!$D$27)-Сценарии_BEP!$D$21 -> -8390900 | F19: =(MIN(Воронка!$D$6*$B19*F$16*Воронка!$D$11*Воронка!$D$17*(1-Воронка!$D$20),Воронка!$D$19)*'Юнит-экономика'!$D$23+Воронка!$D$6*$B19*F$16*Воронка!$D$11*Воронка!$D$17*Воронка!$D$20*'Юнит-экономика'!$D$27)-Сценарии_BEP!$D$21 -> -8237000 | G19: =(MIN(Воронка!$D$6*$B19*G$16*Воронка!$D$11*Воронка!$D$17*(1-Воронка!$D$20),Воронка!$D$19)*'Юнит-экономика'!$D$23+Воронка!$D$6*$B19*G$16*Воронка!$D$11*Воронка!$D$17*Воронка!$D$20*'Юнит-экономика'!$D$27)-Сценарии_BEP!$D$21 -> -8031800
B20: 0.25 | C20: =(MIN(Воронка!$D$6*$B20*C$16*Воронка!$D$11*Воронка!$D$17*(1-Воронка!$D$20),Воронка!$D$19)*'Юнит-экономика'!$D$23+Воронка!$D$6*$B20*C$16*Воронка!$D$11*Воронка!$D$17*Воронка!$D$20*'Юнит-экономика'!$D$27)-Сценарии_BEP!$D$21 -> -8621750 | D20: =(MIN(Воронка!$D$6*$B20*D$16*Воронка!$D$11*Воронка!$D$17*(1-Воронка!$D$20),Воронка!$D$19)*'Юнит-экономика'!$D$23+Воронка!$D$6*$B20*D$16*Воронка!$D$11*Воронка!$D$17*Воронка!$D$20*'Юнит-экономика'!$D$27)-Сценарии_BEP!$D$21 -> -8493500 | E20: =(MIN(Воронка!$D$6*$B20*E$16*Воронка!$D$11*Воронка!$D$17*(1-Воронка!$D$20),Воронка!$D$19)*'Юнит-экономика'!$D$23+Воронка!$D$6*$B20*E$16*Воронка!$D$11*Воронка!$D$17*Воронка!$D$20*'Юнит-экономика'!$D$27)-Сценарии_BEP!$D$21 -> -8301125 | F20: =(MIN(Воронка!$D$6*$B20*F$16*Воронка!$D$11*Воронка!$D$17*(1-Воронка!$D$20),Воронка!$D$19)*'Юнит-экономика'!$D$23+Воронка!$D$6*$B20*F$16*Воронка!$D$11*Воронка!$D$17*Воронка!$D$20*'Юнит-экономика'!$D$27)-Сценарии_BEP!$D$21 -> -8108750 | G20: =(MIN(Воронка!$D$6*$B20*G$16*Воронка!$D$11*Воронка!$D$17*(1-Воронка!$D$20),Воронка!$D$19)*'Юнит-экономика'!$D$23+Воронка!$D$6*$B20*G$16*Воронка!$D$11*Воронка!$D$17*Воронка!$D$20*'Юнит-экономика'!$D$27)-Сценарии_BEP!$D$21 -> -7852250
B21: 0.3 | C21: =(MIN(Воронка!$D$6*$B21*C$16*Воронка!$D$11*Воронка!$D$17*(1-Воронка!$D$20),Воронка!$D$19)*'Юнит-экономика'!$D$23+Воронка!$D$6*$B21*C$16*Воронка!$D$11*Воронка!$D$17*Воронка!$D$20*'Юнит-экономика'!$D$27)-Сценарии_BEP!$D$21 -> -8596100 | D21: =(MIN(Воронка!$D$6*$B21*D$16*Воронка!$D$11*Воронка!$D$17*(1-Воронка!$D$20),Воронка!$D$19)*'Юнит-экономика'!$D$23+Воронка!$D$6*$B21*D$16*Воронка!$D$11*Воронка!$D$17*Воронка!$D$20*'Юнит-экономика'!$D$27)-Сценарии_BEP!$D$21 -> -8442200 | E21: =(MIN(Воронка!$D$6*$B21*E$16*Воронка!$D$11*Воронка!$D$17*(1-Воронка!$D$20),Воронка!$D$19)*'Юнит-экономика'!$D$23+Воронка!$D$6*$B21*E$16*Воронка!$D$11*Воронка!$D$17*Воронка!$D$20*'Юнит-экономика'!$D$27)-Сценарии_BEP!$D$21 -> -8211350 | F21: =(MIN(Воронка!$D$6*$B21*F$16*Воронка!$D$11*Воронка!$D$17*(1-Воронка!$D$20),Воронка!$D$19)*'Юнит-экономика'!$D$23+Воронка!$D$6*$B21*F$16*Воронка!$D$11*Воронка!$D$17*Воронка!$D$20*'Юнит-экономика'!$D$27)-Сценарии_BEP!$D$21 -> -7980500 | G21: =(MIN(Воронка!$D$6*$B21*G$16*Воронка!$D$11*Воронка!$D$17*(1-Воронка!$D$20),Воронка!$D$19)*'Юнит-экономика'!$D$23+Воронка!$D$6*$B21*G$16*Воронка!$D$11*Воронка!$D$17*Воронка!$D$20*'Юнит-экономика'!$D$27)-Сценарии_BEP!$D$21 -> -7672700
B22: С учётом мощности KMT и выбранного I1
B24: 3. БУ: заказов в месяц
B25: строки: доход на заказ с сайта, сум | столбцы: операционные расходы в месяц, сум
C26: 1000000 | D26: 2500000 | E26: 3750000 | F26: 7500000 | G26: 8750000
B27: 100000 | C27: =IF($B27>0,C$26/$B27,"нет БУ") -> 10 | D27: =IF($B27>0,D$26/$B27,"нет БУ") -> 25 | E27: =IF($B27>0,E$26/$B27,"нет БУ") -> 37.5 | F27: =IF($B27>0,F$26/$B27,"нет БУ") -> 75 | G27: =IF($B27>0,G$26/$B27,"нет БУ") -> 87.5
B28: 200000 | C28: =IF($B28>0,C$26/$B28,"нет БУ") -> 5 | D28: =IF($B28>0,D$26/$B28,"нет БУ") -> 12.5 | E28: =IF($B28>0,E$26/$B28,"нет БУ") -> 18.75 | F28: =IF($B28>0,F$26/$B28,"нет БУ") -> 37.5 | G28: =IF($B28>0,G$26/$B28,"нет БУ") -> 43.75
B29: 300000 | C29: =IF($B29>0,C$26/$B29,"нет БУ") -> 3.3333333 | D29: =IF($B29>0,D$26/$B29,"нет БУ") -> 8.3333333 | E29: =IF($B29>0,E$26/$B29,"нет БУ") -> 12.5 | F29: =IF($B29>0,F$26/$B29,"нет БУ") -> 25 | G29: =IF($B29>0,G$26/$B29,"нет БУ") -> 29.166667
B30: 400000 | C30: =IF($B30>0,C$26/$B30,"нет БУ") -> 2.5 | D30: =IF($B30>0,D$26/$B30,"нет БУ") -> 6.25 | E30: =IF($B30>0,E$26/$B30,"нет БУ") -> 9.375 | F30: =IF($B30>0,F$26/$B30,"нет БУ") -> 18.75 | G30: =IF($B30>0,G$26/$B30,"нет БУ") -> 21.875
B31: 600000 | C31: =IF($B31>0,C$26/$B31,"нет БУ") -> 1.6666667 | D31: =IF($B31>0,D$26/$B31,"нет БУ") -> 4.1666667 | E31: =IF($B31>0,E$26/$B31,"нет БУ") -> 6.25 | F31: =IF($B31>0,F$26/$B31,"нет БУ") -> 12.5 | G31: =IF($B31>0,G$26/$B31,"нет БУ") -> 14.583333
B32: 2,5 млн — хостинг, SMS и другое без колл-центра; 3,75 млн — плюс постоянная часть труда; 7,5 млн — с колл-центром 5 млн (без труда); 8,75 млн — с колл-центром и трудом (База)
B34: 4. БУ: расчётов уровня 1 в месяц при сквозной конверсии База
B35: строки: доход на заказ с сайта, сум | столбцы: операционные расходы в месяц, сум
C36: 1000000 | D36: 2500000 | E36: 3750000 | F36: 7500000 | G36: 8750000
B37: 100000 | C37: =IF(AND($B37>0,Сценарии_BEP!$D$35>0),C$36/$B37/Сценарии_BEP!$D$35,"нет БУ") -> 1111.1111 | D37: =IF(AND($B37>0,Сценарии_BEP!$D$35>0),D$36/$B37/Сценарии_BEP!$D$35,"нет БУ") -> 2777.7778 | E37: =IF(AND($B37>0,Сценарии_BEP!$D$35>0),E$36/$B37/Сценарии_BEP!$D$35,"нет БУ") -> 4166.6667 | F37: =IF(AND($B37>0,Сценарии_BEP!$D$35>0),F$36/$B37/Сценарии_BEP!$D$35,"нет БУ") -> 8333.3333 | G37: =IF(AND($B37>0,Сценарии_BEP!$D$35>0),G$36/$B37/Сценарии_BEP!$D$35,"нет БУ") -> 9722.2222
B38: 200000 | C38: =IF(AND($B38>0,Сценарии_BEP!$D$35>0),C$36/$B38/Сценарии_BEP!$D$35,"нет БУ") -> 555.55556 | D38: =IF(AND($B38>0,Сценарии_BEP!$D$35>0),D$36/$B38/Сценарии_BEP!$D$35,"нет БУ") -> 1388.8889 | E38: =IF(AND($B38>0,Сценарии_BEP!$D$35>0),E$36/$B38/Сценарии_BEP!$D$35,"нет БУ") -> 2083.3333 | F38: =IF(AND($B38>0,Сценарии_BEP!$D$35>0),F$36/$B38/Сценарии_BEP!$D$35,"нет БУ") -> 4166.6667 | G38: =IF(AND($B38>0,Сценарии_BEP!$D$35>0),G$36/$B38/Сценарии_BEP!$D$35,"нет БУ") -> 4861.1111
B39: 300000 | C39: =IF(AND($B39>0,Сценарии_BEP!$D$35>0),C$36/$B39/Сценарии_BEP!$D$35,"нет БУ") -> 370.37037 | D39: =IF(AND($B39>0,Сценарии_BEP!$D$35>0),D$36/$B39/Сценарии_BEP!$D$35,"нет БУ") -> 925.92593 | E39: =IF(AND($B39>0,Сценарии_BEP!$D$35>0),E$36/$B39/Сценарии_BEP!$D$35,"нет БУ") -> 1388.8889 | F39: =IF(AND($B39>0,Сценарии_BEP!$D$35>0),F$36/$B39/Сценарии_BEP!$D$35,"нет БУ") -> 2777.7778 | G39: =IF(AND($B39>0,Сценарии_BEP!$D$35>0),G$36/$B39/Сценарии_BEP!$D$35,"нет БУ") -> 3240.7407
B40: 400000 | C40: =IF(AND($B40>0,Сценарии_BEP!$D$35>0),C$36/$B40/Сценарии_BEP!$D$35,"нет БУ") -> 277.77778 | D40: =IF(AND($B40>0,Сценарии_BEP!$D$35>0),D$36/$B40/Сценарии_BEP!$D$35,"нет БУ") -> 694.44444 | E40: =IF(AND($B40>0,Сценарии_BEP!$D$35>0),E$36/$B40/Сценарии_BEP!$D$35,"нет БУ") -> 1041.6667 | F40: =IF(AND($B40>0,Сценарии_BEP!$D$35>0),F$36/$B40/Сценарии_BEP!$D$35,"нет БУ") -> 2083.3333 | G40: =IF(AND($B40>0,Сценарии_BEP!$D$35>0),G$36/$B40/Сценарии_BEP!$D$35,"нет БУ") -> 2430.5556
B41: 600000 | C41: =IF(AND($B41>0,Сценарии_BEP!$D$35>0),C$36/$B41/Сценарии_BEP!$D$35,"нет БУ") -> 185.18519 | D41: =IF(AND($B41>0,Сценарии_BEP!$D$35>0),D$36/$B41/Сценарии_BEP!$D$35,"нет БУ") -> 462.96296 | E41: =IF(AND($B41>0,Сценарии_BEP!$D$35>0),E$36/$B41/Сценарии_BEP!$D$35,"нет БУ") -> 694.44444 | F41: =IF(AND($B41>0,Сценарии_BEP!$D$35>0),F$36/$B41/Сценарии_BEP!$D$35,"нет БУ") -> 1388.8889 | G41: =IF(AND($B41>0,Сценарии_BEP!$D$35>0),G$36/$B41/Сценарии_BEP!$D$35,"нет БУ") -> 1620.3704
B42: Сравнить с заглушкой 100 / 300 / 900 расчётов: нужен реальный размер рынка
B44: 5. Допустимая стоимость привлечения на один расчёт, сум (потолок из «Входные данные»)
B45: строки: доход на заказ с сайта, сум | столбцы: сквозная конверсия расчёт→заказ
C46: 0.003 | D46: 0.007 | E46: 0.0125 | F46: 0.02 | G46: 0.045
B47: 100000 | C47: =$B47*N('Входные данные'!$F$49)*C$46 -> 60 | D47: =$B47*N('Входные данные'!$F$49)*D$46 -> 140 | E47: =$B47*N('Входные данные'!$F$49)*E$46 -> 250 | F47: =$B47*N('Входные данные'!$F$49)*F$46 -> 400 | G47: =$B47*N('Входные данные'!$F$49)*G$46 -> 900
B48: 200000 | C48: =$B48*N('Входные данные'!$F$49)*C$46 -> 120 | D48: =$B48*N('Входные данные'!$F$49)*D$46 -> 280 | E48: =$B48*N('Входные данные'!$F$49)*E$46 -> 500 | F48: =$B48*N('Входные данные'!$F$49)*F$46 -> 800 | G48: =$B48*N('Входные данные'!$F$49)*G$46 -> 1800
B49: 300000 | C49: =$B49*N('Входные данные'!$F$49)*C$46 -> 180 | D49: =$B49*N('Входные данные'!$F$49)*D$46 -> 420 | E49: =$B49*N('Входные данные'!$F$49)*E$46 -> 750 | F49: =$B49*N('Входные данные'!$F$49)*F$46 -> 1200 | G49: =$B49*N('Входные данные'!$F$49)*G$46 -> 2700
B50: 400000 | C50: =$B50*N('Входные данные'!$F$49)*C$46 -> 240 | D50: =$B50*N('Входные данные'!$F$49)*D$46 -> 560 | E50: =$B50*N('Входные данные'!$F$49)*E$46 -> 1000 | F50: =$B50*N('Входные данные'!$F$49)*F$46 -> 1600 | G50: =$B50*N('Входные данные'!$F$49)*G$46 -> 3600
B51: 600000 | C51: =$B51*N('Входные данные'!$F$49)*C$46 -> 360 | D51: =$B51*N('Входные данные'!$F$49)*D$46 -> 840 | E51: =$B51*N('Входные данные'!$F$49)*E$46 -> 1500 | F51: =$B51*N('Входные данные'!$F$49)*F$46 -> 2400 | G51: =$B51*N('Входные данные'!$F$49)*G$46 -> 5400
B52: Сравнить с ценой клика (не проверена, нужно от Темура)
B54: 6. Постоянный труд, сум в месяц, при одной ставке за час для всех (База, часы владельца)
B55: строки: единицы часов: 1 неделя, 2 месяц, 3 весь этап | столбцы: ставка, сум/час
C56: 0 | D56: 25000 | E56: 50000 | F56: 100000 | G56: 200000
B57: 1 | C57: =IF($B57=1,(N('Входные данные'!$F$67)*(1-N('Входные данные'!$F$75))+N('Входные данные'!$F$68)*(1-N('Входные данные'!$F$76))+N('Входные данные'!$F$69)*(1-N('Входные данные'!$F$77)))*52/12*C$56,IF($B57=2,(N('Входные данные'!$F$67)*(1-N('Входные данные'!$F$75))+N('Входные данные'!$F$68)*(1-N('Входные данные'!$F$76))+N('Входные данные'!$F$69)*(1-N('Входные данные'!$F$77)))*C$56,IF(N('Входные данные'!$F$66)>0,(N('Входные данные'!$F$67)*(1-N('Входные данные'!$F$75))+N('Входные данные'!$F$68)*(1-N('Входные данные'!$F$76))+N('Входные данные'!$F$69)*(1-N('Входные данные'!$F$77)))/N('Входные данные'!$F$66)*C$56,"нужна длительность этапа"))) -> 0 | D57: =IF($B57=1,(N('Входные данные'!$F$67)*(1-N('Входные данные'!$F$75))+N('Входные данные'!$F$68)*(1-N('Входные данные'!$F$76))+N('Входные данные'!$F$69)*(1-N('Входные данные'!$F$77)))*52/12*D$56,IF($B57=2,(N('Входные данные'!$F$67)*(1-N('Входные данные'!$F$75))+N('Входные данные'!$F$68)*(1-N('Входные данные'!$F$76))+N('Входные данные'!$F$69)*(1-N('Входные данные'!$F$77)))*D$56,IF(N('Входные данные'!$F$66)>0,(N('Входные данные'!$F$67)*(1-N('Входные данные'!$F$75))+N('Входные данные'!$F$68)*(1-N('Входные данные'!$F$76))+N('Входные данные'!$F$69)*(1-N('Входные данные'!$F$77)))/N('Входные данные'!$F$66)*D$56,"нужна длительность этапа"))) -> 1083333.3 | E57: =IF($B57=1,(N('Входные данные'!$F$67)*(1-N('Входные данные'!$F$75))+N('Входные данные'!$F$68)*(1-N('Входные данные'!$F$76))+N('Входные данные'!$F$69)*(1-N('Входные данные'!$F$77)))*52/12*E$56,IF($B57=2,(N('Входные данные'!$F$67)*(1-N('Входные данные'!$F$75))+N('Входные данные'!$F$68)*(1-N('Входные данные'!$F$76))+N('Входные данные'!$F$69)*(1-N('Входные данные'!$F$77)))*E$56,IF(N('Входные данные'!$F$66)>0,(N('Входные данные'!$F$67)*(1-N('Входные данные'!$F$75))+N('Входные данные'!$F$68)*(1-N('Входные данные'!$F$76))+N('Входные данные'!$F$69)*(1-N('Входные данные'!$F$77)))/N('Входные данные'!$F$66)*E$56,"нужна длительность этапа"))) -> 2166666.7 | F57: =IF($B57=1,(N('Входные данные'!$F$67)*(1-N('Входные данные'!$F$75))+N('Входные данные'!$F$68)*(1-N('Входные данные'!$F$76))+N('Входные данные'!$F$69)*(1-N('Входные данные'!$F$77)))*52/12*F$56,IF($B57=2,(N('Входные данные'!$F$67)*(1-N('Входные данные'!$F$75))+N('Входные данные'!$F$68)*(1-N('Входные данные'!$F$76))+N('Входные данные'!$F$69)*(1-N('Входные данные'!$F$77)))*F$56,IF(N('Входные данные'!$F$66)>0,(N('Входные данные'!$F$67)*(1-N('Входные данные'!$F$75))+N('Входные данные'!$F$68)*(1-N('Входные данные'!$F$76))+N('Входные данные'!$F$69)*(1-N('Входные данные'!$F$77)))/N('Входные данные'!$F$66)*F$56,"нужна длительность этапа"))) -> 4333333.3 | G57: =IF($B57=1,(N('Входные данные'!$F$67)*(1-N('Входные данные'!$F$75))+N('Входные данные'!$F$68)*(1-N('Входные данные'!$F$76))+N('Входные данные'!$F$69)*(1-N('Входные данные'!$F$77)))*52/12*G$56,IF($B57=2,(N('Входные данные'!$F$67)*(1-N('Входные данные'!$F$75))+N('Входные данные'!$F$68)*(1-N('Входные данные'!$F$76))+N('Входные данные'!$F$69)*(1-N('Входные данные'!$F$77)))*G$56,IF(N('Входные данные'!$F$66)>0,(N('Входные данные'!$F$67)*(1-N('Входные данные'!$F$75))+N('Входные данные'!$F$68)*(1-N('Входные данные'!$F$76))+N('Входные данные'!$F$69)*(1-N('Входные данные'!$F$77)))/N('Входные данные'!$F$66)*G$56,"нужна длительность этапа"))) -> 8666666.7
B58: 2 | C58: =IF($B58=1,(N('Входные данные'!$F$67)*(1-N('Входные данные'!$F$75))+N('Входные данные'!$F$68)*(1-N('Входные данные'!$F$76))+N('Входные данные'!$F$69)*(1-N('Входные данные'!$F$77)))*52/12*C$56,IF($B58=2,(N('Входные данные'!$F$67)*(1-N('Входные данные'!$F$75))+N('Входные данные'!$F$68)*(1-N('Входные данные'!$F$76))+N('Входные данные'!$F$69)*(1-N('Входные данные'!$F$77)))*C$56,IF(N('Входные данные'!$F$66)>0,(N('Входные данные'!$F$67)*(1-N('Входные данные'!$F$75))+N('Входные данные'!$F$68)*(1-N('Входные данные'!$F$76))+N('Входные данные'!$F$69)*(1-N('Входные данные'!$F$77)))/N('Входные данные'!$F$66)*C$56,"нужна длительность этапа"))) -> 0 | D58: =IF($B58=1,(N('Входные данные'!$F$67)*(1-N('Входные данные'!$F$75))+N('Входные данные'!$F$68)*(1-N('Входные данные'!$F$76))+N('Входные данные'!$F$69)*(1-N('Входные данные'!$F$77)))*52/12*D$56,IF($B58=2,(N('Входные данные'!$F$67)*(1-N('Входные данные'!$F$75))+N('Входные данные'!$F$68)*(1-N('Входные данные'!$F$76))+N('Входные данные'!$F$69)*(1-N('Входные данные'!$F$77)))*D$56,IF(N('Входные данные'!$F$66)>0,(N('Входные данные'!$F$67)*(1-N('Входные данные'!$F$75))+N('Входные данные'!$F$68)*(1-N('Входные данные'!$F$76))+N('Входные данные'!$F$69)*(1-N('Входные данные'!$F$77)))/N('Входные данные'!$F$66)*D$56,"нужна длительность этапа"))) -> 250000 | E58: =IF($B58=1,(N('Входные данные'!$F$67)*(1-N('Входные данные'!$F$75))+N('Входные данные'!$F$68)*(1-N('Входные данные'!$F$76))+N('Входные данные'!$F$69)*(1-N('Входные данные'!$F$77)))*52/12*E$56,IF($B58=2,(N('Входные данные'!$F$67)*(1-N('Входные данные'!$F$75))+N('Входные данные'!$F$68)*(1-N('Входные данные'!$F$76))+N('Входные данные'!$F$69)*(1-N('Входные данные'!$F$77)))*E$56,IF(N('Входные данные'!$F$66)>0,(N('Входные данные'!$F$67)*(1-N('Входные данные'!$F$75))+N('Входные данные'!$F$68)*(1-N('Входные данные'!$F$76))+N('Входные данные'!$F$69)*(1-N('Входные данные'!$F$77)))/N('Входные данные'!$F$66)*E$56,"нужна длительность этапа"))) -> 500000 | F58: =IF($B58=1,(N('Входные данные'!$F$67)*(1-N('Входные данные'!$F$75))+N('Входные данные'!$F$68)*(1-N('Входные данные'!$F$76))+N('Входные данные'!$F$69)*(1-N('Входные данные'!$F$77)))*52/12*F$56,IF($B58=2,(N('Входные данные'!$F$67)*(1-N('Входные данные'!$F$75))+N('Входные данные'!$F$68)*(1-N('Входные данные'!$F$76))+N('Входные данные'!$F$69)*(1-N('Входные данные'!$F$77)))*F$56,IF(N('Входные данные'!$F$66)>0,(N('Входные данные'!$F$67)*(1-N('Входные данные'!$F$75))+N('Входные данные'!$F$68)*(1-N('Входные данные'!$F$76))+N('Входные данные'!$F$69)*(1-N('Входные данные'!$F$77)))/N('Входные данные'!$F$66)*F$56,"нужна длительность этапа"))) -> 1000000 | G58: =IF($B58=1,(N('Входные данные'!$F$67)*(1-N('Входные данные'!$F$75))+N('Входные данные'!$F$68)*(1-N('Входные данные'!$F$76))+N('Входные данные'!$F$69)*(1-N('Входные данные'!$F$77)))*52/12*G$56,IF($B58=2,(N('Входные данные'!$F$67)*(1-N('Входные данные'!$F$75))+N('Входные данные'!$F$68)*(1-N('Входные данные'!$F$76))+N('Входные данные'!$F$69)*(1-N('Входные данные'!$F$77)))*G$56,IF(N('Входные данные'!$F$66)>0,(N('Входные данные'!$F$67)*(1-N('Входные данные'!$F$75))+N('Входные данные'!$F$68)*(1-N('Входные данные'!$F$76))+N('Входные данные'!$F$69)*(1-N('Входные данные'!$F$77)))/N('Входные данные'!$F$66)*G$56,"нужна длительность этапа"))) -> 2000000
B59: 3 | C59: =IF($B59=1,(N('Входные данные'!$F$67)*(1-N('Входные данные'!$F$75))+N('Входные данные'!$F$68)*(1-N('Входные данные'!$F$76))+N('Входные данные'!$F$69)*(1-N('Входные данные'!$F$77)))*52/12*C$56,IF($B59=2,(N('Входные данные'!$F$67)*(1-N('Входные данные'!$F$75))+N('Входные данные'!$F$68)*(1-N('Входные данные'!$F$76))+N('Входные данные'!$F$69)*(1-N('Входные данные'!$F$77)))*C$56,IF(N('Входные данные'!$F$66)>0,(N('Входные данные'!$F$67)*(1-N('Входные данные'!$F$75))+N('Входные данные'!$F$68)*(1-N('Входные данные'!$F$76))+N('Входные данные'!$F$69)*(1-N('Входные данные'!$F$77)))/N('Входные данные'!$F$66)*C$56,"нужна длительность этапа"))) -> 0 | D59: =IF($B59=1,(N('Входные данные'!$F$67)*(1-N('Входные данные'!$F$75))+N('Входные данные'!$F$68)*(1-N('Входные данные'!$F$76))+N('Входные данные'!$F$69)*(1-N('Входные данные'!$F$77)))*52/12*D$56,IF($B59=2,(N('Входные данные'!$F$67)*(1-N('Входные данные'!$F$75))+N('Входные данные'!$F$68)*(1-N('Входные данные'!$F$76))+N('Входные данные'!$F$69)*(1-N('Входные данные'!$F$77)))*D$56,IF(N('Входные данные'!$F$66)>0,(N('Входные данные'!$F$67)*(1-N('Входные данные'!$F$75))+N('Входные данные'!$F$68)*(1-N('Входные данные'!$F$76))+N('Входные данные'!$F$69)*(1-N('Входные данные'!$F$77)))/N('Входные данные'!$F$66)*D$56,"нужна длительность этапа"))) -> 83333.333 | E59: =IF($B59=1,(N('Входные данные'!$F$67)*(1-N('Входные данные'!$F$75))+N('Входные данные'!$F$68)*(1-N('Входные данные'!$F$76))+N('Входные данные'!$F$69)*(1-N('Входные данные'!$F$77)))*52/12*E$56,IF($B59=2,(N('Входные данные'!$F$67)*(1-N('Входные данные'!$F$75))+N('Входные данные'!$F$68)*(1-N('Входные данные'!$F$76))+N('Входные данные'!$F$69)*(1-N('Входные данные'!$F$77)))*E$56,IF(N('Входные данные'!$F$66)>0,(N('Входные данные'!$F$67)*(1-N('Входные данные'!$F$75))+N('Входные данные'!$F$68)*(1-N('Входные данные'!$F$76))+N('Входные данные'!$F$69)*(1-N('Входные данные'!$F$77)))/N('Входные данные'!$F$66)*E$56,"нужна длительность этапа"))) -> 166666.67 | F59: =IF($B59=1,(N('Входные данные'!$F$67)*(1-N('Входные данные'!$F$75))+N('Входные данные'!$F$68)*(1-N('Входные данные'!$F$76))+N('Входные данные'!$F$69)*(1-N('Входные данные'!$F$77)))*52/12*F$56,IF($B59=2,(N('Входные данные'!$F$67)*(1-N('Входные данные'!$F$75))+N('Входные данные'!$F$68)*(1-N('Входные данные'!$F$76))+N('Входные данные'!$F$69)*(1-N('Входные данные'!$F$77)))*F$56,IF(N('Входные данные'!$F$66)>0,(N('Входные данные'!$F$67)*(1-N('Входные данные'!$F$75))+N('Входные данные'!$F$68)*(1-N('Входные данные'!$F$76))+N('Входные данные'!$F$69)*(1-N('Входные данные'!$F$77)))/N('Входные данные'!$F$66)*F$56,"нужна длительность этапа"))) -> 333333.33 | G59: =IF($B59=1,(N('Входные данные'!$F$67)*(1-N('Входные данные'!$F$75))+N('Входные данные'!$F$68)*(1-N('Входные данные'!$F$76))+N('Входные данные'!$F$69)*(1-N('Входные данные'!$F$77)))*52/12*G$56,IF($B59=2,(N('Входные данные'!$F$67)*(1-N('Входные данные'!$F$75))+N('Входные данные'!$F$68)*(1-N('Входные данные'!$F$76))+N('Входные данные'!$F$69)*(1-N('Входные данные'!$F$77)))*G$56,IF(N('Входные данные'!$F$66)>0,(N('Входные данные'!$F$67)*(1-N('Входные данные'!$F$75))+N('Входные данные'!$F$68)*(1-N('Входные данные'!$F$76))+N('Входные данные'!$F$69)*(1-N('Входные данные'!$F$77)))/N('Входные данные'!$F$66)*G$56,"нужна длительность этапа"))) -> 666666.67
B60: Сетка показывает разброс по единицам часов; основной расчёт идёт по ставкам владельца (в месяц)
B62: 7. Разработка и запуск (труд, разово), сум, при одной ставке за час для всех (База)
B63: строки: единицы часов: 1 неделя, 2 месяц, 3 весь этап | столбцы: ставка, сум/час
C64: 0 | D64: 25000 | E64: 50000 | F64: 100000 | G64: 200000
B65: 1 | C65: =IF($B65=3,(N('Входные данные'!$F$67)*N('Входные данные'!$F$75)+N('Входные данные'!$F$68)*N('Входные данные'!$F$76)+N('Входные данные'!$F$69)*N('Входные данные'!$F$77))*C$64,IF(N('Входные данные'!$F$66)>0,(N('Входные данные'!$F$67)*N('Входные данные'!$F$75)+N('Входные данные'!$F$68)*N('Входные данные'!$F$76)+N('Входные данные'!$F$69)*N('Входные данные'!$F$77))*IF($B65=1,N('Входные данные'!$F$66)*52/12,N('Входные данные'!$F$66))*C$64,"нужна длительность этапа")) -> 0 | D65: =IF($B65=3,(N('Входные данные'!$F$67)*N('Входные данные'!$F$75)+N('Входные данные'!$F$68)*N('Входные данные'!$F$76)+N('Входные данные'!$F$69)*N('Входные данные'!$F$77))*D$64,IF(N('Входные данные'!$F$66)>0,(N('Входные данные'!$F$67)*N('Входные данные'!$F$75)+N('Входные данные'!$F$68)*N('Входные данные'!$F$76)+N('Входные данные'!$F$69)*N('Входные данные'!$F$77))*IF($B65=1,N('Входные данные'!$F$66)*52/12,N('Входные данные'!$F$66))*D$64,"нужна длительность этапа")) -> 24375000 | E65: =IF($B65=3,(N('Входные данные'!$F$67)*N('Входные данные'!$F$75)+N('Входные данные'!$F$68)*N('Входные данные'!$F$76)+N('Входные данные'!$F$69)*N('Входные данные'!$F$77))*E$64,IF(N('Входные данные'!$F$66)>0,(N('Входные данные'!$F$67)*N('Входные данные'!$F$75)+N('Входные данные'!$F$68)*N('Входные данные'!$F$76)+N('Входные данные'!$F$69)*N('Входные данные'!$F$77))*IF($B65=1,N('Входные данные'!$F$66)*52/12,N('Входные данные'!$F$66))*E$64,"нужна длительность этапа")) -> 48750000 | F65: =IF($B65=3,(N('Входные данные'!$F$67)*N('Входные данные'!$F$75)+N('Входные данные'!$F$68)*N('Входные данные'!$F$76)+N('Входные данные'!$F$69)*N('Входные данные'!$F$77))*F$64,IF(N('Входные данные'!$F$66)>0,(N('Входные данные'!$F$67)*N('Входные данные'!$F$75)+N('Входные данные'!$F$68)*N('Входные данные'!$F$76)+N('Входные данные'!$F$69)*N('Входные данные'!$F$77))*IF($B65=1,N('Входные данные'!$F$66)*52/12,N('Входные данные'!$F$66))*F$64,"нужна длительность этапа")) -> 97500000 | G65: =IF($B65=3,(N('Входные данные'!$F$67)*N('Входные данные'!$F$75)+N('Входные данные'!$F$68)*N('Входные данные'!$F$76)+N('Входные данные'!$F$69)*N('Входные данные'!$F$77))*G$64,IF(N('Входные данные'!$F$66)>0,(N('Входные данные'!$F$67)*N('Входные данные'!$F$75)+N('Входные данные'!$F$68)*N('Входные данные'!$F$76)+N('Входные данные'!$F$69)*N('Входные данные'!$F$77))*IF($B65=1,N('Входные данные'!$F$66)*52/12,N('Входные данные'!$F$66))*G$64,"нужна длительность этапа")) -> 195000000
B66: 2 | C66: =IF($B66=3,(N('Входные данные'!$F$67)*N('Входные данные'!$F$75)+N('Входные данные'!$F$68)*N('Входные данные'!$F$76)+N('Входные данные'!$F$69)*N('Входные данные'!$F$77))*C$64,IF(N('Входные данные'!$F$66)>0,(N('Входные данные'!$F$67)*N('Входные данные'!$F$75)+N('Входные данные'!$F$68)*N('Входные данные'!$F$76)+N('Входные данные'!$F$69)*N('Входные данные'!$F$77))*IF($B66=1,N('Входные данные'!$F$66)*52/12,N('Входные данные'!$F$66))*C$64,"нужна длительность этапа")) -> 0 | D66: =IF($B66=3,(N('Входные данные'!$F$67)*N('Входные данные'!$F$75)+N('Входные данные'!$F$68)*N('Входные данные'!$F$76)+N('Входные данные'!$F$69)*N('Входные данные'!$F$77))*D$64,IF(N('Входные данные'!$F$66)>0,(N('Входные данные'!$F$67)*N('Входные данные'!$F$75)+N('Входные данные'!$F$68)*N('Входные данные'!$F$76)+N('Входные данные'!$F$69)*N('Входные данные'!$F$77))*IF($B66=1,N('Входные данные'!$F$66)*52/12,N('Входные данные'!$F$66))*D$64,"нужна длительность этапа")) -> 5625000 | E66: =IF($B66=3,(N('Входные данные'!$F$67)*N('Входные данные'!$F$75)+N('Входные данные'!$F$68)*N('Входные данные'!$F$76)+N('Входные данные'!$F$69)*N('Входные данные'!$F$77))*E$64,IF(N('Входные данные'!$F$66)>0,(N('Входные данные'!$F$67)*N('Входные данные'!$F$75)+N('Входные данные'!$F$68)*N('Входные данные'!$F$76)+N('Входные данные'!$F$69)*N('Входные данные'!$F$77))*IF($B66=1,N('Входные данные'!$F$66)*52/12,N('Входные данные'!$F$66))*E$64,"нужна длительность этапа")) -> 11250000 | F66: =IF($B66=3,(N('Входные данные'!$F$67)*N('Входные данные'!$F$75)+N('Входные данные'!$F$68)*N('Входные данные'!$F$76)+N('Входные данные'!$F$69)*N('Входные данные'!$F$77))*F$64,IF(N('Входные данные'!$F$66)>0,(N('Входные данные'!$F$67)*N('Входные данные'!$F$75)+N('Входные данные'!$F$68)*N('Входные данные'!$F$76)+N('Входные данные'!$F$69)*N('Входные данные'!$F$77))*IF($B66=1,N('Входные данные'!$F$66)*52/12,N('Входные данные'!$F$66))*F$64,"нужна длительность этапа")) -> 22500000 | G66: =IF($B66=3,(N('Входные данные'!$F$67)*N('Входные данные'!$F$75)+N('Входные данные'!$F$68)*N('Входные данные'!$F$76)+N('Входные данные'!$F$69)*N('Входные данные'!$F$77))*G$64,IF(N('Входные данные'!$F$66)>0,(N('Входные данные'!$F$67)*N('Входные данные'!$F$75)+N('Входные данные'!$F$68)*N('Входные данные'!$F$76)+N('Входные данные'!$F$69)*N('Входные данные'!$F$77))*IF($B66=1,N('Входные данные'!$F$66)*52/12,N('Входные данные'!$F$66))*G$64,"нужна длительность этапа")) -> 45000000
B67: 3 | C67: =IF($B67=3,(N('Входные данные'!$F$67)*N('Входные данные'!$F$75)+N('Входные данные'!$F$68)*N('Входные данные'!$F$76)+N('Входные данные'!$F$69)*N('Входные данные'!$F$77))*C$64,IF(N('Входные данные'!$F$66)>0,(N('Входные данные'!$F$67)*N('Входные данные'!$F$75)+N('Входные данные'!$F$68)*N('Входные данные'!$F$76)+N('Входные данные'!$F$69)*N('Входные данные'!$F$77))*IF($B67=1,N('Входные данные'!$F$66)*52/12,N('Входные данные'!$F$66))*C$64,"нужна длительность этапа")) -> 0 | D67: =IF($B67=3,(N('Входные данные'!$F$67)*N('Входные данные'!$F$75)+N('Входные данные'!$F$68)*N('Входные данные'!$F$76)+N('Входные данные'!$F$69)*N('Входные данные'!$F$77))*D$64,IF(N('Входные данные'!$F$66)>0,(N('Входные данные'!$F$67)*N('Входные данные'!$F$75)+N('Входные данные'!$F$68)*N('Входные данные'!$F$76)+N('Входные данные'!$F$69)*N('Входные данные'!$F$77))*IF($B67=1,N('Входные данные'!$F$66)*52/12,N('Входные данные'!$F$66))*D$64,"нужна длительность этапа")) -> 1875000 | E67: =IF($B67=3,(N('Входные данные'!$F$67)*N('Входные данные'!$F$75)+N('Входные данные'!$F$68)*N('Входные данные'!$F$76)+N('Входные данные'!$F$69)*N('Входные данные'!$F$77))*E$64,IF(N('Входные данные'!$F$66)>0,(N('Входные данные'!$F$67)*N('Входные данные'!$F$75)+N('Входные данные'!$F$68)*N('Входные данные'!$F$76)+N('Входные данные'!$F$69)*N('Входные данные'!$F$77))*IF($B67=1,N('Входные данные'!$F$66)*52/12,N('Входные данные'!$F$66))*E$64,"нужна длительность этапа")) -> 3750000 | F67: =IF($B67=3,(N('Входные данные'!$F$67)*N('Входные данные'!$F$75)+N('Входные данные'!$F$68)*N('Входные данные'!$F$76)+N('Входные данные'!$F$69)*N('Входные данные'!$F$77))*F$64,IF(N('Входные данные'!$F$66)>0,(N('Входные данные'!$F$67)*N('Входные данные'!$F$75)+N('Входные данные'!$F$68)*N('Входные данные'!$F$76)+N('Входные данные'!$F$69)*N('Входные данные'!$F$77))*IF($B67=1,N('Входные данные'!$F$66)*52/12,N('Входные данные'!$F$66))*F$64,"нужна длительность этапа")) -> 7500000 | G67: =IF($B67=3,(N('Входные данные'!$F$67)*N('Входные данные'!$F$75)+N('Входные данные'!$F$68)*N('Входные данные'!$F$76)+N('Входные данные'!$F$69)*N('Входные данные'!$F$77))*G$64,IF(N('Входные данные'!$F$66)>0,(N('Входные данные'!$F$67)*N('Входные данные'!$F$75)+N('Входные данные'!$F$68)*N('Входные данные'!$F$76)+N('Входные данные'!$F$69)*N('Входные данные'!$F$77))*IF($B67=1,N('Входные данные'!$F$66)*52/12,N('Входные данные'!$F$66))*G$64,"нужна длительность этапа")) -> 15000000
B69: 8. Цена отчёта ±10% и ±20% (База, выбранный I1; прямые затраты в сумах без изменений)
B70: Изменение цены | C70: Цена, сум | D70: Прибыль KMT на заказ после вознаграждения | E70: Множитель заказов | F70: Заказов с сайта в месяц | G70: Доход владельца в месяц | H70: Допустимо на заказ (потолок)
B71: -0.2 | C71: ='Юнит-экономика'!$D$6*(1+B71) -> 816000 | D71: ='Юнит-экономика'!$D$8*(1+B71)-'Юнит-экономика'!$D$11-N('Входные данные'!$F$45)*N('Входные данные'!$F$46)*'Юнит-экономика'!$D$8*(1+B71) -> 196000 | E71: =MAX(0,1+N('Входные данные'!$F$85)*B71/0.1) -> 1.35 | F71: =Воронка!$D$18*E71 -> 3.645 | G71: =MIN(F71*(1-Воронка!$D$20),Воронка!$D$19)*D71+F71*Воронка!$D$20*N('Входные данные'!$F$40)*N('Входные данные'!$F$43)*(1+B71) -> 418446 | H71: =N('Входные данные'!$F$49)*MAX(0,(1-Воронка!$D$20)*D71+Воронка!$D$20*N('Входные данные'!$F$40)*N('Входные данные'!$F$43)*(1+B71)) -> 22960
B72: -0.1 | C72: ='Юнит-экономика'!$D$6*(1+B72) -> 918000 | D72: ='Юнит-экономика'!$D$8*(1+B72)-'Юнит-экономика'!$D$11-N('Входные данные'!$F$45)*N('Входные данные'!$F$46)*'Юнит-экономика'!$D$8*(1+B72) -> 298000 | E72: =MAX(0,1+N('Входные данные'!$F$85)*B72/0.1) -> 1.175 | F72: =Воронка!$D$18*E72 -> 3.1725 | G72: =MIN(F72*(1-Воронка!$D$20),Воронка!$D$19)*D72+F72*Воронка!$D$20*N('Входные данные'!$F$40)*N('Входные данные'!$F$43)*(1+B72) -> 483489 | H72: =N('Входные данные'!$F$49)*MAX(0,(1-Воронка!$D$20)*D72+Воронка!$D$20*N('Входные данные'!$F$40)*N('Входные данные'!$F$43)*(1+B72)) -> 30480
B73: 0 | C73: ='Юнит-экономика'!$D$6*(1+B73) -> 1020000 | D73: ='Юнит-экономика'!$D$8*(1+B73)-'Юнит-экономика'!$D$11-N('Входные данные'!$F$45)*N('Входные данные'!$F$46)*'Юнит-экономика'!$D$8*(1+B73) -> 400000 | E73: =MAX(0,1+N('Входные данные'!$F$85)*B73/0.1) -> 1 | F73: =Воронка!$D$18*E73 -> 2.7 | G73: =MIN(F73*(1-Воронка!$D$20),Воронка!$D$19)*D73+F73*Воронка!$D$20*N('Входные данные'!$F$40)*N('Входные данные'!$F$43)*(1+B73) -> 513000 | H73: =N('Входные данные'!$F$49)*MAX(0,(1-Воронка!$D$20)*D73+Воронка!$D$20*N('Входные данные'!$F$40)*N('Входные данные'!$F$43)*(1+B73)) -> 38000
B74: 0.1 | C74: ='Юнит-экономика'!$D$6*(1+B74) -> 1122000 | D74: ='Юнит-экономика'!$D$8*(1+B74)-'Юнит-экономика'!$D$11-N('Входные данные'!$F$45)*N('Входные данные'!$F$46)*'Юнит-экономика'!$D$8*(1+B74) -> 502000 | E74: =MAX(0,1+N('Входные данные'!$F$85)*B74/0.1) -> 0.825 | F74: =Воронка!$D$18*E74 -> 2.2275 | G74: =MIN(F74*(1-Воронка!$D$20),Воронка!$D$19)*D74+F74*Воронка!$D$20*N('Входные данные'!$F$40)*N('Входные данные'!$F$43)*(1+B74) -> 506979 | H74: =N('Входные данные'!$F$49)*MAX(0,(1-Воронка!$D$20)*D74+Воронка!$D$20*N('Входные данные'!$F$40)*N('Входные данные'!$F$43)*(1+B74)) -> 45520
B75: 0.2 | C75: ='Юнит-экономика'!$D$6*(1+B75) -> 1224000 | D75: ='Юнит-экономика'!$D$8*(1+B75)-'Юнит-экономика'!$D$11-N('Входные данные'!$F$45)*N('Входные данные'!$F$46)*'Юнит-экономика'!$D$8*(1+B75) -> 604000 | E75: =MAX(0,1+N('Входные данные'!$F$85)*B75/0.1) -> 0.65 | F75: =Воронка!$D$18*E75 -> 1.755 | G75: =MIN(F75*(1-Воронка!$D$20),Воронка!$D$19)*D75+F75*Воронка!$D$20*N('Входные данные'!$F$40)*N('Входные данные'!$F$43)*(1+B75) -> 465426 | H75: =N('Входные данные'!$F$49)*MAX(0,(1-Воронка!$D$20)*D75+Воронка!$D$20*N('Входные данные'!$F$40)*N('Входные данные'!$F$43)*(1+B75)) -> 53040
B76: Реакция спроса: при +10% цены заказов на 17,5% меньше (середина «15–20%», вопрос 19). Цена не меняет прямые затраты: при снижении цены прибыль падает на всю разницу.
B78: 9. Агрегатор: доход владельца на заказ с сайта (База) от доли партнёров и комиссии
B79: строки: доля заказов партнёров | столбцы: комиссия проекту, % от договора
C80: 0.05 | D80: 0.1 | E80: 0.15 | F80: 0.2
B81: 0 | C81: =(1-$B81)*'Юнит-экономика'!$D$23+$B81*C$80*N('Входные данные'!$F$43) -> 400000 | D81: =(1-$B81)*'Юнит-экономика'!$D$23+$B81*D$80*N('Входные данные'!$F$43) -> 400000 | E81: =(1-$B81)*'Юнит-экономика'!$D$23+$B81*E$80*N('Входные данные'!$F$43) -> 400000 | F81: =(1-$B81)*'Юнит-экономика'!$D$23+$B81*F$80*N('Входные данные'!$F$43) -> 400000
B82: 0.2 | C82: =(1-$B82)*'Юнит-экономика'!$D$23+$B82*C$80*N('Входные данные'!$F$43) -> 330000 | D82: =(1-$B82)*'Юнит-экономика'!$D$23+$B82*D$80*N('Входные данные'!$F$43) -> 340000 | E82: =(1-$B82)*'Юнит-экономика'!$D$23+$B82*E$80*N('Входные данные'!$F$43) -> 350000 | F82: =(1-$B82)*'Юнит-экономика'!$D$23+$B82*F$80*N('Входные данные'!$F$43) -> 360000
B83: 0.4 | C83: =(1-$B83)*'Юнит-экономика'!$D$23+$B83*C$80*N('Входные данные'!$F$43) -> 260000 | D83: =(1-$B83)*'Юнит-экономика'!$D$23+$B83*D$80*N('Входные данные'!$F$43) -> 280000 | E83: =(1-$B83)*'Юнит-экономика'!$D$23+$B83*E$80*N('Входные данные'!$F$43) -> 300000 | F83: =(1-$B83)*'Юнит-экономика'!$D$23+$B83*F$80*N('Входные данные'!$F$43) -> 320000
B84: 0.7 | C84: =(1-$B84)*'Юнит-экономика'!$D$23+$B84*C$80*N('Входные данные'!$F$43) -> 155000 | D84: =(1-$B84)*'Юнит-экономика'!$D$23+$B84*D$80*N('Входные данные'!$F$43) -> 190000 | E84: =(1-$B84)*'Юнит-экономика'!$D$23+$B84*E$80*N('Входные данные'!$F$43) -> 225000 | F84: =(1-$B84)*'Юнит-экономика'!$D$23+$B84*F$80*N('Входные данные'!$F$43) -> 260000
B85: 1 | C85: =(1-$B85)*'Юнит-экономика'!$D$23+$B85*C$80*N('Входные данные'!$F$43) -> 50000 | D85: =(1-$B85)*'Юнит-экономика'!$D$23+$B85*D$80*N('Входные данные'!$F$43) -> 100000 | E85: =(1-$B85)*'Юнит-экономика'!$D$23+$B85*E$80*N('Входные данные'!$F$43) -> 150000 | F85: =(1-$B85)*'Юнит-экономика'!$D$23+$B85*F$80*N('Входные данные'!$F$43) -> 200000
B86: Каждый процент заказов, ушедший партнёру при комиссии 10%, снижает доход владельца: заказ KMT приносит 400 тыс., заказ партнёра — 100 тыс.
B88: 10. D10: заказы и доход владельца в месяц (База) от доли заказов, сохраняющихся при нейтральном тексте
B89: строки: доля сохранившихся заказов | столбцы: показатель
C90: Заказов в месяц | D90: Доход владельца в месяц, сум | E90: Потеря к б+, сум
B91: 0 | C91: =Воронка!$D$12*$B91 -> 0 | D91: =(MIN(Воронка!$D$12*$B91*(1-Воронка!$D$20),Воронка!$D$19)*'Юнит-экономика'!$D$23+Воронка!$D$12*$B91*Воронка!$D$20*'Юнит-экономика'!$D$27) -> 0 | E91: =Воронка!$D$28-(MIN(Воронка!$D$12*$B91*(1-Воронка!$D$20),Воронка!$D$19)*'Юнит-экономика'!$D$23+Воронка!$D$12*$B91*Воронка!$D$20*'Юнит-экономика'!$D$27) -> 513000
B92: 0.1 | C92: =Воронка!$D$12*$B92 -> 0.27 | D92: =(MIN(Воронка!$D$12*$B92*(1-Воронка!$D$20),Воронка!$D$19)*'Юнит-экономика'!$D$23+Воронка!$D$12*$B92*Воронка!$D$20*'Юнит-экономика'!$D$27) -> 51300 | E92: =Воронка!$D$28-(MIN(Воронка!$D$12*$B92*(1-Воронка!$D$20),Воронка!$D$19)*'Юнит-экономика'!$D$23+Воронка!$D$12*$B92*Воронка!$D$20*'Юнит-экономика'!$D$27) -> 461700
B93: 0.25 | C93: =Воронка!$D$12*$B93 -> 0.675 | D93: =(MIN(Воронка!$D$12*$B93*(1-Воронка!$D$20),Воронка!$D$19)*'Юнит-экономика'!$D$23+Воронка!$D$12*$B93*Воронка!$D$20*'Юнит-экономика'!$D$27) -> 128250 | E93: =Воронка!$D$28-(MIN(Воронка!$D$12*$B93*(1-Воронка!$D$20),Воронка!$D$19)*'Юнит-экономика'!$D$23+Воронка!$D$12*$B93*Воронка!$D$20*'Юнит-экономика'!$D$27) -> 384750
B94: 0.5 | C94: =Воронка!$D$12*$B94 -> 1.35 | D94: =(MIN(Воронка!$D$12*$B94*(1-Воронка!$D$20),Воронка!$D$19)*'Юнит-экономика'!$D$23+Воронка!$D$12*$B94*Воронка!$D$20*'Юнит-экономика'!$D$27) -> 256500 | E94: =Воронка!$D$28-(MIN(Воронка!$D$12*$B94*(1-Воронка!$D$20),Воронка!$D$19)*'Юнит-экономика'!$D$23+Воронка!$D$12*$B94*Воронка!$D$20*'Юнит-экономика'!$D$27) -> 256500
B95: 0.75 | C95: =Воронка!$D$12*$B95 -> 2.025 | D95: =(MIN(Воронка!$D$12*$B95*(1-Воронка!$D$20),Воронка!$D$19)*'Юнит-экономика'!$D$23+Воронка!$D$12*$B95*Воронка!$D$20*'Юнит-экономика'!$D$27) -> 384750 | E95: =Воронка!$D$28-(MIN(Воронка!$D$12*$B95*(1-Воронка!$D$20),Воронка!$D$19)*'Юнит-экономика'!$D$23+Воронка!$D$12*$B95*Воронка!$D$20*'Юнит-экономика'!$D$27) -> 128250
B96: 1 | C96: =Воронка!$D$12*$B96 -> 2.7 | D96: =(MIN(Воронка!$D$12*$B96*(1-Воронка!$D$20),Воронка!$D$19)*'Юнит-экономика'!$D$23+Воронка!$D$12*$B96*Воронка!$D$20*'Юнит-экономика'!$D$27) -> 513000 | E96: =Воронка!$D$28-(MIN(Воронка!$D$12*$B96*(1-Воронка!$D$20),Воронка!$D$19)*'Юнит-экономика'!$D$23+Воронка!$D$12*$B96*Воронка!$D$20*'Юнит-экономика'!$D$27) -> 0
B98: 11. Расчётов уровня 1 в месяц, нужных для полной БУ владельца (База): c1 × c2
B99: строки: расчёт→интерес | столбцы: интерес→заказ
C100: 0.01 | D100: 0.02 | E100: 0.035 | F100: 0.05 | G100: 0.07
B101: 0.1 | C101: =IF('Юнит-экономика'!$D$34>0,Сценарии_BEP!$D$21/('Юнит-экономика'!$D$34*$B101*C$100*Воронка!$D$11*Воронка!$D$17),"нет БУ") -> 51169.591 | D101: =IF('Юнит-экономика'!$D$34>0,Сценарии_BEP!$D$21/('Юнит-экономика'!$D$34*$B101*D$100*Воронка!$D$11*Воронка!$D$17),"нет БУ") -> 25584.795 | E101: =IF('Юнит-экономика'!$D$34>0,Сценарии_BEP!$D$21/('Юнит-экономика'!$D$34*$B101*E$100*Воронка!$D$11*Воронка!$D$17),"нет БУ") -> 14619.883 | F101: =IF('Юнит-экономика'!$D$34>0,Сценарии_BEP!$D$21/('Юнит-экономика'!$D$34*$B101*F$100*Воронка!$D$11*Воронка!$D$17),"нет БУ") -> 10233.918 | G101: =IF('Юнит-экономика'!$D$34>0,Сценарии_BEP!$D$21/('Юнит-экономика'!$D$34*$B101*G$100*Воронка!$D$11*Воронка!$D$17),"нет БУ") -> 7309.9415
B102: 0.15 | C102: =IF('Юнит-экономика'!$D$34>0,Сценарии_BEP!$D$21/('Юнит-экономика'!$D$34*$B102*C$100*Воронка!$D$11*Воронка!$D$17),"нет БУ") -> 34113.06 | D102: =IF('Юнит-экономика'!$D$34>0,Сценарии_BEP!$D$21/('Юнит-экономика'!$D$34*$B102*D$100*Воронка!$D$11*Воронка!$D$17),"нет БУ") -> 17056.53 | E102: =IF('Юнит-экономика'!$D$34>0,Сценарии_BEP!$D$21/('Юнит-экономика'!$D$34*$B102*E$100*Воронка!$D$11*Воронка!$D$17),"нет БУ") -> 9746.5887 | F102: =IF('Юнит-экономика'!$D$34>0,Сценарии_BEP!$D$21/('Юнит-экономика'!$D$34*$B102*F$100*Воронка!$D$11*Воронка!$D$17),"нет БУ") -> 6822.6121 | G102: =IF('Юнит-экономика'!$D$34>0,Сценарии_BEP!$D$21/('Юнит-экономика'!$D$34*$B102*G$100*Воронка!$D$11*Воронка!$D$17),"нет БУ") -> 4873.2943
B103: 0.2 | C103: =IF('Юнит-экономика'!$D$34>0,Сценарии_BEP!$D$21/('Юнит-экономика'!$D$34*$B103*C$100*Воронка!$D$11*Воронка!$D$17),"нет БУ") -> 25584.795 | D103: =IF('Юнит-экономика'!$D$34>0,Сценарии_BEP!$D$21/('Юнит-экономика'!$D$34*$B103*D$100*Воронка!$D$11*Воронка!$D$17),"нет БУ") -> 12792.398 | E103: =IF('Юнит-экономика'!$D$34>0,Сценарии_BEP!$D$21/('Юнит-экономика'!$D$34*$B103*E$100*Воронка!$D$11*Воронка!$D$17),"нет БУ") -> 7309.9415 | F103: =IF('Юнит-экономика'!$D$34>0,Сценарии_BEP!$D$21/('Юнит-экономика'!$D$34*$B103*F$100*Воронка!$D$11*Воронка!$D$17),"нет БУ") -> 5116.9591 | G103: =IF('Юнит-экономика'!$D$34>0,Сценарии_BEP!$D$21/('Юнит-экономика'!$D$34*$B103*G$100*Воронка!$D$11*Воронка!$D$17),"нет БУ") -> 3654.9708
B104: 0.25 | C104: =IF('Юнит-экономика'!$D$34>0,Сценарии_BEP!$D$21/('Юнит-экономика'!$D$34*$B104*C$100*Воронка!$D$11*Воронка!$D$17),"нет БУ") -> 20467.836 | D104: =IF('Юнит-экономика'!$D$34>0,Сценарии_BEP!$D$21/('Юнит-экономика'!$D$34*$B104*D$100*Воронка!$D$11*Воронка!$D$17),"нет БУ") -> 10233.918 | E104: =IF('Юнит-экономика'!$D$34>0,Сценарии_BEP!$D$21/('Юнит-экономика'!$D$34*$B104*E$100*Воронка!$D$11*Воронка!$D$17),"нет БУ") -> 5847.9532 | F104: =IF('Юнит-экономика'!$D$34>0,Сценарии_BEP!$D$21/('Юнит-экономика'!$D$34*$B104*F$100*Воронка!$D$11*Воронка!$D$17),"нет БУ") -> 4093.5673 | G104: =IF('Юнит-экономика'!$D$34>0,Сценарии_BEP!$D$21/('Юнит-экономика'!$D$34*$B104*G$100*Воронка!$D$11*Воронка!$D$17),"нет БУ") -> 2923.9766
B105: 0.3 | C105: =IF('Юнит-экономика'!$D$34>0,Сценарии_BEP!$D$21/('Юнит-экономика'!$D$34*$B105*C$100*Воронка!$D$11*Воронка!$D$17),"нет БУ") -> 17056.53 | D105: =IF('Юнит-экономика'!$D$34>0,Сценарии_BEP!$D$21/('Юнит-экономика'!$D$34*$B105*D$100*Воронка!$D$11*Воронка!$D$17),"нет БУ") -> 8528.2651 | E105: =IF('Юнит-экономика'!$D$34>0,Сценарии_BEP!$D$21/('Юнит-экономика'!$D$34*$B105*E$100*Воронка!$D$11*Воронка!$D$17),"нет БУ") -> 4873.2943 | F105: =IF('Юнит-экономика'!$D$34>0,Сценарии_BEP!$D$21/('Юнит-экономика'!$D$34*$B105*F$100*Воронка!$D$11*Воронка!$D$17),"нет БУ") -> 3411.306 | G105: =IF('Юнит-экономика'!$D$34>0,Сценарии_BEP!$D$21/('Юнит-экономика'!$D$34*$B105*G$100*Воронка!$D$11*Воронка!$D$17),"нет БУ") -> 2436.6472
B106: Без учёта мощности KMT: при БУ нужно слишком много заказов для нынешнего запаса 10 в месяц
B108: 12. Как читать ставку труда (База): три трактовки
B109: Трактовка | C109: Труд за все часы, сум/мес | D109: Постоянная часть, сум/мес | E109: Разработка разово, сум
B110: 2 — месячная ставка полной занятости, оплачиваются фактические часы | C110: =(IF(N('Входные данные'!$F$71)>0,N('Входные данные'!$F$67)*IF(N('Входные данные'!$F$65)=1,52/12,IF(N('Входные данные'!$F$65)=2,1,IF(AND(N('Входные данные'!$F$65)=3,N('Входные данные'!$F$66)>0),1/N('Входные данные'!$F$66),0)))/(N('Входные данные'!$F$71)*52/12)*N('Входные данные'!$F$72),0))+(IF(N('Входные данные'!$F$71)>0,N('Входные данные'!$F$68)*IF(N('Входные данные'!$F$65)=1,52/12,IF(N('Входные данные'!$F$65)=2,1,IF(AND(N('Входные данные'!$F$65)=3,N('Входные данные'!$F$66)>0),1/N('Входные данные'!$F$66),0)))/(N('Входные данные'!$F$71)*52/12)*N('Входные данные'!$F$73),0))+(IF(N('Входные данные'!$F$71)>0,N('Входные данные'!$F$69)*IF(N('Входные данные'!$F$65)=1,52/12,IF(N('Входные данные'!$F$65)=2,1,IF(AND(N('Входные данные'!$F$65)=3,N('Входные данные'!$F$66)>0),1/N('Входные данные'!$F$66),0)))/(N('Входные данные'!$F$71)*52/12)*N('Входные данные'!$F$74),0)) -> 23750000 | D110: =(IF(N('Входные данные'!$F$71)>0,N('Входные данные'!$F$67)*IF(N('Входные данные'!$F$65)=1,52/12,IF(N('Входные данные'!$F$65)=2,1,IF(AND(N('Входные данные'!$F$65)=3,N('Входные данные'!$F$66)>0),1/N('Входные данные'!$F$66),0)))/(N('Входные данные'!$F$71)*52/12)*N('Входные данные'!$F$72),0))*(1-N('Входные данные'!$F$75))+(IF(N('Входные данные'!$F$71)>0,N('Входные данные'!$F$68)*IF(N('Входные данные'!$F$65)=1,52/12,IF(N('Входные данные'!$F$65)=2,1,IF(AND(N('Входные данные'!$F$65)=3,N('Входные данные'!$F$66)>0),1/N('Входные данные'!$F$66),0)))/(N('Входные данные'!$F$71)*52/12)*N('Входные данные'!$F$73),0))*(1-N('Входные данные'!$F$76))+(IF(N('Входные данные'!$F$71)>0,N('Входные данные'!$F$69)*IF(N('Входные данные'!$F$65)=1,52/12,IF(N('Входные данные'!$F$65)=2,1,IF(AND(N('Входные данные'!$F$65)=3,N('Входные данные'!$F$66)>0),1/N('Входные данные'!$F$66),0)))/(N('Входные данные'!$F$71)*52/12)*N('Входные данные'!$F$74),0))*(1-N('Входные данные'!$F$77)) -> 1250000 | E110: =(IF(N('Входные данные'!$F$71)>0,N('Входные данные'!$F$67)*IF(N('Входные данные'!$F$65)=1,52/12,IF(N('Входные данные'!$F$65)=2,1,IF(AND(N('Входные данные'!$F$65)=3,N('Входные данные'!$F$66)>0),1/N('Входные данные'!$F$66),0)))/(N('Входные данные'!$F$71)*52/12)*N('Входные данные'!$F$72),0))*N('Входные данные'!$F$75)*N('Входные данные'!$F$66)+(IF(N('Входные данные'!$F$71)>0,N('Входные данные'!$F$68)*IF(N('Входные данные'!$F$65)=1,52/12,IF(N('Входные данные'!$F$65)=2,1,IF(AND(N('Входные данные'!$F$65)=3,N('Входные данные'!$F$66)>0),1/N('Входные данные'!$F$66),0)))/(N('Входные данные'!$F$71)*52/12)*N('Входные данные'!$F$73),0))*N('Входные данные'!$F$76)*N('Входные данные'!$F$66)+(IF(N('Входные данные'!$F$71)>0,N('Входные данные'!$F$69)*IF(N('Входные данные'!$F$65)=1,52/12,IF(N('Входные данные'!$F$65)=2,1,IF(AND(N('Входные данные'!$F$65)=3,N('Входные данные'!$F$66)>0),1/N('Входные данные'!$F$66),0)))/(N('Входные данные'!$F$71)*52/12)*N('Входные данные'!$F$74),0))*N('Входные данные'!$F$77)*N('Входные данные'!$F$66) -> 67500000
B111: 3 — месячная ставка как есть, независимо от часов | C111: =(N('Входные данные'!$F$72))+(N('Входные данные'!$F$73))+(N('Входные данные'!$F$74)) -> 45000000 | D111: =(N('Входные данные'!$F$72))*(1-N('Входные данные'!$F$75))+(N('Входные данные'!$F$73))*(1-N('Входные данные'!$F$76))+(N('Входные данные'!$F$74))*(1-N('Входные данные'!$F$77)) -> 1000000 | E111: =(N('Входные данные'!$F$72))*N('Входные данные'!$F$75)*N('Входные данные'!$F$66)+(N('Входные данные'!$F$73))*N('Входные данные'!$F$76)*N('Входные данные'!$F$66)+(N('Входные данные'!$F$74))*N('Входные данные'!$F$77)*N('Входные данные'!$F$66) -> 132000000
B112: Выбор между 2 и 3 — вопрос к владельцу (см. «Вопросы к Темуру»). Основной расчёт идёт по значению rate_mode.
...

Sheet Проверка
A1: Проверка модели
A2: Статусы: OK, ОШИБКА (нужно исправить формулу), НЕТ ДАННЫХ (формулы верны, нужен ввод владельца), ВНИМАНИЕ (результат верен, но допущение вызывает сомнения).
B3: Общий статус: | C3: =IF(COUNTIF(D6:D34,"ОШИБКА")>0,"ЕСТЬ ОШИБКИ",IF(COUNTIF(D6:D34,"НЕТ ДАННЫХ")>0,"ФОРМУЛЫ ОК, НЕ ХВАТАЕТ ДАННЫХ ВЛАДЕЛЬЦА",IF(COUNTIF(D6:D34,"ВНИМАНИЕ")>0,"ФОРМУЛЫ ОК, ЕСТЬ ПРЕДУПРЕЖДЕНИЯ","ВСЁ ОК"))) -> ФОРМУЛЫ ОК, НЕ ХВАТАЕТ ДАННЫХ ВЛАДЕЛЬЦА
A5: № | B5: Проверка | C5: Значение | D5: Статус | E5: Комментарий
A6: C01 | B6: Ошибки формул: Входные данные | C6: =SUMPRODUCT(--ISERROR('Входные данные'!E13:G85)) -> 0 | D6: =IF(C6=0,"OK","ОШИБКА") -> OK
A7: C02 | B7: Ошибки формул: Юнит-экономика | C7: =SUMPRODUCT(--ISERROR('Юнит-экономика'!C5:E44)) -> 0 | D7: =IF(C7=0,"OK","ОШИБКА") -> OK
A8: C03 | B8: Ошибки формул: Воронка | C8: =SUMPRODUCT(--ISERROR(Воронка!C5:E29)) -> 0 | D8: =IF(C8=0,"OK","ОШИБКА") -> OK
A9: C04 | B9: Ошибки формул: Сценарии_BEP | C9: =SUMPRODUCT(--ISERROR(Сценарии_BEP!C5:P150)) -> 0 | D9: =IF(C9=0,"OK","ОШИБКА") -> OK
A10: C05 | B10: Ошибки формул: D10_I1 | C10: =SUMPRODUCT(--ISERROR(D10_I1!C4:F66)) -> 0 | D10: =IF(C10=0,"OK","ОШИБКА") -> OK
A11: C06 | B11: Ошибки формул: Чувствительность | C11: =SUMPRODUCT(--ISERROR(Чувствительность!B4:H123)) -> 0 | D11: =IF(C11=0,"OK","ОШИБКА") -> OK
A12: C07 | B12: Тождество юнит-экономики: выручка − прямые затраты − вознаграждение − прибыль = 0 (по 3 сценариям) | C12: =ABS('Юнит-экономика'!$C$8-'Юнит-экономика'!$C$11-'Юнит-экономика'!$C$22-'Юнит-экономика'!$C$23)+ABS('Юнит-экономика'!$D$8-'Юнит-экономика'!$D$11-'Юнит-экономика'!$D$22-'Юнит-экономика'!$D$23)+ABS('Юнит-экономика'!$E$8-'Юнит-экономика'!$E$11-'Юнит-экономика'!$E$22-'Юнит-экономика'!$E$23) -> 0 | D12: =IF(C12<0.001,"OK","ОШИБКА") -> OK
A13: C08 | B13: Метод 3: прибыль заказа равна вводу владельца | C13: =IF(AND(N('Входные данные'!$E$26)=3,'Юнит-экономика'!$C$8>0),ABS('Юнит-экономика'!$C$12-N('Входные данные'!$E$27)),0)+IF(AND(N('Входные данные'!$F$26)=3,'Юнит-экономика'!$D$8>0),ABS('Юнит-экономика'!$D$12-N('Входные данные'!$F$27)),0)+IF(AND(N('Входные данные'!$G$26)=3,'Юнит-экономика'!$E$8>0),ABS('Юнит-экономика'!$E$12-N('Входные данные'!$G$27)),0) -> 0 | D13: =IF(C13<0.001,"OK","ОШИБКА") -> OK | E13: Проверяется, когда выручка > 0
A14: C09 | B14: Доли цены в сумме дают 100% (800 тыс. + 1 млн + дороже) | C14: =ABS(N('Входные данные'!$F$14)+N('Входные данные'!$F$15)+N('Входные данные'!$F$16)-1) -> 0 | D14: =IF(C14<0.001,"OK","ОШИБКА") -> OK
A15: C10 | B15: Воронка: заказы = расчёты × c1 × c2 × инкрементальность | C15: =ABS(Воронка!$C$12-N('Входные данные'!$E$55)*N('Входные данные'!$E$57)*N('Входные данные'!$E$58)*N('Входные данные'!$E$59))+ABS(Воронка!$D$12-N('Входные данные'!$F$55)*N('Входные данные'!$F$57)*N('Входные данные'!$F$58)*N('Входные данные'!$F$59))+ABS(Воронка!$E$12-N('Входные данные'!$G$55)*N('Входные данные'!$G$57)*N('Входные данные'!$G$58)*N('Входные данные'!$G$59)) -> 0 | D15: =IF(C15<0.001,"OK","ОШИБКА") -> OK
A16: C11 | B16: Заказы сохраняются: направлено в KMT + у партнёров = заказов с сайта (режим) | C16: =ABS(Воронка!$C$21+Воронка!$C$24-Воронка!$C$18)+ABS(Воронка!$D$21+Воронка!$D$24-Воронка!$D$18)+ABS(Воронка!$E$21+Воронка!$E$24-Воронка!$E$18) -> 0 | D16: =IF(C16<0.001,"OK","ОШИБКА") -> OK
A17: C12 | B17: Доход владельца = доход проекта + прибыль KMT после комиссии = K × прибыль + P × комиссия партнёра (режим) | C17: =ABS(Воронка!$C$28-(Воронка!$C$22*'Юнит-экономика'!$C$23+Воронка!$C$24*'Юнит-экономика'!$C$27))+ABS(Воронка!$D$28-(Воронка!$D$22*'Юнит-экономика'!$D$23+Воронка!$D$24*'Юнит-экономика'!$D$27))+ABS(Воронка!$E$28-(Воронка!$E$22*'Юнит-экономика'!$E$23+Воронка!$E$24*'Юнит-экономика'!$E$27)) -> 0 | D17: =IF(C17<0.001,"OK","ОШИБКА") -> OK | E17: Комиссия KMT → проект гасится
A18: C13 | B18: Помесячная модель: итог за 12 мес = −разработка + сумма операций (владелец и проект, по 3 сценариям) | C18: =ABS(Сценарии_BEP!O91-(Сценарии_BEP!C90+Сценарии_BEP!P86))+ABS(Сценарии_BEP!O92-(Сценарии_BEP!C90+Сценарии_BEP!P87))+ABS(Сценарии_BEP!O117-(Сценарии_BEP!C116+Сценарии_BEP!P112))+ABS(Сценарии_BEP!O118-(Сценарии_BEP!C116+Сценарии_BEP!P113))+ABS(Сценарии_BEP!O143-(Сценарии_BEP!C142+Сценарии_BEP!P138))+ABS(Сценарии_BEP!O144-(Сценарии_BEP!C142+Сценарии_BEP!P139)) -> 0 | D18: =IF(C18<0.001,"OK","ОШИБКА") -> OK
A19: C14 | B19: Помесячная модель выходит на режим: заказы в 12-м месяце = режим Воронки | C19: =IF(N('Входные данные'!$F$60)>12,0,IF(OR(N('Входные данные'!$E$37)=1,N('Входные данные'!$E$42)<12),ABS(Сценарии_BEP!O78+Сценарии_BEP!O80-(Воронка!$C$22+Воронка!$C$24)),0)+IF(OR(N('Входные данные'!$F$37)=1,N('Входные данные'!$F$42)<12),ABS(Сценарии_BEP!O104+Сценарии_BEP!O106-(Воронка!$D$22+Воронка!$D$24)),0)+IF(OR(N('Входные данные'!$G$37)=1,N('Входные данные'!$G$42)<12),ABS(Сценарии_BEP!O130+Сценарии_BEP!O132-(Воронка!$E$22+Воронка!$E$24)),0)) -> 0 | D19: =IF(C19<0.001,"OK","ОШИБКА") -> OK | E19: Пропускается, если выход на режим дольше 12 мес или партнёры подключаются позже 12-го месяца
A20: C15 | B20: D10_I1: выбранное сочетание совпадает с основным расчётом (результат владельца в режиме) | C20: =ABS(INDEX(D10_I1!C15:F15,1,(N('Входные данные'!$E$37)-1)*2+N('Входные данные'!$E$38))-Сценарии_BEP!$C$45)+ABS(INDEX(D10_I1!C33:F33,1,(N('Входные данные'!$F$37)-1)*2+N('Входные данные'!$F$38))-Сценарии_BEP!$D$45)+ABS(INDEX(D10_I1!C51:F51,1,(N('Входные данные'!$G$37)-1)*2+N('Входные данные'!$G$38))-Сценарии_BEP!$E$45) -> 0 | D20: =IF(C20<0.001,"OK","ОШИБКА") -> OK
A21: C16 | B21: Доли и конверсии лежат в диапазоне 0–100% | C21: =IF(AND(MIN('Входные данные'!E44:G44)>=0,MAX('Входные данные'!E44:G44)<=1,MIN('Входные данные'!E45:G45)>=0,MAX('Входные данные'!E45:G45)<=1,MIN('Входные данные'!E46:G46)>=0,MAX('Входные данные'!E46:G46)<=1,MIN('Входные данные'!E40:G40)>=0,MAX('Входные данные'!E40:G40)<=1,MIN('Входные данные'!E41:G41)>=0,MAX('Входные данные'!E41:G41)<=1,MIN('Входные данные'!E47:G47)>=0,MAX('Входные данные'!E47:G47)<=1,MIN('Входные данные'!E49:G49)>=0,MAX('Входные данные'!E49:G49)<=1,MIN('Входные данные'!E57:G57)>=0,MAX('Входные данные'!E57:G57)<=1,MIN('Входные данные'!E58:G58)>=0,MAX('Входные данные'!E58:G58)<=1,MIN('Входные данные'!E59:G59)>=0,MAX('Входные данные'!E59:G59)<=1,MIN('Входные данные'!E75:G75)>=0,MAX('Входные данные'!E75:G75)<=1,MIN('Входные данные'!E76:G76)>=0,MAX('Входные данные'!E76:G76)<=1,MIN('Входные данные'!E77:G77)>=0,MAX('Входные данные'!E77:G77)<=1,MIN('Входные данные'!E14:G14)>=0,MAX('Входные данные'!E14:G14)<=1,MIN('Входные данные'!E15:G15)>=0,MAX('Входные данные'!E15:G15)<=1,MIN('Входные данные'!E16:G16)>=0,MAX('Входные данные'!E16:G16)<=1),0,1) -> 0 | D21: =IF(C21=0,"OK","ОШИБКА") -> OK
A22: C17 | B22: Переключатели допустимы (метод 1–3, I1 1–2, D10 1–2, часы 1–3, ставка 1–3, НДС 0/1, комиссия KMT 0/1) | C22: =IF(AND(OR('Входные данные'!F26=1,'Входные данные'!F26=2,'Входные данные'!F26=3),OR('Входные данные'!F37=1,'Входные данные'!F37=2),OR('Входные данные'!F38=1,'Входные данные'!F38=2),OR(N('Входные данные'!F65)=0,N('Входные данные'!F65)=1,N('Входные данные'!F65)=2,N('Входные данные'!F65)=3),OR('Входные данные'!F70=1,'Входные данные'!F70=2,'Входные данные'!F70=3),OR(N('Входные данные'!F22)=0,N('Входные данные'!F22)=1),OR(N('Входные данные'!F39)=0,N('Входные данные'!F39)=1)),0,1) -> 0 | D22: =IF(C22=0,"OK","ОШИБКА") -> OK
A23: C18 | B23: Метод 2 выбран, но построчные затраты пусты (прибыль вышла бы 100%) | C23: =IF(AND('Входные данные'!F26=2,'Юнит-экономика'!$D$9=0),1,0) -> 0 | D23: =IF(C23=0,"OK","ОШИБКА") -> OK
A24: C19 | B24: Пустых входов «нужно от Темура» (из 3) | C24: =IF('Входные данные'!F35="",1,0)+IF('Входные данные'!F45="",1,0)+IF('Входные данные'!F56="",1,0) -> 3 | D24: =IF(C24=0,"OK","НЕТ ДАННЫХ") -> НЕТ ДАННЫХ | E24: Список вопросов — лист «Вопросы к Темуру»
A25: C20 | B25: Единицы часов не заданы: труд команды не оценён | C25: =IF(N('Входные данные'!F65)=0,1,0) -> 0 | D25: =IF(C25=0,"OK","НЕТ ДАННЫХ") -> OK
A26: C21 | B26: Единицы часов заданы, а длительность этапа нет: разработка и труд занижены | C26: =IF(AND(N('Входные данные'!F65)>0,N('Входные данные'!F66)<=0),1,0) -> 0 | D26: =IF(C26=0,"OK","НЕТ ДАННЫХ") -> OK
A27: C22 | B27: Ставки не заданы: труд команды = 0 | C27: =IF(AND(N('Входные данные'!F72)=0,N('Входные данные'!F73)=0,N('Входные данные'!F74)=0),1,0) -> 0 | D27: =IF(C27=0,"OK","НЕТ ДАННЫХ") -> OK
A28: C23 | B28: Затраты на разработку не заданы: окупаемость разработки не считается | C28: =IF(Сценарии_BEP!$D$29<=0,1,0) -> 0 | D28: =IF(C28=0,"OK","НЕТ ДАННЫХ") -> OK
A29: C24 | B29: ВНИМАНИЕ: объём расчётов — заглушка (market_sizing.xlsx не подключён) | C29: =IF(LEFT('Входные данные'!D55,10)="[заглушка]",1,0) -> 1 | D29: =IF(C29=0,"OK","ВНИМАНИЕ") -> ВНИМАНИЕ | E29: Все итоги по объёму — иллюстрация, не прогноз
A30: C25 | B30: ВНИМАНИЕ: конверсия интерес → заказ одинакова во всех трёх сценариях | C30: =IF(AND('Входные данные'!E58='Входные данные'!F58,'Входные данные'!F58='Входные данные'!G58),1,0) -> 1 | D30: =IF(C30=0,"OK","ВНИМАНИЕ") -> ВНИМАНИЕ | E30: Разброс сценариев занижен; см. Q5 и таблицы чувствительности
A31: C26 | B31: ВНИМАНИЕ: прибыль заказа по строкам (вопросы 4–5) расходится с прибылью владельца (вопрос 3) | C31: =IF(ABS('Юнит-экономика'!$D$16)>0.05*'Юнит-экономика'!$D$10,1,0) -> 1 | D31: =IF(C31=0,"OK","ВНИМАНИЕ") -> ВНИМАНИЕ | E31: Расхождение 300 тыс. сум; см. Q1
A32: C27 | B32: ВНИМАНИЕ: заказы с сайта упираются в мощность KMT (в одном из сценариев в режиме) | C32: =IF(Воронка!$C$23>0.0001,1,0)+IF(Воронка!$D$23>0.0001,1,0)+IF(Воронка!$E$23>0.0001,1,0) -> 0 | D32: =IF(C32=0,"OK","ВНИМАНИЕ") -> OK | E32: Часть заказов теряется без найма
A33: C28 | B33: ВНИМАНИЕ: I1 = агрегатор при D10 = блок KMT (противоречие) | C33: =IF(AND('Входные данные'!F37=2,'Входные данные'!F38=1),1,0) -> 1 | D33: =IF(C33=0,"OK","ВНИМАНИЕ") -> ВНИМАНИЕ | E33: Блок только с контактами KMT не передаёт заказы партнёрам; решение за владельцем
A34: C29 | B34: ВНИМАНИЕ: труд Темура и Равшана на 100% — разработка (после запуска не считается) | C34: =IF(AND('Входные данные'!F75>=1,'Входные данные'!F76>=1),1,0) -> 1 | D34: =IF(C34=0,"OK","ВНИМАНИЕ") -> ВНИМАНИЕ | E34: См. Q3
B36: Баланс допущений (по статусам строк во «Входные данные»)
B37: [факт] (включая [факт][проверить]) | C37: =SUMPRODUCT(--(LEFT('Входные данные'!D13:D85,6)="[факт]")) -> 43
B38: [гипотеза] (включая [проверить]) | C38: =SUMPRODUCT(--(LEFT('Входные данные'!D13:D85,10)="[гипотеза]")) -> 12
B39: [заглушка] | C39: =SUMPRODUCT(--(LEFT('Входные данные'!D13:D85,10)="[заглушка]")) -> 2
B40: нужно от Темура | C40: =SUMPRODUCT(--(LEFT('Входные данные'!D13:D85,15)="нужно от Темура")) -> 3
B41: [выбор] | C41: =SUMPRODUCT(--(LEFT('Входные данные'!D13:D85,7)="[выбор]")) -> 4
B42: Всего параметров | C42: =SUM(C37:C41) -> 64 | D42: =IF(C42=64,"OK","ОШИБКА") -> OK | E42: Сумма по статусам должна равняться числу параметров
B43: Драйверы дохода (объём, c1, c2, инкрементальность, прибыль заказа): из них [факт] | C43: =IF(LEFT('Входные данные'!D55,6)="[факт]",1,0)+IF(LEFT('Входные данные'!D57,6)="[факт]",1,0)+IF(LEFT('Входные данные'!D58,6)="[факт]",1,0)+IF(LEFT('Входные данные'!D59,6)="[факт]",1,0)+IF(LEFT('Входные данные'!D27,6)="[факт]",1,0) -> 1 | E43: из 5: основной вывод модели держится на гипотезах и заглушке объёма
B45: Граничные случаи (прогон скриптом при создании файла; каждый — отдельная копия книги с пересчётом)
A46: № | B46: Случай | C46: Ошибок формул | D46: Результат | E46: Что показали
A47: T01 | B47: Ответы владельца 18.10.2026 как есть | C47: 0 | D47: OK | E47: Результат владельца в режиме, млн сум/мес (пессимист / база / оптимист): -8.64 / -8.24 / -5.92. Ошибок формул нет, проверки не нарушены.
A48: T02 | B48: Прибыль заказа = 0 во всех сценариях | C48: 0 | D48: OK | E48: Результат владельца в режиме, млн сум/мес (пессимист / база / оптимист): -8.70 / -8.56 / -8.04. Ошибок формул нет, проверки не нарушены.
A49: T03 | B49: Конверсия расчёт → интерес = 0 | C49: 0 | D49: OK | E49: Результат владельца в режиме, млн сум/мес (пессимист / база / оптимист): -8.75 / -8.75 / -8.75. Ошибок формул нет, проверки не нарушены.
A50: T04 | B50: Расчётов уровня 1 в месяц = 0 | C50: 0 | D50: OK | E50: Результат владельца в режиме, млн сум/мес (пессимист / база / оптимист): -8.75 / -8.75 / -8.75. Ошибок формул нет, проверки не нарушены.
A51: T05 | B51: Потолок привлечения = 0 | C51: 0 | D51: OK | E51: Результат владельца в режиме, млн сум/мес (пессимист / база / оптимист): -8.64 / -8.24 / -5.92. Ошибок формул нет, проверки не нарушены.
A52: T06 | B52: Доли цены обнулены (цена = 0) | C52: 0 | D52: OK | E52: Результат владельца в режиме, млн сум/мес (пессимист / база / оптимист): -8.64 / -8.24 / -5.92. Проверка C09 сработала, как и должна.
A53: T07 | B53: Метод прибыли 2 (построчно) | C53: 0 | D53: OK | E53: Результат владельца в режиме, млн сум/мес (пессимист / база / оптимист): -8.56 / -7.98 / -5.85. Ошибок формул нет, проверки не нарушены.
A54: T08 | B54: Метод прибыли 1 (процент) | C54: 0 | D54: OK | E54: Результат владельца в режиме, млн сум/мес (пессимист / база / оптимист): -8.64 / -8.15 / -6.49. Ошибок формул нет, проверки не нарушены.
A55: T09 | B55: НДС включён, ставка 12% (тестовое значение, не факт) | C55: 0 | D55: OK | E55: Результат владельца в режиме, млн сум/мес (пессимист / база / оптимист): -8.64 / -8.24 / -5.92. Ошибок формул нет, проверки не нарушены.
A56: T10 | B56: Длительность этапа = 0 | C56: 0 | D56: OK | E56: Результат владельца в режиме, млн сум/мес (пессимист / база / оптимист): -8.64 / -8.24 / -5.92. Ошибок формул нет, проверки не нарушены.
A57: T11 | B57: Единицы часов не заданы | C57: 0 | D57: OK | E57: Результат владельца в режиме, млн сум/мес (пессимист / база / оптимист): -7.39 / -6.99 / -4.67. Ошибок формул нет, проверки не нарушены.
A58: T12 | B58: Ставка — сум за час (100 000) | C58: 0 | D58: OK | E58: Результат владельца в режиме, млн сум/мес (пессимист / база / оптимист): -11.73 / -11.32 / -9.00. Ошибок формул нет, проверки не нарушены.
... A77: T31 | B77: Нарушение границ: сумма долей цены ≠ 100% | C77: 0 | D77: OK | E77: Результат владельца в режиме, млн сум/мес (пессимист / база / оптимист): -8.64 / -8.24 / -5.92. Проверка C09 сработала, как и должна.
